[{"id":"121101","changeuuid":"e184aada-47f4-11e9-aa55-52543be04c81","stationuuid":"e184aaca-47f4-11e9-aa55-52543be04c81","name":"904","url":"http://icecast.902.gr:8000/904.m3u","homepage":"http://icecast.902.gr:8000/904.m3u","favicon":"http://icecast.902.gr:8000/favicon.ico","tags":"","country":"Greece, Ελλάδα","state":"","language":"","votes":"3","negativevotes":"0","lastchangetime":"2019-03-16 15:07:50","ip":"2a02:908:694:2d60::16a","codec":"MP3","bitrate":"128","hls":"0","lastcheckok":"1","lastchecktime":"2019-07-01 11:15:06","lastcheckoktime":"2019-07-01 11:15:06","clicktimestamp":"2019-07-13 04:31:16","clickcount":"0","clicktrend":"0"},{"id":"123074","changeuuid":"95909090-6f25-11e9-af37-52543be04c81","stationuuid":"9590907f-6f25-11e9-af37-52543be04c81","name":"Akous Palko (Greek Radio)","url":"http://live.akous.gr/akouspalko","homepage":"http://www.akous.gr/player/palko","favicon":"http://www.akous.gr/logos/akous_palko_2.png","tags":"","country":"Greece, Ελλάδα","state":"Athens","language":"Greek","votes":"9","negativevotes":"0","lastchangetime":"2019-05-05 13:04:42","ip":"2a02:2788:4c4:528:f070:ed6a:876f:2fb9","codec":"MP3","bitrate":"128","hls":"0","lastcheckok":"1","lastchecktime":"2019-07-02 09:54:52","lastcheckoktime":"2019-07-02 09:54:52","clicktimestamp":"2019-07-13 07:51:13","clickcount":"0","clicktrend":"0"},{"id":"121633","changeuuid":"700551af-594c-11e9-a622-52543be04c81","stationuuid":"700551a0-594c-11e9-a622-52543be04c81","name":"Athina 9.84","url":"http://athina984.live24.gr/athina984","homepage":"","favicon":"","tags":"","country":"Greece, Ελλάδα","state":"","language":"greek (ελληνικά)","votes":"1","negativevotes":"0","lastchangetime":"2019-04-07 17:47:24","ip":"37.153.147.249","codec":"MP3","bitrate":"128","hls":"0","lastcheckok":"1","lastchecktime":"2019-07-01 12:39:25","lastcheckoktime":"2019-07-01 12:39:25","clicktimestamp":"2019-07-08 03:43:34","clickcount":"0","clicktrend":"0"},{"id":"120785","changeuuid":"56212611-3ec6-11e9-aa55-52543be04c81","stationuuid":"56212605-3ec6-11e9-aa55-52543be04c81","name":"Church of Piraeus 91.2","url":"http://136.243.61.157:8310","homepage":"http://peradio.com/","favicon":"https://www.peradio.com/wp-content/uploads/2018/11/logo.png","tags":"ιερά μητρόπολις,εκκλησία,ορθοδοξία,ecclesia,greek,orthodoxy,orthodox christian,byzantine","country":"Greece, Ελλάδα","state":"Pireaus (Greece)","language":"Greek (Ελληνικά)","votes":"179","negativevotes":"0","lastchangetime":"2019-03-04 22:41:59","ip":"2.84.1.203","codec":"MP3","bitrate":"96","hls":"0","lastcheckok":"1","lastchecktime":"2019-07-02 07:39:32","lastcheckoktime":"2019-07-02 07:39:32","clicktimestamp":"2019-07-13 07:55:11","clickcount":"0","clicktrend":"0"},{"id":"123831","changeuuid":"0e5fdeaf-7b19-11e9-aa30-52543be04c81","stationuuid":"0e5fdea5-7b19-11e9-aa30-52543be04c81","name":"e-Ροή (e-roi.gr - Ενιαίο Παλλαϊκό Μέτωπο)","url":"http://217.147.94.171:23963/;stream.mp3","homepage":"http://www.e-roi.gr","favicon":"http://e-roi.gr/eroi.jpg","tags":"ειδήσεις,πολιτική,ελληνική-μουσική,talk radio,talk,politics,news","country":"Greece, Ελλάδα","state":"","language":"Greek","votes":"4","negativevotes":"0","lastchangetime":"2019-05-20 18:05:15","ip":"109.242.33.174","codec":"MP3","bitrate":"128","hls":"0","lastcheckok":"1","lastchecktime":"2019-07-02 10:11:20","lastcheckoktime":"2019-07-02 10:11:20","clicktimestamp":"2019-07-07 14:07:05","clickcount":"0","clicktrend":"0"},{"id":"121106","changeuuid":"70145518-47f5-11e9-aa55-52543be04c81","stationuuid":"70145509-47f5-11e9-aa55-52543be04c81","name":"ERTOPEN","url":"http://live.thegreekradio.com/erasport.pls","homepage":"http://live.thegreekradio.com/erasport.pls","favicon":"http://live.thegreekradio.com/favicon.ico","tags":"","country":"Greece, Ελλάδα","state":"","language":"","votes":"2","negativevotes":"0","lastchangetime":"2019-03-16 15:11:49","ip":"2a02:908:694:2d60::16a","codec":"UNKNOWN","bitrate":"0","hls":"0","lastcheckok":"1","lastchecktime":"2019-07-02 11:01:35","lastcheckoktime":"2019-07-02 11:01:35","clicktimestamp":"2019-07-07 14:07:08","clickcount":"0","clicktrend":"0"},{"id":"121107","changeuuid":"b602e490-47f5-11e9-aa55-52543be04c81","stationuuid":"b602e47c-47f5-11e9-aa55-52543be04c81","name":"FM 102 Thessaloniki","url":"http://radiostreaming.ert.gr/ert-102fm","homepage":"http://radiostreaming.ert.gr/ert-102fm","favicon":"","tags":"","country":"Greece, Ελλάδα","state":"","language":"","votes":"3","negativevotes":"0","lastchangetime":"2019-03-16 15:13:46","ip":"2a02:908:694:2d60::16a","codec":"MP3","bitrate":"128","hls":"0","lastcheckok":"1","lastchecktime":"2019-07-01 11:13:47","lastcheckoktime":"2019-07-01 11:13:47","clicktimestamp":"2019-07-07 14:07:11","clickcount":"0","clicktrend":"0"},{"id":"120746","changeuuid":"8ee23149-3e97-11e9-aa55-52543be04c81","stationuuid":"8ee23138-3e97-11e9-aa55-52543be04c81","name":"Lydia 94.2 Fm (Λυδία η Φιλιππησία)","url":"http://82.192.84.30:1086/","homepage":"http://www.radiolydia.com/","favicon":"http://www.radiolydia.com/favicon.ico","tags":"greek,ορθοδοξία,orthodox christian,orthodoxy,orthodox","country":"Greece, Ελλάδα","state":"Thessaloniki","language":"Greek (Ελληνικά)","votes":"93","negativevotes":"0","lastchangetime":"2019-03-04 17:07:07","ip":"2a02:582:1cea:a800:f518:f41d:6a1c:65e3","codec":"MP3","bitrate":"128","hls":"0","lastcheckok":"1","lastchecktime":"2019-07-01 12:41:13","lastcheckoktime":"2019-07-01 12:41:13","clicktimestamp":"2019-07-13 07:56:27","clickcount":"0","clicktrend":"0"},{"id":"122377","changeuuid":"64a903fc-6354-11e9-a622-52543be04c81","stationuuid":"64a903ea-6354-11e9-a622-52543be04c81","name":"Parapolitika","url":"http://netradio.live24.gr:80/athinaradio","homepage":"","favicon":"","tags":"","country":"Greece, Ελλάδα","state":"","language":"greek (ελληνικά)","votes":"8","negativevotes":"0","lastchangetime":"2019-04-20 12:09:33","ip":"2a00:23c4:1215:7d00:71c4:ae9e:3b35:ead","codec":"MP3","bitrate":"128","hls":"0","lastcheckok":"1","lastchecktime":"2019-07-02 08:31:04","lastcheckoktime":"2019-07-02 08:31:04","clicktimestamp":"2019-07-13 12:49:10","clickcount":"0","clicktrend":"0"},{"id":"120744","changeuuid":"95c47887-3e95-11e9-aa55-52543be04c81","stationuuid":"95c47879-3e95-11e9-aa55-52543be04c81","name":"Radio Filopoli","url":"http://147.135.252.4:10043/","homepage":"http://filopoli-webmagazine.blogspot.gr","favicon":"https://filopoli-webmagazine.blogspot.com/favicon.ico","tags":"ορθοδοξία,greek,orthodox","country":"Greece, Ελλάδα","state":"","language":"Greek","votes":"69","negativevotes":"0","lastchangetime":"2019-03-04 16:53:00","ip":"2a02:582:1cea:a800:f518:f41d:6a1c:65e3","codec":"","bitrate":"0","hls":"0","lastcheckok":"0","lastchecktime":"2019-07-02 10:23:56","lastcheckoktime":"2019-06-21 17:20:53","clicktimestamp":"2019-06-27 15:16:34","clickcount":"0","clicktrend":"0"},{"id":"124056","changeuuid":"67a82eb3-8079-11e9-aa30-52543be04c81","stationuuid":"67a82ea4-8079-11e9-aa30-52543be04c81","name":"Thessradio","url":"http://noc.ezhellas.com:30570/zbutsam?1558953137492","homepage":"http://thessradio.net","favicon":"http://thessradio.net/wp-content/uploads/2019/04/cropped--270x270.jpg","tags":"","country":"Greece, Ελλάδα","state":"Thessaloniki","language":"greek","votes":"3","negativevotes":"0","lastchangetime":"2019-05-27 14:17:33","ip":"2.86.224.65","codec":"MP3","bitrate":"128","hls":"0","lastcheckok":"1","lastchecktime":"2019-07-02 07:40:01","lastcheckoktime":"2019-07-02 07:40:01","clicktimestamp":"2019-07-08 09:55:54","clickcount":"0","clicktrend":"0"},{"id":"120748","changeuuid":"f56adbf6-3e9d-11e9-aa55-52543be04c81","stationuuid":"f56adbeb-3e9d-11e9-aa55-52543be04c81","name":"Άγιος Οικουμένιος 102","url":"http://s5.onweb.gr:8508/","homepage":"http://imtks.gr/","favicon":"http://imtks.gr//favicon.ico","tags":"ecclesia,orthodoxy,ιερά μητρόπολις,ορθοδοξία,greek,orthodox christian","country":"Greece, Ελλάδα","state":"Trikala (Greece)","language":"Greek (Ελληνικά)","votes":"76","negativevotes":"0","lastchangetime":"2019-03-04 17:52:56","ip":"2a02:582:1cea:a800:f518:f41d:6a1c:65e3","codec":"MP3","bitrate":"64","hls":"0","lastcheckok":"1","lastchecktime":"2019-07-02 11:05:51","lastcheckoktime":"2019-07-02 11:05:51","clicktimestamp":"2019-07-11 17:42:33","clickcount":"0","clicktrend":"0"},{"id":"120750","changeuuid":"69843a91-3ea0-11e9-aa55-52543be04c81","stationuuid":"69843a86-3ea0-11e9-aa55-52543be04c81","name":"Αλήθεια FM 96.3","url":"http://sc2.streamwithq.com:8070","homepage":"http://www.alithiafm.gr/","favicon":"http://www.alithiafm.gr/templates/alithiafm-template/images/alithiafm_logo.png","tags":"ecclesia,ορθοδοξία,εκκλησία,greek,orthodoxy,orthodox christian","country":"Greece, Ελλάδα","state":"Kalymnos","language":"Greek (Ελληνικά)","votes":"70","negativevotes":"0","lastchangetime":"2019-03-04 18:10:30","ip":"2a02:582:1cea:a800:f518:f41d:6a1c:65e3","codec":"MP3","bitrate":"256","hls":"0","lastcheckok":"1","lastchecktime":"2019-07-02 10:45:38","lastcheckoktime":"2019-07-02 10:45:38","clicktimestamp":"2019-07-13 08:01:02","clickcount":"0","clicktrend":"0"},{"id":"120751","changeuuid":"e4da502b-3ea1-11e9-aa55-52543be04c81","stationuuid":"e4da5017-3ea1-11e9-aa55-52543be04c81","name":"Βοιωτική Εκκλησία 99.2","url":"http://78.129.163.129:5957/","homepage":"https://viotikiekklisia.blogspot.com/","favicon":"https://3.bp.blogspot.com/-8_jo40hLZC0/WSaZdfBxOHI/AAAAAAAAA7U/f-8eB3XzktI9wHgPyLjKR9VFeMhib-GFwCK4B/s120-pf/10403180_862085383851132_6585050971837782390_n.jpg","tags":"ecclesia,εκκλησία,ορθοδοξία,greek,orthodoxy,orthodox christian","country":"Greece, Ελλάδα","state":"Βοιωτία","language":"Greek (Ελληνικά)","votes":"69","negativevotes":"0","lastchangetime":"2019-03-04 18:21:07","ip":"2a02:582:1cea:a800:f518:f41d:6a1c:65e3","codec":"MP3","bitrate":"96","hls":"0","lastcheckok":"1","lastchecktime":"2019-07-02 07:27:08","lastcheckoktime":"2019-07-02 07:27:08","clicktimestamp":"2019-07-11 17:48:14","clickcount":"0","clicktrend":"0"},{"id":"120753","changeuuid":"6aa91844-3ea8-11e9-aa55-52543be04c81","stationuuid":"6aa91836-3ea8-11e9-aa55-52543be04c81","name":"Διακονία 93.8","url":"http://193.92.70.63:8081/broadwavehigh.mp3?src=2/","homepage":"https://im-xanthis.gr/","favicon":"https://im-xanthis.gr/wp-content/uploads/2018/07/logo.png","tags":"ecclesia,εκκλησία,ιερά μητρόπολις,greek,orthodoxy,orthodox christian","country":"Greece, Ελλάδα","state":"Ξάνθη","language":"Greek (Ελληνικά)","votes":"33","negativevotes":"0","lastchangetime":"2019-03-04 19:07:48","ip":"2a02:582:1cea:a800:f518:f41d:6a1c:65e3","codec":"MP3","bitrate":"0","hls":"0","lastcheckok":"1","lastchecktime":"2019-07-01 12:44:45","lastcheckoktime":"2019-07-01 12:44:45","clicktimestamp":"2019-07-10 23:38:24","clickcount":"0","clicktrend":"0"},{"id":"120814","changeuuid":"9e858210-3f73-11e9-aa55-52543be04c81","stationuuid":"9e858206-3f73-11e9-aa55-52543be04c81","name":"Εκκλησία της Ελλάδος 89.5","url":"http://85.10.206.222:8002/","homepage":"http://www.ecclesia.gr","favicon":"http://www.ecclesia.gr/greek/ecclesiaradio/images/final_03.gif","tags":"religious,εκκλησία,ορθοδοξία,byzantine,greek,ecclesia,orthodoxy,orthodox christian","country":"Greece, Ελλάδα","state":"Attica","language":"Greek","votes":"207","negativevotes":"0","lastchangetime":"2019-03-05 19:22:23","ip":"2.84.1.203","codec":"MP3","bitrate":"96","hls":"0","lastcheckok":"1","lastchecktime":"2019-07-01 12:57:46","lastcheckoktime":"2019-07-01 12:57:46","clicktimestamp":"2019-07-13 07:53:41","clickcount":"0","clicktrend":"0"},{"id":"120754","changeuuid":"111407d0-3ea9-11e9-aa55-52543be04c81","stationuuid":"111407c4-3ea9-11e9-aa55-52543be04c81","name":"Ι. Αρχιεπισκοπή Κρήτης / Το Φως 99.7","url":"http://s1.onweb.gr:8432","homepage":"http://www.iak.gr/","favicon":"http://www.iak.gr/favicon.ico","tags":"εκκλησία,ιερά μητρόπολις,ορθοδοξία,greek,ecclesia,orthodoxy,orthodox christian","country":"Greece, Ελλάδα","state":"Crete","language":"Greek (Ελληνικά)","votes":"73","negativevotes":"0","lastchangetime":"2019-03-04 19:12:27","ip":"2a02:582:1cea:a800:f518:f41d:6a1c:65e3","codec":"MP3","bitrate":"32","hls":"0","lastcheckok":"1","lastchecktime":"2019-07-02 06:53:38","lastcheckoktime":"2019-07-02 06:53:38","clicktimestamp":"2019-07-11 17:45:47","clickcount":"0","clicktrend":"0"},{"id":"120755","changeuuid":"8df8a114-3ea9-11e9-aa55-52543be04c81","stationuuid":"8df8a104-3ea9-11e9-aa55-52543be04c81","name":"Ι. Μητρ. Λαρίσης και Τυρνάβου 96.3","url":"http://s1.onweb.gr:8004","homepage":"http://www.imlarisis.gr/","favicon":"https://imlarisis.gr/wp-content/uploads/2016/02/cropped-cropped-logo-all-3-1-1-300x300-192x192.png","tags":"εκκλησία,ιερά μητρόπολις,ορθοδοξία,ecclesia,greek,orthodoxy,orthodox christian","country":"Greece, Ελλάδα","state":"Larissa","language":"Greek (Ελληνικά)","votes":"88","negativevotes":"0","lastchangetime":"2019-03-04 19:15:57","ip":"2a02:582:1cea:a800:f518:f41d:6a1c:65e3","codec":"MP3","bitrate":"32","hls":"0","lastcheckok":"1","lastchecktime":"2019-07-02 08:27:21","lastcheckoktime":"2019-07-02 08:27:21","clicktimestamp":"2019-07-13 07:54:06","clickcount":"0","clicktrend":"0"},{"id":"120756","changeuuid":"1fbbecc0-3eaa-11e9-aa55-52543be04c81","stationuuid":"1fbbecaa-3eaa-11e9-aa55-52543be04c81","name":"Ι. Μητρ. Πατρών 88.4","url":"http://eco.onestreaming.com:8468/","homepage":"http://www.i-m-patron.gr","favicon":"http://i-m-patron.gr/wp-content/uploads/2015/10/imp-logo-image.png","tags":"ιερά μητρόπολις,εκκλησία,ορθοδοξία,ecclesia,greek,orthodoxy,orthodox christian,byzantine","country":"Greece, Ελλάδα","state":"Patra","language":"Greek (Ελληνικά)","votes":"76","negativevotes":"0","lastchangetime":"2019-03-04 19:20:01","ip":"2a02:582:1cea:a800:f518:f41d:6a1c:65e3","codec":"MP3","bitrate":"32","hls":"0","lastcheckok":"1","lastchecktime":"2019-07-02 10:53:25","lastcheckoktime":"2019-07-02 10:53:25","clicktimestamp":"2019-07-11 17:43:34","clickcount":"0","clicktrend":"0"},{"id":"120761","changeuuid":"00e61a05-3ead-11e9-aa55-52543be04c81","stationuuid":"00e619f2-3ead-11e9-aa55-52543be04c81","name":"Ι. Μητρ. Χαλκίδος 97.7 Ο ΑΓΙΟΣ ΤΙΜΟΘΕΟΣ ΕΥΡΙΠΟΥ","url":"http://85.10.206.222:8010/stream","homepage":"http://radioimchalk.blogspot.gr/","favicon":"https://4.bp.blogspot.com/-maaDFSFgYY8/UylkuiTifzI/AAAAAAAABTs/oIE3OYGxYRo/s246/Logo.png","tags":"ιερά μητρόπολις,εκκλησία,ορθοδοξία,greek,ecclesia,orthodoxy,orthodox christian,byzantine","country":"Greece, Ελλάδα","state":"Chalkida Evia","language":"Greek (Ελληνικά)","votes":"75","negativevotes":"0","lastchangetime":"2019-03-04 19:40:38","ip":"2a02:582:1cea:a800:f518:f41d:6a1c:65e3","codec":"MP3","bitrate":"96","hls":"0","lastcheckok":"1","lastchecktime":"2019-07-02 07:44:19","lastcheckoktime":"2019-07-02 07:44:19","clicktimestamp":"2019-07-13 01:14:11","clickcount":"0","clicktrend":"0"},{"id":"120757","changeuuid":"de6ac85b-3eaa-11e9-aa55-52543be04c81","stationuuid":"de6ac84d-3eaa-11e9-aa55-52543be04c81","name":"Ι.Μ. Αιτωλίας και Ακαρνανίας 106.3","url":"http://136.243.61.157:8048","homepage":"http://www.radioimaa.gr/","favicon":"http://www.radioimaa.gr/templates/t_radio2/images/object2140786898.png","tags":"ιερά μητρόπολις,εκκλησία,ορθοδοξία,ecclesia,greek,orthodoxy,orthodox christian,byzantine","country":"Greece, Ελλάδα","state":"Etolia Akarnania","language":"Greek (Ελληνικά)","votes":"74","negativevotes":"0","lastchangetime":"2019-03-04 19:25:21","ip":"2a02:582:1cea:a800:f518:f41d:6a1c:65e3","codec":"MP3","bitrate":"128","hls":"0","lastcheckok":"1","lastchecktime":"2019-07-02 10:24:17","lastcheckoktime":"2019-07-02 10:24:17","clicktimestamp":"2019-07-11 17:44:35","clickcount":"0","clicktrend":"0"},{"id":"120759","changeuuid":"9022751a-3eab-11e9-aa55-52543be04c81","stationuuid":"90227508-3eab-11e9-aa55-52543be04c81","name":"Ι.Μ. Παροναξίας 92.3","url":"http://s6.onweb.gr:8080","homepage":"http://www.i-m-paronaxias.gr/","favicon":"http://www.i-m-paronaxias.gr/paronaxia/templates/j51_oxygen/images/logo.png","tags":"ιερά μητρόπολις,εκκλησία,εκκλησία,ορθοδοξία,ecclesia,greek,orthodoxy,orthodox christian,byzantine","country":"Greece, Ελλάδα","state":"Paros Naxos (Greece)","language":"Greek (Ελληνικά)","votes":"68","negativevotes":"0","lastchangetime":"2019-03-04 19:30:20","ip":"2a02:582:1cea:a800:f518:f41d:6a1c:65e3","codec":"AAC","bitrate":"64","hls":"0","lastcheckok":"1","lastchecktime":"2019-07-02 09:54:55","lastcheckoktime":"2019-07-02 09:54:55","clicktimestamp":"2019-07-13 12:39:29","clickcount":"0","clicktrend":"0"},{"id":"120760","changeuuid":"38577c0e-3eac-11e9-aa55-52543be04c81","stationuuid":"38577bf8-3eac-11e9-aa55-52543be04c81","name":"Ι.Μ. Σπάρτης 88.8","url":"http://s4.onweb.gr:8862/","homepage":"http://www.immspartis.gr/","favicon":"http://www.immspartis.gr/wp-content/themes/church_40/images/favicon.ico","tags":"ιερά μητρόπολις,εκκλησία,ορθοδοξία,ecclesia,greek,orthodoxy,orthodox christian","country":"Greece, Ελλάδα","state":"Sparta","language":"Greek (Ελληνικά)","votes":"75","negativevotes":"0","lastchangetime":"2019-03-04 19:35:02","ip":"2a02:582:1cea:a800:f518:f41d:6a1c:65e3","codec":"MP3","bitrate":"64","hls":"0","lastcheckok":"1","lastchecktime":"2019-07-01 11:51:17","lastcheckoktime":"2019-07-01 11:51:17","clicktimestamp":"2019-07-12 08:37:19","clickcount":"0","clicktrend":"0"},{"id":"120762","changeuuid":"c7e426d8-3ead-11e9-aa55-52543be04c81","stationuuid":"c7e426c8-3ead-11e9-aa55-52543be04c81","name":"Ιερά Μητροπόλη Φθιώτιδος 89.4","url":"http://eco.onestreaming.com:8264","homepage":"http://www.imfth.gr/","favicon":"http://www.imfth.gr/sites/all/themes/zircon/logo-fb.jpg","tags":"ιερά μητρόπολις,εκκλησία,ορθοδοξία,ecclesia,greek,orthodoxy,orthodox christian","country":"Greece, Ελλάδα","state":"Lamia (Greece)","language":"Greek (Ελληνικά)","votes":"79","negativevotes":"0","lastchangetime":"2019-03-04 19:46:12","ip":"2a02:582:1cea:a800:f518:f41d:6a1c:65e3","codec":"MP3","bitrate":"64","hls":"0","lastcheckok":"1","lastchecktime":"2019-07-01 14:16:30","lastcheckoktime":"2019-07-01 14:16:30","clicktimestamp":"2019-07-11 17:42:18","clickcount":"0","clicktrend":"0"},{"id":"120764","changeuuid":"61821a1c-3eae-11e9-aa55-52543be04c81","stationuuid":"61821a11-3eae-11e9-aa55-52543be04c81","name":"Ιερά Μητρόπολις Άρτης 106.6","url":"http://i.streams.ovh:9566/live","homepage":"http://www.imartis.gr/","favicon":"http://www.imartis.gr/images/v2/logo_no_text_black.png","tags":"ιερά μητρόπολις,εκκλησία,ορθοδοξία,ecclesia,greek,orthodoxy,orthodox christian,byzantine","country":"Greece, Ελλάδα","state":"Arta (Greece)","language":"Greek (Ελληνικά)","votes":"71","negativevotes":"0","lastchangetime":"2019-03-04 19:50:30","ip":"2a02:582:1cea:a800:f518:f41d:6a1c:65e3","codec":"MP3","bitrate":"320","hls":"0","lastcheckok":"1","lastchecktime":"2019-07-01 11:46:20","lastcheckoktime":"2019-07-01 11:46:20","clicktimestamp":"2019-07-11 17:47:11","clickcount":"0","clicktrend":"0"},{"id":"120745","changeuuid":"a5d4c366-3e96-11e9-aa55-52543be04c81","stationuuid":"a5d4c355-3e96-11e9-aa55-52543be04c81","name":"Ιερά Μονή Παμμεγίστων Ταξιαρχών","url":"http://eco.onestreaming.com:8019/","homepage":"http://www.impt.gr/","favicon":"http://www.impt.gr/favicon.jpg","tags":"monastery,ιερά μονή,greek,χριστιανισμός,christian,orthodox,ορθοδοξία","country":"Greece, Ελλάδα","state":"Μαγνησία (Greece)","language":"Greek (Ελληνικά)","votes":"87","negativevotes":"0","lastchangetime":"2019-03-04 17:00:36","ip":"2a02:582:1cea:a800:f518:f41d:6a1c:65e3","codec":"MP3","bitrate":"24","hls":"0","lastcheckok":"1","lastchecktime":"2019-07-01 11:25:16","lastcheckoktime":"2019-07-01 11:25:16","clicktimestamp":"2019-07-13 07:56:48","clickcount":"0","clicktrend":"0"},{"id":"120765","changeuuid":"0d2e63a3-3eaf-11e9-aa55-52543be04c81","stationuuid":"0d2e6395-3eaf-11e9-aa55-52543be04c81","name":"Μητρόπολη Κομοτηνής 95.8","url":"http://ice.streamcloud.mediacdn.com:80/imkomotini","homepage":"http://immaroniaskomotinis.gr/","favicon":"http://immaroniaskomotinis.gr/wp-content/themes/belief/fb_screenshot.png","tags":"ιερά μητρόπολις,εκκλησία,ορθοδοξία,ecclesia,greek,orthodoxy,orthodox christian","country":"Greece, Ελλάδα","state":"Komotini (Greece)","language":"Greek (Ελληνικά)","votes":"71","negativevotes":"0","lastchangetime":"2019-03-04 19:55:18","ip":"2a02:582:1cea:a800:f518:f41d:6a1c:65e3","codec":"MP3","bitrate":"64","hls":"0","lastcheckok":"1","lastchecktime":"2019-07-02 09:53:37","lastcheckoktime":"2019-07-02 09:53:37","clicktimestamp":"2019-07-11 17:47:23","clickcount":"0","clicktrend":"0"},{"id":"120766","changeuuid":"9a7979c8-3eaf-11e9-aa55-52543be04c81","stationuuid":"9a7979b5-3eaf-11e9-aa55-52543be04c81","name":"Μοναδική Πολιτεία 96 - Αδελφότης Μεταμορφώσεως του Σωτήρος Ναυπάκτου","url":"http://mp96fm.live24.gr:80/monadikipolitia96","homepage":"http://www.mp96fm.gr/","favicon":"http://www.mp96fm.gr/mp96fm.png","tags":"ιερά μονή,εκκλησία,ορθοδοξία,greek,ecclesia,orthodoxy,orthodox christian,byzantine","country":"Greece, Ελλάδα","state":"Nafpaktos (Greece)","language":"Greek (Ελληνικά)","votes":"71","negativevotes":"0","lastchangetime":"2019-03-04 19:59:15","ip":"2.84.1.203","codec":"MP3","bitrate":"64","hls":"0","lastcheckok":"1","lastchecktime":"2019-07-02 07:27:37","lastcheckoktime":"2019-07-02 07:27:37","clicktimestamp":"2019-07-11 17:46:55","clickcount":"0","clicktrend":"0"},{"id":"120768","changeuuid":"8e5e1603-3eb0-11e9-aa55-52543be04c81","stationuuid":"8e5e15f0-3eb0-11e9-aa55-52543be04c81","name":"Ο Εύδιος Λιμήν 101.9","url":"http://eco.onestreaming.com:8650/","homepage":"http://www.imga.gr/","favicon":"http://www.imga.gr/wp-content/uploads/2015/10/cropped-Logo_imga-270x270.jpg","tags":"ιερά μητρόπολις,εκκλησία,ορθοδοξία,greek,ecclesia,orthodoxy,orthodox christian","country":"Greece, Ελλάδα","state":"Mires Crete","language":"Greek (Ελληνικά)","votes":"68","negativevotes":"0","lastchangetime":"2019-03-04 20:06:04","ip":"2a02:582:1cea:a800:f518:f41d:6a1c:65e3","codec":"MP3","bitrate":"128","hls":"0","lastcheckok":"1","lastchecktime":"2019-07-02 10:11:11","lastcheckoktime":"2019-07-02 10:11:11","clicktimestamp":"2019-07-11 17:49:33","clickcount":"0","clicktrend":"0"},{"id":"120769","changeuuid":"2faa33b4-3eb1-11e9-aa55-52543be04c81","stationuuid":"2faa33aa-3eb1-11e9-aa55-52543be04c81","name":"Ορθόδοξη Μαρτυρία 104.0","url":"http://streamyourdream.org:8042/imd","homepage":"http://orthodoximartyria.blogspot.gr/","favicon":"https://3.bp.blogspot.com/-HMde8zU-x7A/TxQCKi4GL6I/AAAAAAAAAAc/pdJY0f_ycbE/s1600/imdradio.JPG","tags":"ιερά μητρόπολις,εκκλησία,ορθοδοξία,greek,ecclesia,orthodoxy,orthodox christian","country":"Greece, Ελλάδα","state":"Melissiatika (Greece)","language":"Greek (Ελληνικά)","votes":"67","negativevotes":"0","lastchangetime":"2019-03-04 20:10:35","ip":"2a02:582:1cea:a800:f518:f41d:6a1c:65e3","codec":"MP3","bitrate":"128","hls":"0","lastcheckok":"1","lastchecktime":"2019-07-01 14:33:57","lastcheckoktime":"2019-07-01 14:33:57","clicktimestamp":"2019-07-10 23:16:32","clickcount":"0","clicktrend":"0"},{"id":"120770","changeuuid":"316e6116-3eb3-11e9-aa55-52543be04c81","stationuuid":"316e610b-3eb3-11e9-aa55-52543be04c81","name":"Ορθόδοξη Παρουσία 106.8","url":"http://www.gwebstream.net:8008/stream","homepage":"http://www.imlagada.gr/","favicon":"http://www.imlagada.gr/UsersFiles/admin/images/logo.png","tags":"ιερά μητρόπολις,εκκλησία,ορθοδοξία,ecclesia,greek,orthodoxy,orthodox christian,byzantine","country":"Greece, Ελλάδα","state":"Laggadas (Macedonia Greece)","language":"Greek (Ελληνικά)","votes":"71","negativevotes":"0","lastchangetime":"2019-03-04 20:24:57","ip":"2a02:582:1cea:a800:f518:f41d:6a1c:65e3","codec":"MP3","bitrate":"128","hls":"0","lastcheckok":"1","lastchecktime":"2019-07-01 12:57:47","lastcheckoktime":"2019-07-01 12:57:47","clicktimestamp":"2019-07-13 07:54:40","clickcount":"0","clicktrend":"0"},{"id":"120773","changeuuid":"ea38834e-3ebe-11e9-aa55-52543be04c81","stationuuid":"ea388340-3ebe-11e9-aa55-52543be04c81","name":"Ορθοδοξία και Παράδοση 103","url":"http://radio.lts-group.eu:52390/ANS","homepage":"http://siatistaagiosnikolaos.gr/","favicon":"https://siatistaagiosnikolaos.files.wordpress.com/2011/10/orthodox1.jpg?w=160","tags":"εκκλησία,ορθοδοξία,greek,byzantine,ecclesia,orthodoxy,orthodox christian","country":"Greece, Ελλάδα","state":"Siatista (Greece)","language":"Greek (Ελληνικά)","votes":"71","negativevotes":"0","lastchangetime":"2019-03-04 21:48:51","ip":"2a02:582:1cea:a800:f518:f41d:6a1c:65e3","codec":"MP3","bitrate":"128","hls":"0","lastcheckok":"1","lastchecktime":"2019-07-02 09:00:23","lastcheckoktime":"2019-07-02 09:00:23","clicktimestamp":"2019-07-13 07:53:53","clickcount":"0","clicktrend":"0"},{"id":"120774","changeuuid":"92723b34-3ebf-11e9-aa55-52543be04c81","stationuuid":"92723b29-3ebf-11e9-aa55-52543be04c81","name":"Παύλειος Λόγος - Ι.M.Β.Ν.Κ 90.2","url":"http://eco.onestreaming.com:8548/","homepage":"http://www.imverias.gr/","favicon":"https://cdn.e-radio.gr/logos/gr/big/pavleioslogos.png","tags":"ιερά μονή,εκκλησία,ορθοδοξία,greek,ecclesia,orthodoxy,orthodox christian,byzantine","country":"Greece, Ελλάδα","state":"Βέροια (Greece)","language":"Greek (Ελληνικά)","votes":"74","negativevotes":"0","lastchangetime":"2019-03-04 21:53:33","ip":"2a02:582:1cea:a800:f518:f41d:6a1c:65e3","codec":"MP3","bitrate":"96","hls":"0","lastcheckok":"1","lastchecktime":"2019-07-02 11:10:40","lastcheckoktime":"2019-07-02 11:10:40","clicktimestamp":"2019-07-11 17:44:21","clickcount":"0","clicktrend":"0"},{"id":"120775","changeuuid":"3e13646d-3ec0-11e9-aa55-52543be04c81","stationuuid":"3e136463-3ec0-11e9-aa55-52543be04c81","name":"Πεμπτουσία FM","url":"http://pemptousia2.primcast.com:5824/","homepage":"http://www.pemptousia.gr/","favicon":"https://www.pemptousia.gr/wp-content/themes/pem_gr_new/images/pem_fm.png","tags":"ορθοδοξία,εκκλησία,ecclesia,greek,orthodoxy,orthodox christian,byzantine","country":"Greece, Ελλάδα","state":"Attica","language":"Greek (Ελληνικά)","votes":"89","negativevotes":"0","lastchangetime":"2019-03-04 21:58:21","ip":"2a02:582:1cea:a800:f518:f41d:6a1c:65e3","codec":"MP3","bitrate":"128","hls":"0","lastcheckok":"1","lastchecktime":"2019-07-02 10:35:21","lastcheckoktime":"2019-07-02 10:35:21","clicktimestamp":"2019-07-13 07:59:39","clickcount":"0","clicktrend":"0"},{"id":"120776","changeuuid":"de3c1702-3ec0-11e9-aa55-52543be04c81","stationuuid":"de3c16f9-3ec0-11e9-aa55-52543be04c81","name":"Ρ/Σ Ιερά Μητρόπολις Σύρου 95.4","url":"http://s2.onweb.gr:8852/","homepage":"http://www.imsyrou.gr","favicon":"http://www.imsyrou.gr/images/modules/Syndesmoi/NewImSyrou3koumpiaOver_05.jpg","tags":"ιερά μητρόπολις,εκκλησία,ορθοδοξία,greek,ecclesia,orthodoxy,orthodox christian,byzantine","country":"Greece, Ελλάδα","state":"Syros","language":"Greek (Ελληνικά)","votes":"73","negativevotes":"0","lastchangetime":"2019-03-04 22:02:50","ip":"2a02:582:1cea:a800:f518:f41d:6a1c:65e3","codec":"MP3","bitrate":"64","hls":"0","lastcheckok":"1","lastchecktime":"2019-07-01 12:27:49","lastcheckoktime":"2019-07-01 12:27:49","clicktimestamp":"2019-07-12 14:23:09","clickcount":"0","clicktrend":"0"},{"id":"120778","changeuuid":"bdf074a7-3ec1-11e9-aa55-52543be04c81","stationuuid":"bdf07498-3ec1-11e9-aa55-52543be04c81","name":"Ραδ. Σταθμός Ι.Μ. Ηλείας 107.6","url":"http://s6.onweb.gr:8094/","homepage":"https://www.imilias.gr/","favicon":"https://www.imilias.gr/images/stories/Radio/radiosima_live.jpg","tags":"ιερά μητρόπολις,εκκλησία,ορθοδοξία,greek,ecclesia,orthodoxy,orthodox christian,byzantine","country":"Greece, Ελλάδα","state":"Pyrgos (Greece)","language":"Greek (Ελληνικά)","votes":"67","negativevotes":"0","lastchangetime":"2019-03-04 22:09:05","ip":"2a02:582:1cea:a800:f518:f41d:6a1c:65e3","codec":"MP3","bitrate":"128","hls":"0","lastcheckok":"1","lastchecktime":"2019-07-01 14:42:14","lastcheckoktime":"2019-07-01 14:42:14","clicktimestamp":"2019-07-11 17:36:44","clickcount":"0","clicktrend":"0"},{"id":"120780","changeuuid":"1ac38ee3-3ec3-11e9-aa55-52543be04c81","stationuuid":"1ac38ed3-3ec3-11e9-aa55-52543be04c81","name":"Ράδιο Ελπίδα 96.1","url":"http://eco.onestreaming.com:8564/","homepage":"http://www.imalex.gr/","favicon":"http://resources.live24.gr/resources/images/stations/aac2ec5f-6f52-4111-94fb-f5f91265d738.jpg","tags":"ιερά μητρόπολις,εκκλησία,ορθοδοξία,greek,ecclesia,orthodoxy,orthodox christian,byzantine","country":"Greece, Ελλάδα","state":"Αλεξανδρούπολις (Greece)","language":"Greek (Ελληνικά)","votes":"73","negativevotes":"0","lastchangetime":"2019-03-04 22:18:51","ip":"2a02:582:1cea:a800:f518:f41d:6a1c:65e3","codec":"MP3","bitrate":"128","hls":"0","lastcheckok":"1","lastchecktime":"2019-07-01 12:01:47","lastcheckoktime":"2019-07-01 12:01:47","clicktimestamp":"2019-07-13 08:00:25","clickcount":"0","clicktrend":"0"},{"id":"120781","changeuuid":"ab99dc2e-3ec3-11e9-aa55-52543be04c81","stationuuid":"ab99dc1d-3ec3-11e9-aa55-52543be04c81","name":"Ράδιο Κιβωτός 99.2","url":"http://s3.onweb.gr:8452","homepage":"http://www.imsn.gr/","favicon":"https://www.imsn.gr/wp-content/uploads/2017/06/radiokivotos1.jpg","tags":"ιερά μητρόπολις,εκκλησία,ορθοδοξία,greek,ecclesia,orthodoxy,orthodox christian,byzantine","country":"Greece, Ελλάδα","state":"Serres","language":"Greek (Ελληνικά)","votes":"76","negativevotes":"0","lastchangetime":"2019-03-04 22:22:54","ip":"2.84.1.203","codec":"MP3","bitrate":"128","hls":"0","lastcheckok":"1","lastchecktime":"2019-07-01 15:03:48","lastcheckoktime":"2019-07-01 15:03:48","clicktimestamp":"2019-07-11 17:42:45","clickcount":"0","clicktrend":"0"},{"id":"120782","changeuuid":"18505212-3ec4-11e9-aa55-52543be04c81","stationuuid":"185051fe-3ec4-11e9-aa55-52543be04c81","name":"Ράδιο Μαρτυρία 95.5","url":"http://sc2.streamwithq.com:8006/","homepage":"http://martiria.imka.gr/","favicon":"http://martiria.imka.gr/wp-content/uploads/2015/04/logo-big.jpg","tags":"ιερά μητρόπολις,εκκλησία,ορθοδοξία,greek,ecclesia,orthodoxy,orthodox christian,byzantine","country":"Greece, Ελλάδα","state":"Chania (Greece)","language":"Greek (Ελληνικά)","votes":"80","negativevotes":"0","lastchangetime":"2019-03-04 22:25:56","ip":"2.84.1.203","codec":"MP3","bitrate":"128","hls":"0","lastcheckok":"1","lastchecktime":"2019-07-02 06:53:44","lastcheckoktime":"2019-07-02 06:53:44","clicktimestamp":"2019-07-13 08:00:43","clickcount":"0","clicktrend":"0"},{"id":"120783","changeuuid":"019b7473-3ec5-11e9-aa55-52543be04c81","stationuuid":"019b7466-3ec5-11e9-aa55-52543be04c81","name":"ΡΣ. Ι.Μ. Αργολίδος 105.2","url":"http://eco.onestreaming.com:8556/","homepage":"https://www.imargolidos.gr/","favicon":"https://imargolidos.gr/wp-content/uploads/2019/01/Παναγία.jpg","tags":"ιερά μητρόπολις,ορθοδοξία,greek,orthodoxy,orthodox christian","country":"Greece, Ελλάδα","state":"Argolis (Greece)","language":"Greek (Ελληνικά)","votes":"70","negativevotes":"0","lastchangetime":"2019-03-04 22:32:27","ip":"2.84.1.203","codec":"MP3","bitrate":"128","hls":"0","lastcheckok":"1","lastchecktime":"2019-07-01 14:47:24","lastcheckoktime":"2019-07-01 14:47:24","clicktimestamp":"2019-07-12 18:44:25","clickcount":"0","clicktrend":"0"},{"id":"120784","changeuuid":"9cfc5194-3ec5-11e9-aa55-52543be04c81","stationuuid":"9cfc5186-3ec5-11e9-aa55-52543be04c81","name":"Σήμαντρο Χιακής Εκκλησίας 93.1","url":"http://148.251.179.119:8019/","homepage":"https://simantrochios.blogspot.com/","favicon":"http://resources.live24.gr/resources/images/stations/cbb17ed3-7244-4d57-a901-bb42771781dc.jpg","tags":"εκκλησία,ορθοδοξία,greek,ecclesia,orthodoxy,orthodox christian,byzantine","country":"Greece, Ελλάδα","state":"Χίος (Greece)","language":"Greek (Ελληνικά)","votes":"68","negativevotes":"0","lastchangetime":"2019-03-04 22:36:48","ip":"2.84.1.203","codec":"MP3","bitrate":"48","hls":"0","lastcheckok":"1","lastchecktime":"2019-07-02 09:30:06","lastcheckoktime":"2019-07-02 09:30:06","clicktimestamp":"2019-07-11 02:26:58","clickcount":"0","clicktrend":"0"}]