[{"changeuuid":"5e3d5831-561c-40e4-8934-2f48985525b3","stationuuid":"d78c4367-fd2d-40f7-9f2c-80a7c3e066ad","serveruuid":"57fefeeb-c941-4f4e-b1bc-f5a337eb952e","name":"101.1 BIG HEART FM","url":"http://162.220.162.10:8011/stream","url_resolved":"http://162.220.162.10:8011/stream","homepage":"https://bigheartfm.weebly.com/","favicon":"https://encrypted-tbn0.gstatic.com/images?q=tbn:ANd9GcTqDYrujwxE2yBwEKh2u8RjH7tmi6LGsImmWeCugDjLUQ&s","tags":"variety,world music","country":"Macao","countrycode":"MO","iso_3166_2":"","state":"Macao, SAR of China","language":"cantonese,mandarin","languagecodes":"cmn,yue","votes":53,"lastchangetime":"2025-08-09 06:30:39","lastchangetime_iso8601":"2025-08-09T06:30:39Z","codec":"MP3","bitrate":128,"hls":0,"lastcheckok":1,"lastchecktime":"2025-12-01 02:43:05","lastchecktime_iso8601":"2025-12-01T02:43:05Z","lastcheckoktime":"2025-12-01 02:43:05","lastcheckoktime_iso8601":"2025-12-01T02:43:05Z","lastlocalchecktime":"2025-11-30 14:57:36","lastlocalchecktime_iso8601":"2025-11-30T14:57:36Z","clicktimestamp":"2025-11-30 18:55:03","clicktimestamp_iso8601":"2025-11-30T18:55:03Z","clickcount":5,"clicktrend":-2,"ssl_error":0,"geo_lat":null,"geo_long":null,"geo_distance":null,"has_extended_info":false},{"changeuuid":"8f3b6c87-a928-4c1c-a092-3af04f204652","stationuuid":"4adaac34-b0dd-4a6f-9423-9da3cc554678","serveruuid":"70262386-2475-4ab9-ad34-066a631aa64f","name":"101.1 Smooth FM","url":"https://stream-icy.bauermedia.pt/smooth.aac","url_resolved":"https://stream-icy.bauermedia.pt/smooth.aac","homepage":"https://smoothfm.pt/","favicon":"","tags":"jazz,smooth jazz","country":"Macao","countrycode":"MO","iso_3166_2":"","state":"Macao, SAR of China","language":"chinese,portuguese","languagecodes":"pt,zh","votes":76,"lastchangetime":"2025-08-09 07:16:28","lastchangetime_iso8601":"2025-08-09T07:16:28Z","codec":"AAC","bitrate":127,"hls":0,"lastcheckok":1,"lastchecktime":"2025-12-01 06:36:58","lastchecktime_iso8601":"2025-12-01T06:36:58Z","lastcheckoktime":"2025-12-01 06:36:58","lastcheckoktime_iso8601":"2025-12-01T06:36:58Z","lastlocalchecktime":"2025-11-30 15:25:27","lastlocalchecktime_iso8601":"2025-11-30T15:25:27Z","clicktimestamp":"2025-12-01 06:10:04","clicktimestamp_iso8601":"2025-12-01T06:10:04Z","clickcount":5,"clicktrend":1,"ssl_error":0,"geo_lat":null,"geo_long":null,"geo_distance":null,"has_extended_info":false},{"changeuuid":"ae783bb0-7092-4d61-b711-7b0f6fde5ac3","stationuuid":"a4c941e9-5ce2-4926-ae3c-4bd7d8f697e2","serveruuid":"8ae14782-54cb-4c1a-aeac-7d8549f31759","name":"101.7 BIG HEART FM","url":"https://62.138.18.102:8133/stream","url_resolved":"https://62.138.18.102:8133/stream","homepage":"https://bigheartfm.weebly.com/","favicon":"https://encrypted-tbn0.gstatic.com/images?q=tbn:ANd9GcTJlv53fkkLJDk_Kfdz2kv20-Rad_UnpdEgUKjuHbnKHmwoL7lSyYTsZLe6&s=10","tags":"top 40,variety,world music","country":"Macao","countrycode":"MO","iso_3166_2":"","state":"Macao, SAR of China","language":"english","languagecodes":"en","votes":8,"lastchangetime":"2025-08-09 07:19:38","lastchangetime_iso8601":"2025-08-09T07:19:38Z","codec":"AAC+","bitrate":24,"hls":0,"lastcheckok":1,"lastchecktime":"2025-11-30 19:19:18","lastchecktime_iso8601":"2025-11-30T19:19:18Z","lastcheckoktime":"2025-11-30 19:19:18","lastcheckoktime_iso8601":"2025-11-30T19:19:18Z","lastlocalchecktime":"2025-11-30 15:56:22","lastlocalchecktime_iso8601":"2025-11-30T15:56:22Z","clicktimestamp":"2025-11-30 15:26:05","clicktimestamp_iso8601":"2025-11-30T15:26:05Z","clickcount":4,"clicktrend":-1,"ssl_error":0,"geo_lat":null,"geo_long":null,"geo_distance":null,"has_extended_info":false},{"changeuuid":"47753dd9-5717-4df3-b2d8-18c79f956749","stationuuid":"b14a7f8b-eae9-49d7-81e0-e52797556805","serveruuid":"eb8d0224-6f9d-4893-a3c7-019242790bbe","name":"91.5 HIT FM MACAU (成都）","url":"http://lhttp.qingting.fm/live/15318703/64k.mp3","url_resolved":"http://lhttp.qingting.fm/live/15318703/64k.mp3","homepage":"https://www.hitfm.cn/","favicon":"https://upload.wikimedia.org/wikipedia/zh/1/1b/CRI_Hit_FM_logo.png","tags":"hot ac,pop,top 40","country":"Macao","countrycode":"MO","iso_3166_2":"","state":"Macao, SAR of China","language":"mandarin","languagecodes":"cmn","votes":41,"lastchangetime":"2025-08-08 22:36:52","lastchangetime_iso8601":"2025-08-08T22:36:52Z","codec":"MP3","bitrate":0,"hls":0,"lastcheckok":1,"lastchecktime":"2025-12-01 03:50:32","lastchecktime_iso8601":"2025-12-01T03:50:32Z","lastcheckoktime":"2025-12-01 03:50:32","lastcheckoktime_iso8601":"2025-12-01T03:50:32Z","lastlocalchecktime":"2025-12-01 03:50:32","lastlocalchecktime_iso8601":"2025-12-01T03:50:32Z","clicktimestamp":"2025-11-30 21:55:17","clicktimestamp_iso8601":"2025-11-30T21:55:17Z","clickcount":5,"clicktrend":-3,"ssl_error":0,"geo_lat":null,"geo_long":null,"geo_distance":null,"has_extended_info":false},{"changeuuid":"5ae6a14c-0d39-42c3-902a-720d187f4a2b","stationuuid":"63180907-1c42-4513-a6f7-d85472bf2188","serveruuid":"cb8f6669-15d6-4eb3-97d9-6deb484075a5","name":"Abdulbasit Abdulsamad","url":"https://radio.mp3islam.com/listen/abdulbasit/radio.mp3","url_resolved":"https://radio.mp3islam.com/listen/abdulbasit/radio.mp3","homepage":"https://mp3islam.com/","favicon":"null","tags":"","country":"Macao","countrycode":"MO","iso_3166_2":"","state":"","language":"arabic","languagecodes":"ar","votes":6,"lastchangetime":"2025-08-09 05:49:00","lastchangetime_iso8601":"2025-08-09T05:49:00Z","codec":"MP3","bitrate":192,"hls":0,"lastcheckok":1,"lastchecktime":"2025-12-01 06:53:53","lastchecktime_iso8601":"2025-12-01T06:53:53Z","lastcheckoktime":"2025-12-01 06:53:53","lastcheckoktime_iso8601":"2025-12-01T06:53:53Z","lastlocalchecktime":"2025-11-30 12:25:26","lastlocalchecktime_iso8601":"2025-11-30T12:25:26Z","clicktimestamp":"2025-12-01 00:15:04","clicktimestamp_iso8601":"2025-12-01T00:15:04Z","clickcount":1,"clicktrend":1,"ssl_error":0,"geo_lat":null,"geo_long":null,"geo_distance":null,"has_extended_info":false},{"changeuuid":"e733f6b3-4c03-4769-929e-6443584d971c","stationuuid":"bb43694b-89ba-4ec6-a947-7e2406a0bf63","serveruuid":"47bfc7f1-6c2e-4e4f-94dc-5bea7c614a6a","name":"Asia FM 106.9","url":"https://lhttp.qingting.fm/live/20071/64k.mp3","url_resolved":"https://lhttp.qingting.fm/live/20071/64k.mp3","homepage":"http://www.asiafm.net/","favicon":"http://www.asiafm.net/favicon.ico","tags":"asian music,variety","country":"Macao","countrycode":"MO","iso_3166_2":"","state":"Macao, SAR of China","language":"cantonese","languagecodes":"yue","votes":31,"lastchangetime":"2025-08-09 00:46:23","lastchangetime_iso8601":"2025-08-09T00:46:23Z","codec":"MP3","bitrate":0,"hls":0,"lastcheckok":1,"lastchecktime":"2025-12-01 08:21:02","lastchecktime_iso8601":"2025-12-01T08:21:02Z","lastcheckoktime":"2025-12-01 08:21:02","lastcheckoktime_iso8601":"2025-12-01T08:21:02Z","lastlocalchecktime":"2025-12-01 03:20:30","lastlocalchecktime_iso8601":"2025-12-01T03:20:30Z","clicktimestamp":"2025-12-01 01:18:17","clicktimestamp_iso8601":"2025-12-01T01:18:17Z","clickcount":6,"clicktrend":-1,"ssl_error":0,"geo_lat":null,"geo_long":null,"geo_distance":null,"has_extended_info":false},{"changeuuid":"db4d4c9d-8b3d-421e-9df7-eb6e111a7d3a","stationuuid":"7b0db4ec-a09f-49a9-a3d9-f7c3e468d4b0","serveruuid":"47bfc7f1-6c2e-4e4f-94dc-5bea7c614a6a","name":"Asia FM 106.9","url":"https://lhttp.qingting.fm/live/20071/64k.mp3","url_resolved":"https://lhttp.qingting.fm/live/20071/64k.mp3","homepage":"http://www.asiafm.cn/","favicon":"","tags":"asian music,variety","country":"Macao","countrycode":"MO","iso_3166_2":"","state":"Macao, SAR of China","language":"cantonese","languagecodes":"yue","votes":22,"lastchangetime":"2025-08-09 07:07:31","lastchangetime_iso8601":"2025-08-09T07:07:31Z","codec":"MP3","bitrate":0,"hls":0,"lastcheckok":1,"lastchecktime":"2025-11-30 23:56:28","lastchecktime_iso8601":"2025-11-30T23:56:28Z","lastcheckoktime":"2025-11-30 23:56:28","lastcheckoktime_iso8601":"2025-11-30T23:56:28Z","lastlocalchecktime":"2025-11-30 13:25:04","lastlocalchecktime_iso8601":"2025-11-30T13:25:04Z","clicktimestamp":"2025-12-01 07:55:08","clicktimestamp_iso8601":"2025-12-01T07:55:08Z","clickcount":4,"clicktrend":0,"ssl_error":0,"geo_lat":null,"geo_long":null,"geo_distance":null,"has_extended_info":false},{"changeuuid":"e70b2edf-a28c-41b2-a195-eb10ba13cef2","stationuuid":"d26b96a1-4fe5-4e45-86b9-2dd210a46aeb","serveruuid":"fe18fcc7-f5d0-4991-b516-d909c568b251","name":"CGTN Radio - Macau 1341 AM","url":"https://sk.cri.cn/am846.m3u8","url_resolved":"https://sk.cri.cn/am846.m3u8","homepage":"https://radio.cgtn.com/","favicon":"https://upload.wikimedia.org/wikipedia/commons/2/25/CGTN.png","tags":"world news","country":"Macao","countrycode":"MO","iso_3166_2":"","state":"Macao, SAR of China","language":"chinese,english,portuguese","languagecodes":"en,pt,zh","votes":57,"lastchangetime":"2025-08-09 06:08:49","lastchangetime_iso8601":"2025-08-09T06:08:49Z","codec":"UNKNOWN","bitrate":0,"hls":1,"lastcheckok":1,"lastchecktime":"2025-11-30 17:07:01","lastchecktime_iso8601":"2025-11-30T17:07:01Z","lastcheckoktime":"2025-11-30 17:07:01","lastcheckoktime_iso8601":"2025-11-30T17:07:01Z","lastlocalchecktime":"2025-11-30 17:07:01","lastlocalchecktime_iso8601":"2025-11-30T17:07:01Z","clicktimestamp":"2025-11-29 21:13:32","clicktimestamp_iso8601":"2025-11-29T21:13:32Z","clickcount":4,"clicktrend":-1,"ssl_error":0,"geo_lat":null,"geo_long":null,"geo_distance":null,"has_extended_info":false},{"changeuuid":"ce3a656a-70dc-44fe-a949-25268db6d0a6","stationuuid":"51e8b781-8061-424a-bea6-57c5ed682db4","serveruuid":"2e78adc4-cdb9-439e-b588-2e2f75eab30d","name":"Channel [V] International","url":"https://listen.radioking.com/radio/453221/stream/508076","url_resolved":"https://listen.radioking.com/radio/453221/stream/508076","homepage":"https://en.m.wikipedia.org/wiki/Channel_V","favicon":"https://upload.wikimedia.org/wikipedia/commons/thumb/4/4b/Channel_V_Logo.svg/800px-Channel_V_Logo.svg.png","tags":"hot ac,music videos,top 40","country":"Macao","countrycode":"MO","iso_3166_2":"","state":"Macao, SAR of China","language":"english","languagecodes":"en","votes":19,"lastchangetime":"2025-08-09 04:11:19","lastchangetime_iso8601":"2025-08-09T04:11:19Z","codec":"MP3","bitrate":128,"hls":0,"lastcheckok":1,"lastchecktime":"2025-12-01 07:49:40","lastchecktime_iso8601":"2025-12-01T07:49:40Z","lastcheckoktime":"2025-12-01 07:49:40","lastcheckoktime_iso8601":"2025-12-01T07:49:40Z","lastlocalchecktime":"2025-11-30 13:13:07","lastlocalchecktime_iso8601":"2025-11-30T13:13:07Z","clicktimestamp":"2025-11-29 16:54:48","clicktimestamp_iso8601":"2025-11-29T16:54:48Z","clickcount":4,"clicktrend":-2,"ssl_error":0,"geo_lat":null,"geo_long":null,"geo_distance":null,"has_extended_info":false},{"changeuuid":"0cc2f897-6ade-451e-a76b-2f077bd3ea11","stationuuid":"5a7a719f-ed6b-46fc-a25e-b16d5d373b25","serveruuid":"e10becba-7fe1-4874-b584-3766440a86c2","name":"CityFM Macau - 90.5 FM","url":"https://lhttp.qtfm.cn/live/20500153/64k.mp3","url_resolved":"https://lhttp.qtfm.cn/live/20500153/64k.mp3","homepage":"https://m.qtfm.cn/","favicon":"https://pic.qtfm.cn/2022/0703/20220703121159.jpeg","tags":"internet radio,music","country":"Macao","countrycode":"MO","iso_3166_2":"","state":"Macao, SAR of China","language":"chinese,portuguese","languagecodes":"pt,zh","votes":81,"lastchangetime":"2025-08-09 02:34:54","lastchangetime_iso8601":"2025-08-09T02:34:54Z","codec":"MP3","bitrate":0,"hls":0,"lastcheckok":1,"lastchecktime":"2025-11-30 23:56:28","lastchecktime_iso8601":"2025-11-30T23:56:28Z","lastcheckoktime":"2025-11-30 23:56:28","lastcheckoktime_iso8601":"2025-11-30T23:56:28Z","lastlocalchecktime":"2025-11-30 12:59:08","lastlocalchecktime_iso8601":"2025-11-30T12:59:08Z","clicktimestamp":"2025-11-30 18:57:51","clicktimestamp_iso8601":"2025-11-30T18:57:51Z","clickcount":9,"clicktrend":-6,"ssl_error":0,"geo_lat":null,"geo_long":null,"geo_distance":null,"has_extended_info":false},{"changeuuid":"f9d0f4e6-ec96-4827-a428-62ee03104124","stationuuid":"0754f053-39db-4831-b5a7-79f6c63053b8","serveruuid":"5eceef41-0eff-4b28-bf29-897bd43d5e5b","name":"CNR-7 粵港澳大灣區之聲","url":"https://satellitepull.cnr.cn/live/wxhxzs/playlist.m3u8?wsSession=a919bd0baf31a1a6f3966f08-174761752612586&wsIPSercert=270c8446fe14303f2433a2f164ccd9e5","url_resolved":"https://satellitepull.cnr.cn/live/wxhxzs/playlist.m3u8?wsSession=a919bd0baf31a1a6f3966f08-174761752612586&wsIPSercert=270c8446fe14303f2433a2f164ccd9e5","homepage":"http://rtgb.cnr.cn/","favicon":"https://wx4.sinaimg.cn/mw2000/0081HCo7ly8g9uvqyy67nj30dw0dw756.jpg","tags":"full service","country":"Macao","countrycode":"MO","iso_3166_2":"","state":"","language":"cantonese,chinese","languagecodes":"yue,zh","votes":28,"lastchangetime":"2025-08-09 00:28:42","lastchangetime_iso8601":"2025-08-09T00:28:42Z","codec":"UNKNOWN","bitrate":0,"hls":1,"lastcheckok":1,"lastchecktime":"2025-12-01 06:00:10","lastchecktime_iso8601":"2025-12-01T06:00:10Z","lastcheckoktime":"2025-12-01 06:00:10","lastcheckoktime_iso8601":"2025-12-01T06:00:10Z","lastlocalchecktime":"2025-12-01 06:00:10","lastlocalchecktime_iso8601":"2025-12-01T06:00:10Z","clicktimestamp":"2025-12-01 02:19:48","clicktimestamp_iso8601":"2025-12-01T02:19:48Z","clickcount":3,"clicktrend":-1,"ssl_error":0,"geo_lat":null,"geo_long":null,"geo_distance":null,"has_extended_info":false},{"changeuuid":"37bda433-ed51-4dc4-b8ae-c0558f91c00b","stationuuid":"deb070ed-fa67-411a-afa4-b36bd45a15be","serveruuid":"e10becba-7fe1-4874-b584-3766440a86c2","name":"Lotus FM Macau HD - 97.4 FM","url":"https://lhttp.qtfm.cn/live/20533/64k.mp3","url_resolved":"https://lhttp.qtfm.cn/live/20533/64k.mp3","homepage":"https://wap.macaulotustv.cc/wap.php","favicon":"https://upload.wikimedia.org/wikipedia/en/9/99/Lotus_TV_Macau_logo.jpg","tags":"variety,world music","country":"Macao","countrycode":"MO","iso_3166_2":"","state":"Macao, SAR of China","language":"english,mandarin","languagecodes":"cmn,en","votes":25,"lastchangetime":"2025-08-09 03:48:30","lastchangetime_iso8601":"2025-08-09T03:48:30Z","codec":"MP3","bitrate":0,"hls":0,"lastcheckok":1,"lastchecktime":"2025-12-01 04:33:41","lastchecktime_iso8601":"2025-12-01T04:33:41Z","lastcheckoktime":"2025-12-01 04:33:41","lastcheckoktime_iso8601":"2025-12-01T04:33:41Z","lastlocalchecktime":"2025-11-30 09:17:44","lastlocalchecktime_iso8601":"2025-11-30T09:17:44Z","clicktimestamp":"2025-11-30 07:49:45","clicktimestamp_iso8601":"2025-11-30T07:49:45Z","clickcount":2,"clicktrend":-2,"ssl_error":0,"geo_lat":null,"geo_long":null,"geo_distance":null,"has_extended_info":false},{"changeuuid":"85060e54-48e4-4858-a5e8-b2b637e2a77d","stationuuid":"535befe5-6f62-4e14-86bb-ec4ac4b7b337","serveruuid":"e10becba-7fe1-4874-b584-3766440a86c2","name":"Lotus Macau Radio - 1062 AM","url":"https://lhttp.qtfm.cn/live/20133/64k.mp3","url_resolved":"https://lhttp.qtfm.cn/live/20133/64k.mp3","homepage":"https://wap.macaulotustv.cc/wap.php","favicon":"https://upload.wikimedia.org/wikipedia/en/9/99/Lotus_TV_Macau_logo.jpg","tags":"variety,world music","country":"Macao","countrycode":"MO","iso_3166_2":"","state":"Macao, SAR of China","language":"english,mandarin","languagecodes":"cmn,en","votes":21,"lastchangetime":"2025-08-09 04:28:13","lastchangetime_iso8601":"2025-08-09T04:28:13Z","codec":"MP3","bitrate":0,"hls":0,"lastcheckok":1,"lastchecktime":"2025-12-01 04:40:47","lastchecktime_iso8601":"2025-12-01T04:40:47Z","lastcheckoktime":"2025-12-01 04:40:47","lastcheckoktime_iso8601":"2025-12-01T04:40:47Z","lastlocalchecktime":"2025-12-01 03:23:48","lastlocalchecktime_iso8601":"2025-12-01T03:23:48Z","clicktimestamp":"2025-12-01 02:44:35","clicktimestamp_iso8601":"2025-12-01T02:44:35Z","clickcount":7,"clicktrend":-4,"ssl_error":0,"geo_lat":null,"geo_long":null,"geo_distance":null,"has_extended_info":false},{"changeuuid":"c7f39405-5fa1-40a1-a763-dafc38ca6cdd","stationuuid":"b591479f-e323-4fae-89be-23a3925c654a","serveruuid":"70262386-2475-4ab9-ad34-066a631aa64f","name":"M80 Radio Macau - 107.1 FM","url":"https://stream-icy.bauermedia.pt/m80.mp3","url_resolved":"https://stream-icy.bauermedia.pt/m80.mp3","homepage":"https://m80.pt/","favicon":"https://m80.pt/favicon.ico","tags":"pop,rock,variety","country":"Macao","countrycode":"MO","iso_3166_2":"","state":"Macao, SAR of China","language":"chinese,portuguese","languagecodes":"pt,zh","votes":51,"lastchangetime":"2025-08-09 04:13:09","lastchangetime_iso8601":"2025-08-09T04:13:09Z","codec":"MP3","bitrate":128,"hls":0,"lastcheckok":1,"lastchecktime":"2025-12-01 01:03:25","lastchecktime_iso8601":"2025-12-01T01:03:25Z","lastcheckoktime":"2025-12-01 01:03:25","lastcheckoktime_iso8601":"2025-12-01T01:03:25Z","lastlocalchecktime":"2025-11-30 13:24:18","lastlocalchecktime_iso8601":"2025-11-30T13:24:18Z","clicktimestamp":"2025-11-29 20:15:10","clicktimestamp_iso8601":"2025-11-29T20:15:10Z","clickcount":2,"clicktrend":-2,"ssl_error":0,"geo_lat":null,"geo_long":null,"geo_distance":null,"has_extended_info":false},{"changeuuid":"cb979522-b668-4250-94da-c069c5bfa6ad","stationuuid":"849c06ea-d61f-45c3-a1d9-87d54d1e86eb","serveruuid":"70262386-2475-4ab9-ad34-066a631aa64f","name":"M80 Radio Macau - 80s","url":"https://stream-icy.bauermedia.pt/m8080.aac","url_resolved":"https://stream-icy.bauermedia.pt/m8080.aac","homepage":"https://m80.pt/","favicon":"","tags":"classic hits","country":"Macao","countrycode":"MO","iso_3166_2":"","state":"Macao, SAR of China","language":"cantonese,mandarin","languagecodes":"cmn,yue","votes":39,"lastchangetime":"2025-08-09 05:44:39","lastchangetime_iso8601":"2025-08-09T05:44:39Z","codec":"AAC","bitrate":127,"hls":0,"lastcheckok":1,"lastchecktime":"2025-12-01 07:27:22","lastchecktime_iso8601":"2025-12-01T07:27:22Z","lastcheckoktime":"2025-12-01 07:27:22","lastcheckoktime_iso8601":"2025-12-01T07:27:22Z","lastlocalchecktime":"2025-11-30 15:39:20","lastlocalchecktime_iso8601":"2025-11-30T15:39:20Z","clicktimestamp":"2025-12-01 02:17:25","clicktimestamp_iso8601":"2025-12-01T02:17:25Z","clickcount":5,"clicktrend":-1,"ssl_error":0,"geo_lat":null,"geo_long":null,"geo_distance":null,"has_extended_info":false},{"changeuuid":"9960eaa6-e2c5-4449-8302-7c0db62e692d","stationuuid":"6d70bf8d-8590-4e20-847d-e5f49148210d","serveruuid":"70262386-2475-4ab9-ad34-066a631aa64f","name":"M80 Radio Macau - 90s","url":"https://stream-icy.bauermedia.pt/m8090.aac","url_resolved":"https://stream-icy.bauermedia.pt/m8090.aac","homepage":"https://bauermedia.pt/m80/m80-90","favicon":"https://bauermedia.pt/m80/m80-90/favicon.ico","tags":"90s,hits,pop,retro,rock","country":"Macao","countrycode":"MO","iso_3166_2":"","state":"Macao, SAR of China","language":"chinese,portuguese","languagecodes":"pt,zh","votes":48,"lastchangetime":"2025-08-08 19:34:00","lastchangetime_iso8601":"2025-08-08T19:34:00Z","codec":"AAC","bitrate":128,"hls":0,"lastcheckok":1,"lastchecktime":"2025-12-01 00:50:42","lastchecktime_iso8601":"2025-12-01T00:50:42Z","lastcheckoktime":"2025-12-01 00:50:42","lastcheckoktime_iso8601":"2025-12-01T00:50:42Z","lastlocalchecktime":"2025-12-01 00:50:42","lastlocalchecktime_iso8601":"2025-12-01T00:50:42Z","clicktimestamp":"2025-11-28 16:11:08","clicktimestamp_iso8601":"2025-11-28T16:11:08Z","clickcount":1,"clicktrend":0,"ssl_error":0,"geo_lat":null,"geo_long":null,"geo_distance":null,"has_extended_info":false},{"changeuuid":"1e5c9bec-7ebb-42bb-919f-a54ecaa0ca27","stationuuid":"300f74ed-1fe7-4fc5-88fc-6063f73591f4","serveruuid":"70262386-2475-4ab9-ad34-066a631aa64f","name":"M80 Radio Macau - Rock","url":"https://stream-icy.bauermedia.pt/m80rock.aac","url_resolved":"https://stream-icy.bauermedia.pt/m80rock.aac","homepage":"https://bauermedia.pt/m80/m80-rock","favicon":"https://bauermedia.pt/m80/m80-rock/favicon.ico","tags":"classic rock","country":"Macao","countrycode":"MO","iso_3166_2":"","state":"Macao, SAR of China","language":"chinese,portuguese","languagecodes":"pt,zh","votes":64,"lastchangetime":"2025-08-09 08:13:51","lastchangetime_iso8601":"2025-08-09T08:13:51Z","codec":"AAC","bitrate":128,"hls":0,"lastcheckok":1,"lastchecktime":"2025-11-30 22:20:18","lastchecktime_iso8601":"2025-11-30T22:20:18Z","lastcheckoktime":"2025-11-30 22:20:18","lastcheckoktime_iso8601":"2025-11-30T22:20:18Z","lastlocalchecktime":"2025-11-30 15:42:42","lastlocalchecktime_iso8601":"2025-11-30T15:42:42Z","clicktimestamp":"2025-11-30 10:55:12","clicktimestamp_iso8601":"2025-11-30T10:55:12Z","clickcount":3,"clicktrend":-1,"ssl_error":0,"geo_lat":null,"geo_long":null,"geo_distance":null,"has_extended_info":false},{"changeuuid":"7ffa839b-477c-48f3-8666-ef4f147e2fae","stationuuid":"e8d5fa81-e361-4952-9f18-4daea447e2eb","serveruuid":"f3efe49d-8e83-4a0d-8a92-2c30ce9cbea5","name":"Rádio Macau FM98.0","url":"https://mo.ufofm.com/live/rch1.live/chunklist_w1881620473.m3u8?audio","url_resolved":"https://mo.ufofm.com/live/rch1.live/chunklist_w1881620473.m3u8?audio","homepage":"https://www.tdm.com.mo/zh-hant/program/radio_zh","favicon":"https://cdn.sao.fm/wp-content/uploads/20240115004813288.jpg","tags":"public radio","country":"Macao","countrycode":"MO","iso_3166_2":"","state":"","language":"portuguese","languagecodes":"pt","votes":48,"lastchangetime":"2025-08-08 22:53:54","lastchangetime_iso8601":"2025-08-08T22:53:54Z","codec":"UNKNOWN","bitrate":0,"hls":1,"lastcheckok":1,"lastchecktime":"2025-12-01 08:53:40","lastchecktime_iso8601":"2025-12-01T08:53:40Z","lastcheckoktime":"2025-12-01 08:53:40","lastcheckoktime_iso8601":"2025-12-01T08:53:40Z","lastlocalchecktime":"2025-11-30 21:08:20","lastlocalchecktime_iso8601":"2025-11-30T21:08:20Z","clicktimestamp":"2025-11-30 05:49:45","clicktimestamp_iso8601":"2025-11-30T05:49:45Z","clickcount":1,"clicktrend":-1,"ssl_error":0,"geo_lat":null,"geo_long":null,"geo_distance":null,"has_extended_info":false},{"changeuuid":"45d4bb3e-ff4d-4d65-bd21-1101e878cd88","stationuuid":"9dc1af39-5f93-11e9-a622-52543be04c81","serveruuid":"d2f7ab50-f234-4645-aa54-ce1847b1aef2","name":"RADIO MARIA MACAU","url":"http://dreamsiteradiocp2.com:8038/stream","url_resolved":"http://dreamsiteradiocp2.com:8038/stream","homepage":"http://www.voiceofmary.org.mo/VoiceOfMary/jsp/index.jsp","favicon":"","tags":"catholic,catolica,christian,katholik,religion,religious,talk","country":"Macao","countrycode":"MO","iso_3166_2":"","state":"","language":"","languagecodes":"","votes":365,"lastchangetime":"2025-08-08 16:03:21","lastchangetime_iso8601":"2025-08-08T16:03:21Z","codec":"MP3","bitrate":32,"hls":0,"lastcheckok":1,"lastchecktime":"2025-11-30 23:29:53","lastchecktime_iso8601":"2025-11-30T23:29:53Z","lastcheckoktime":"2025-11-30 23:29:53","lastcheckoktime_iso8601":"2025-11-30T23:29:53Z","lastlocalchecktime":"2025-11-30 23:29:53","lastlocalchecktime_iso8601":"2025-11-30T23:29:53Z","clicktimestamp":"2025-11-30 14:23:53","clicktimestamp_iso8601":"2025-11-30T14:23:53Z","clickcount":2,"clicktrend":1,"ssl_error":0,"geo_lat":null,"geo_long":null,"geo_distance":null,"has_extended_info":false},{"changeuuid":"6ef9e0e3-ebb7-4555-863d-dd586b011fda","stationuuid":"a7dfd0bc-c9cd-492d-aeb4-e43c8ed83745","serveruuid":"db26ddf1-8a98-4a00-8b1a-d7c68dfbef78","name":"Radio Top 80 Macau 強電台 - 89.9 FM","url":"http://live.top80.fm:8086/;","url_resolved":"http://live.top80.fm:8086/;","homepage":"https://www.top80.fm/","favicon":"https://img.radios.com.br/radio/xl/radio232214_1699645003.jpg","tags":"2000s,80s,90s,classic hits,retro","country":"Macao","countrycode":"MO","iso_3166_2":"","state":"Macao, SAR of China","language":"cantonese,mandarin","languagecodes":"cmn,yue","votes":150,"lastchangetime":"2025-08-08 21:36:50","lastchangetime_iso8601":"2025-08-08T21:36:50Z","codec":"MP3","bitrate":320,"hls":0,"lastcheckok":1,"lastchecktime":"2025-12-01 09:01:18","lastchecktime_iso8601":"2025-12-01T09:01:18Z","lastcheckoktime":"2025-12-01 09:01:18","lastcheckoktime_iso8601":"2025-12-01T09:01:18Z","lastlocalchecktime":"2025-12-01 01:39:52","lastlocalchecktime_iso8601":"2025-12-01T01:39:52Z","clicktimestamp":"2025-12-01 08:52:37","clicktimestamp_iso8601":"2025-12-01T08:52:37Z","clickcount":20,"clicktrend":-7,"ssl_error":0,"geo_lat":null,"geo_long":null,"geo_distance":null,"has_extended_info":false},{"changeuuid":"157fd7da-43b1-4444-a298-e3cd31174ee1","stationuuid":"8cb70465-2796-4d90-aed3-968dea6a3184","serveruuid":"ee2265b7-ff49-41aa-9568-daed7dfb88fc","name":"Radio Veritas Asia 1044 AM","url":"http://icecast.eradioportal.com:8000/radyo-veritas-846","url_resolved":"http://icecast.eradioportal.com:8000/radyo-veritas-846","homepage":"https://www.rvasia.org/","favicon":"https://www.rvasia.org/favicon","tags":"religious","country":"Macao","countrycode":"MO","iso_3166_2":"","state":"Macao, SAR of China","language":"english,filipino,mandarin","languagecodes":"cmn,en","votes":30,"lastchangetime":"2025-08-09 00:10:13","lastchangetime_iso8601":"2025-08-09T00:10:13Z","codec":"MP3","bitrate":128,"hls":0,"lastcheckok":1,"lastchecktime":"2025-12-01 07:44:18","lastchecktime_iso8601":"2025-12-01T07:44:18Z","lastcheckoktime":"2025-12-01 07:44:18","lastcheckoktime_iso8601":"2025-12-01T07:44:18Z","lastlocalchecktime":"2025-12-01 07:00:49","lastlocalchecktime_iso8601":"2025-12-01T07:00:49Z","clicktimestamp":"2025-11-28 23:14:23","clicktimestamp_iso8601":"2025-11-28T23:14:23Z","clickcount":1,"clicktrend":0,"ssl_error":0,"geo_lat":null,"geo_long":null,"geo_distance":null,"has_extended_info":false},{"changeuuid":"499df911-9e90-4498-99c3-40666d8111e9","stationuuid":"82c7579a-dcfe-4224-bb02-ec11cf2f4744","serveruuid":"b4a90e06-b350-4206-967f-b69bb98efdbd","name":"Radio Vilaverde Lda","url":"https://fm995.ddns.net/hls1/fm995.m3u8","url_resolved":"https://fm995.ddns.net/hls1/fm995.m3u8","homepage":"https://www.vfm995.com/m.html","favicon":"","tags":"","country":"Macao","countrycode":"MO","iso_3166_2":"","state":"","language":"","languagecodes":"","votes":17,"lastchangetime":"2025-08-08 16:03:19","lastchangetime_iso8601":"2025-08-08T16:03:19Z","codec":"UNKNOWN","bitrate":0,"hls":1,"lastcheckok":1,"lastchecktime":"2025-12-01 03:34:58","lastchecktime_iso8601":"2025-12-01T03:34:58Z","lastcheckoktime":"2025-12-01 03:34:58","lastcheckoktime_iso8601":"2025-12-01T03:34:58Z","lastlocalchecktime":"2025-11-30 12:56:33","lastlocalchecktime_iso8601":"2025-11-30T12:56:33Z","clicktimestamp":"2025-11-29 14:46:13","clicktimestamp_iso8601":"2025-11-29T14:46:13Z","clickcount":1,"clicktrend":-1,"ssl_error":0,"geo_lat":null,"geo_long":null,"geo_distance":null,"has_extended_info":false},{"changeuuid":"268fdc85-1b73-4520-9d82-ca7a07c8c281","stationuuid":"8492f4b4-8eb8-488f-b5cf-e81025882b3b","serveruuid":"18f126ae-f797-4f65-9cd2-0016c16eafd9","name":"Record FM 100.3 Macau","url":"https://nl.digitalrm.pt:8028/stream","url_resolved":"https://nl.digitalrm.pt:8028/stream","homepage":"https://www.recordfm.pt/player_m_lisboa.htm","favicon":"https://encrypted-tbn0.gstatic.com/images?q=tbn:ANd9GcQWxzia_Bkrj8iaa6iQ7uAbi1eem1GcDGKDFYGmE_HYjdlILYB2R9hKtMoF&s=10","tags":"hot ac,talk,variety","country":"Macao","countrycode":"MO","iso_3166_2":"","state":"Macao, SAR of China","language":"cantonese,portuguese","languagecodes":"pt,yue","votes":36,"lastchangetime":"2025-08-09 03:13:05","lastchangetime_iso8601":"2025-08-09T03:13:05Z","codec":"MP3","bitrate":128,"hls":0,"lastcheckok":1,"lastchecktime":"2025-12-01 06:05:54","lastchecktime_iso8601":"2025-12-01T06:05:54Z","lastcheckoktime":"2025-12-01 06:05:54","lastcheckoktime_iso8601":"2025-12-01T06:05:54Z","lastlocalchecktime":"2025-12-01 05:48:56","lastlocalchecktime_iso8601":"2025-12-01T05:48:56Z","clicktimestamp":"2025-11-29 14:45:54","clicktimestamp_iso8601":"2025-11-29T14:45:54Z","clickcount":2,"clicktrend":-1,"ssl_error":0,"geo_lat":null,"geo_long":null,"geo_distance":null,"has_extended_info":false},{"changeuuid":"86bb5f90-82f6-4eaa-866b-c32841f8f847","stationuuid":"ea10db0c-35e8-4f6b-ae2d-7adb099d5de0","serveruuid":"57fefeeb-c941-4f4e-b1bc-f5a337eb952e","name":"Romance Radio 95.5 FM","url":"http://162.220.162.10:8011/stream","url_resolved":"http://162.220.162.10:8011/stream","homepage":"https://norilynonecoin.wixsite.com/criradioplayers-push","favicon":"https://encrypted-tbn0.gstatic.com/images?q=tbn:ANd9GcS0ZaX_MeobQXgZYNlYWuf1F_UdPiX_QHNuHQ&usqp=CAU","tags":"love songs","country":"Macao","countrycode":"MO","iso_3166_2":"","state":"Macao, SAR of China","language":"chinese,mandarin","languagecodes":"cmn,zh","votes":152,"lastchangetime":"2025-08-09 09:06:52","lastchangetime_iso8601":"2025-08-09T09:06:52Z","codec":"MP3","bitrate":128,"hls":0,"lastcheckok":1,"lastchecktime":"2025-12-01 02:06:45","lastchecktime_iso8601":"2025-12-01T02:06:45Z","lastcheckoktime":"2025-12-01 02:06:45","lastcheckoktime_iso8601":"2025-12-01T02:06:45Z","lastlocalchecktime":"2025-11-30 16:22:31","lastlocalchecktime_iso8601":"2025-11-30T16:22:31Z","clicktimestamp":"2025-11-30 23:02:50","clicktimestamp_iso8601":"2025-11-30T23:02:50Z","clickcount":4,"clicktrend":0,"ssl_error":0,"geo_lat":null,"geo_long":null,"geo_distance":null,"has_extended_info":false},{"changeuuid":"cbf1823b-6295-4ba3-948c-0b23294ab0d7","stationuuid":"59a7497f-5f04-4b64-8fdc-3fd7ef55d7a3","serveruuid":"3b0e61fe-2ed5-482d-a2ce-83bc191222f9","name":"RTP Macau - 97.1 FM","url":"https://radiocast.rtp.pt/antena1madeira80a.mp3","url_resolved":"https://radiocast.rtp.pt/antena1madeira80a.mp3","homepage":"https://madeira.rtp.pt/","favicon":"https://madeira.rtp.pt/favicon.ico","tags":"music,news","country":"Macao","countrycode":"MO","iso_3166_2":"","state":"Macao, SAR of China","language":"mandarin,portuguese","languagecodes":"cmn,pt","votes":36,"lastchangetime":"2025-08-09 08:38:24","lastchangetime_iso8601":"2025-08-09T08:38:24Z","codec":"MP3","bitrate":0,"hls":0,"lastcheckok":1,"lastchecktime":"2025-11-30 19:39:57","lastchecktime_iso8601":"2025-11-30T19:39:57Z","lastcheckoktime":"2025-11-30 19:39:57","lastcheckoktime_iso8601":"2025-11-30T19:39:57Z","lastlocalchecktime":"2025-11-30 16:17:06","lastlocalchecktime_iso8601":"2025-11-30T16:17:06Z","clicktimestamp":"2025-11-29 21:13:39","clicktimestamp_iso8601":"2025-11-29T21:13:39Z","clickcount":4,"clicktrend":-3,"ssl_error":0,"geo_lat":null,"geo_long":null,"geo_distance":null,"has_extended_info":false},{"changeuuid":"c7202c6a-c25c-4d5f-a4fa-46fae0a4d6d8","stationuuid":"6c07a526-7445-40f9-be2e-89f78c6fb7b0","serveruuid":"8036a3dc-fe16-4bfb-ab29-da75c347dfc3","name":"SZR 城市 FM 97.1 Macau - HD2","url":"https://stream-hls.bauermedia.pt/cidade.aac/playlist.m3u8","url_resolved":"https://stream-hls.bauermedia.pt/cidade.aac/playlist.m3u8","homepage":"https://www.szmg.com.cn/","favicon":"https://upload.wikimedia.org/wikipedia/en/9/95/Szr.jpg?20060826171746","tags":"top 40,variety,world music","country":"Macao","countrycode":"MO","iso_3166_2":"","state":"Macao, SAR of China","language":"cantonese,portuguese","languagecodes":"pt,yue","votes":22,"lastchangetime":"2025-08-09 06:46:08","lastchangetime_iso8601":"2025-08-09T06:46:08Z","codec":"AAC","bitrate":127,"hls":1,"lastcheckok":1,"lastchecktime":"2025-12-01 03:03:43","lastchecktime_iso8601":"2025-12-01T03:03:43Z","lastcheckoktime":"2025-12-01 03:03:43","lastcheckoktime_iso8601":"2025-12-01T03:03:43Z","lastlocalchecktime":"2025-11-30 22:49:27","lastlocalchecktime_iso8601":"2025-11-30T22:49:27Z","clicktimestamp":"2025-12-01 02:17:04","clicktimestamp_iso8601":"2025-12-01T02:17:04Z","clickcount":6,"clicktrend":-3,"ssl_error":0,"geo_lat":null,"geo_long":null,"geo_distance":null,"has_extended_info":false},{"changeuuid":"5177842f-f14d-446a-a1c8-234c0cd32326","stationuuid":"279027e0-2f13-4f7e-91fd-8aa40c41b05e","serveruuid":"20d94727-9146-4d6a-9e79-beb090fb1779","name":"VOA Macau","url":"http://voa-ingest.akamaized.net/hls/live/2035206/151_124L/playlist.m3u8","url_resolved":"http://voa-ingest.akamaized.net/hls/live/2035206/151_124L/playlist.m3u8","homepage":"https://www.voachinese.com/","favicon":"https://www.voachinese.com/favicon","tags":"news,world news","country":"Macao","countrycode":"MO","iso_3166_2":"","state":"Macao, SAR of China","language":"cantonese,portuguese","languagecodes":"pt,yue","votes":195,"lastchangetime":"2025-08-09 01:42:21","lastchangetime_iso8601":"2025-08-09T01:42:21Z","codec":"AAC","bitrate":140,"hls":1,"lastcheckok":1,"lastchecktime":"2025-12-01 09:07:13","lastchecktime_iso8601":"2025-12-01T09:07:13Z","lastcheckoktime":"2025-12-01 09:07:13","lastcheckoktime_iso8601":"2025-12-01T09:07:13Z","lastlocalchecktime":"2025-12-01 09:07:13","lastlocalchecktime_iso8601":"2025-12-01T09:07:13Z","clicktimestamp":"2025-11-30 14:46:13","clicktimestamp_iso8601":"2025-11-30T14:46:13Z","clickcount":6,"clicktrend":-1,"ssl_error":0,"geo_lat":null,"geo_long":null,"geo_distance":null,"has_extended_info":false},{"changeuuid":"b0db310e-8080-42a6-86e5-b6b06daa318b","stationuuid":"2c59da7b-3ac1-481a-8c8e-656163382326","serveruuid":"3fe438bf-5d75-4e4e-9850-4e8b2dc45933","name":"VOA Macau","url":"https://voa-ingest.akamaized.net/hls/live/2035206/151_124L/playlist.m3u8","url_resolved":"https://voa-ingest.akamaized.net/hls/live/2035206/151_124L/playlist.m3u8","homepage":"https://www.voachinese.com/","favicon":"","tags":"news,world news","country":"Macao","countrycode":"MO","iso_3166_2":"","state":"Macao","language":"chinese,portuguese","languagecodes":"pt,zh","votes":573,"lastchangetime":"2025-08-09 04:34:51","lastchangetime_iso8601":"2025-08-09T04:34:51Z","codec":"AAC","bitrate":140,"hls":1,"lastcheckok":1,"lastchecktime":"2025-11-30 23:23:47","lastchecktime_iso8601":"2025-11-30T23:23:47Z","lastcheckoktime":"2025-11-30 23:23:47","lastcheckoktime_iso8601":"2025-11-30T23:23:47Z","lastlocalchecktime":"2025-11-30 13:22:02","lastlocalchecktime_iso8601":"2025-11-30T13:22:02Z","clicktimestamp":"2025-11-30 23:01:17","clicktimestamp_iso8601":"2025-11-30T23:01:17Z","clickcount":6,"clicktrend":0,"ssl_error":0,"geo_lat":null,"geo_long":null,"geo_distance":null,"has_extended_info":false},{"changeuuid":"a2b2e25d-2634-46dc-a79d-269170e6067f","stationuuid":"dd9cddc3-e19b-40be-8f22-c5e20420b4cb","serveruuid":"47bfc7f1-6c2e-4e4f-94dc-5bea7c614a6a","name":"YW City Radio - Macau 954 AM","url":"https://lhttp.qingting.fm/live/1259/64k.mp3?app_id=web","url_resolved":"https://lhttp.qingting.fm/live/1259/64k.mp3?app_id=web","homepage":"https://www.ywcity.cn/#/homepage","favicon":"https://encrypted-tbn0.gstatic.com/images?q=tbn:ANd9GcRAloACLs4j25afKVh2uzyJX3NGhCBaZTLSo_Ud6VcuDiP358zYKXSPuw&s=10","tags":"talk radio","country":"Macao","countrycode":"MO","iso_3166_2":"","state":"Macao, SAR of China","language":"mandarin","languagecodes":"cmn","votes":14,"lastchangetime":"2025-08-09 04:26:20","lastchangetime_iso8601":"2025-08-09T04:26:20Z","codec":"MP3","bitrate":0,"hls":0,"lastcheckok":1,"lastchecktime":"2025-12-01 09:17:18","lastchecktime_iso8601":"2025-12-01T09:17:18Z","lastcheckoktime":"2025-12-01 09:17:18","lastcheckoktime_iso8601":"2025-12-01T09:17:18Z","lastlocalchecktime":"2025-11-30 12:13:39","lastlocalchecktime_iso8601":"2025-11-30T12:13:39Z","clicktimestamp":"2025-11-29 14:45:47","clicktimestamp_iso8601":"2025-11-29T14:45:47Z","clickcount":2,"clicktrend":-1,"ssl_error":0,"geo_lat":null,"geo_long":null,"geo_distance":null,"has_extended_info":false},{"changeuuid":"7b99134f-acce-4ed3-92ae-e60d23aa6154","stationuuid":"6999fe07-c0f3-4d36-ad2c-179bdc749c03","serveruuid":"b4a90e06-b350-4206-967f-b69bb98efdbd","name":"澳門綠邨電台","url":"https://fm995.ddns.net/hls1/fm995.m3u8","url_resolved":"https://fm995.ddns.net/hls1/fm995.m3u8","homepage":"https://www.vfm995.com/m.html","favicon":"","tags":"lifestyle","country":"Macao","countrycode":"MO","iso_3166_2":"","state":"","language":"cantonese","languagecodes":"yue","votes":645,"lastchangetime":"2025-08-09 09:08:37","lastchangetime_iso8601":"2025-08-09T09:08:37Z","codec":"UNKNOWN","bitrate":0,"hls":1,"lastcheckok":1,"lastchecktime":"2025-12-01 08:13:33","lastchecktime_iso8601":"2025-12-01T08:13:33Z","lastcheckoktime":"2025-12-01 08:13:33","lastcheckoktime_iso8601":"2025-12-01T08:13:33Z","lastlocalchecktime":"2025-12-01 08:13:33","lastlocalchecktime_iso8601":"2025-12-01T08:13:33Z","clicktimestamp":"2025-12-01 08:06:32","clicktimestamp_iso8601":"2025-12-01T08:06:32Z","clickcount":7,"clicktrend":5,"ssl_error":0,"geo_lat":null,"geo_long":null,"geo_distance":null,"has_extended_info":false},{"changeuuid":"7b582d9b-2d14-4b49-afa4-40fb3d80066f","stationuuid":"8b815a7a-da6a-468b-8e6f-08979408f1bd","serveruuid":"f3efe49d-8e83-4a0d-8a92-2c30ce9cbea5","name":"澳門電台 FM100.7","url":"https://mo.ufofm.com/live/rch2.live/chunklist_w905210118.m3u8?audio","url_resolved":"https://mo.ufofm.com/live/rch2.live/chunklist_w905210118.m3u8?audio","homepage":"https://www.tdm.com.mo/zh-hant/program/radio_zh","favicon":"https://cdn.sao.fm/wp-content/uploads/20240115003259241.jpg","tags":"public radio","country":"Macao","countrycode":"MO","iso_3166_2":"","state":"","language":"cantonese","languagecodes":"yue","votes":318,"lastchangetime":"2025-08-08 22:15:02","lastchangetime_iso8601":"2025-08-08T22:15:02Z","codec":"UNKNOWN","bitrate":0,"hls":1,"lastcheckok":1,"lastchecktime":"2025-12-01 06:26:11","lastchecktime_iso8601":"2025-12-01T06:26:11Z","lastcheckoktime":"2025-12-01 06:26:11","lastcheckoktime_iso8601":"2025-12-01T06:26:11Z","lastlocalchecktime":"2025-12-01 04:53:00","lastlocalchecktime_iso8601":"2025-12-01T04:53:00Z","clicktimestamp":"2025-11-30 03:03:04","clicktimestamp_iso8601":"2025-11-30T03:03:04Z","clickcount":3,"clicktrend":-2,"ssl_error":0,"geo_lat":null,"geo_long":null,"geo_distance":null,"has_extended_info":false},{"changeuuid":"c5242a6e-add5-4fec-94f3-a7c2812c0f66","stationuuid":"3faf8d23-bae1-4724-8201-89e0cc66fa21","serveruuid":"b4a90e06-b350-4206-967f-b69bb98efdbd","name":"綠邨","url":"https://fm995.ddns.net/hls1/fm995.m3u8","url_resolved":"https://fm995.ddns.net/hls1/fm995.m3u8","homepage":"https://fm995.ddns.net/","favicon":"","tags":"","country":"Macao","countrycode":"MO","iso_3166_2":"","state":"","language":"","languagecodes":"","votes":211,"lastchangetime":"2025-08-08 16:03:18","lastchangetime_iso8601":"2025-08-08T16:03:18Z","codec":"UNKNOWN","bitrate":0,"hls":1,"lastcheckok":1,"lastchecktime":"2025-12-01 01:12:13","lastchecktime_iso8601":"2025-12-01T01:12:13Z","lastcheckoktime":"2025-12-01 01:12:13","lastcheckoktime_iso8601":"2025-12-01T01:12:13Z","lastlocalchecktime":"2025-12-01 01:12:13","lastlocalchecktime_iso8601":"2025-12-01T01:12:13Z","clicktimestamp":"2025-11-28 11:09:08","clicktimestamp_iso8601":"2025-11-28T11:09:08Z","clickcount":1,"clicktrend":0,"ssl_error":0,"geo_lat":null,"geo_long":null,"geo_distance":null,"has_extended_info":false}]