[{"changeuuid":"6f3b0cd1-b6f8-4608-a327-58c18ccbc3e9","stationuuid":"f6be111d-2ea7-4eb4-b989-06adb8f269d6","serveruuid":"9faa7ab1-83d1-42a0-b3f6-9ec0190e09fa","name":"#Radio Quran","url":"https://n0a.radiojar.com/0tpy1h0kxtzuv?rj-ttl=5&rj-tok=AAABhdgGORQA-2acfyF3_4WY2g","url_resolved":"http://n0d.radiojar.com/0tpy1h0kxtzuv?rj-ttl=5&rj-tok=AAABmtchY9cASyiZVMA5WtNA0Q","homepage":"","favicon":"","tags":"classical","country":"Nigeria","countrycode":"NG","iso_3166_2":"","state":"","language":"","languagecodes":"","votes":550,"lastchangetime":"2025-08-08 16:03:18","lastchangetime_iso8601":"2025-08-08T16:03:18Z","codec":"MP3","bitrate":0,"hls":0,"lastcheckok":1,"lastchecktime":"2025-11-30 23:29:34","lastchecktime_iso8601":"2025-11-30T23:29:34Z","lastcheckoktime":"2025-11-30 23:29:34","lastcheckoktime_iso8601":"2025-11-30T23:29:34Z","lastlocalchecktime":"2025-11-30 13:47:12","lastlocalchecktime_iso8601":"2025-11-30T13:47:12Z","clicktimestamp":"2025-12-01 08:43:51","clicktimestamp_iso8601":"2025-12-01T08:43:51Z","clickcount":32,"clicktrend":-10,"ssl_error":0,"geo_lat":null,"geo_long":null,"geo_distance":null,"has_extended_info":false},{"changeuuid":"7b89e072-1e94-4c12-8d15-59653fa6eb40","stationuuid":"28ec90b0-62b1-42fc-9a8e-b685aea470b4","serveruuid":"3dbb0d9b-a0b7-4812-bd90-a653d160d670","name":"94.5 – BRTV Borno Radio, Maiduguri","url":"https://stream.zeno.fm/px5k346357zuv","url_resolved":"https://stream-179.zeno.fm/px5k346357zuv?zt=eyJhbGciOiJIUzI1NiJ9.eyJzdHJlYW0iOiJweDVrMzQ2MzU3enV2IiwiaG9zdCI6InN0cmVhbS0xNzkuemVuby5mbSIsInRtIjpmYWxzZSwicnR0bCI6NSwianRpIjoiWHF3U2o0TlBRazJydlZtejVJNXo2QSIsImlhdCI6MTc2NDU2NzIxOCwiZXhwIjoxNzY0NTY3Mjc4fQ.O4b14E0omhsgcDpLklvE3J3ulgjUER1cfpZnUK6NzwY","homepage":"https://brtv24.live/","favicon":"https://brtv24.live/images/brtv-logo.png","tags":"","country":"Nigeria","countrycode":"NG","iso_3166_2":"","state":"","language":"","languagecodes":"","votes":146,"lastchangetime":"2025-08-08 16:03:19","lastchangetime_iso8601":"2025-08-08T16:03:19Z","codec":"MP3","bitrate":0,"hls":0,"lastcheckok":1,"lastchecktime":"2025-12-01 05:36:01","lastchecktime_iso8601":"2025-12-01T05:36:01Z","lastcheckoktime":"2025-12-01 05:36:01","lastcheckoktime_iso8601":"2025-12-01T05:36:01Z","lastlocalchecktime":"2025-11-30 11:33:31","lastlocalchecktime_iso8601":"2025-11-30T11:33:31Z","clicktimestamp":"2025-12-01 05:24:36","clicktimestamp_iso8601":"2025-12-01T05:24:36Z","clickcount":9,"clicktrend":-2,"ssl_error":0,"geo_lat":null,"geo_long":null,"geo_distance":null,"has_extended_info":false},{"changeuuid":"949886f7-0936-4fdc-8b4a-d712692104f7","stationuuid":"cc15b2ae-77ab-4764-9a55-d87f574bbb53","serveruuid":"cb8f6669-15d6-4eb3-97d9-6deb484075a5","name":"Abdulbasit Abdulsamad","url":"https://radio.mp3islam.com/listen/abdulbasit/radio.mp3","url_resolved":"https://radio.mp3islam.com/listen/abdulbasit/radio.mp3","homepage":"https://mp3islam.com/","favicon":"null","tags":"","country":"Nigeria","countrycode":"NG","iso_3166_2":"","state":"","language":"arabic","languagecodes":"ar","votes":46,"lastchangetime":"2025-08-09 05:13:34","lastchangetime_iso8601":"2025-08-09T05:13:34Z","codec":"MP3","bitrate":192,"hls":0,"lastcheckok":1,"lastchecktime":"2025-12-01 05:55:46","lastchecktime_iso8601":"2025-12-01T05:55:46Z","lastcheckoktime":"2025-12-01 05:55:46","lastcheckoktime_iso8601":"2025-12-01T05:55:46Z","lastlocalchecktime":"2025-12-01 05:55:46","lastlocalchecktime_iso8601":"2025-12-01T05:55:46Z","clicktimestamp":"2025-12-01 08:51:38","clicktimestamp_iso8601":"2025-12-01T08:51:38Z","clickcount":14,"clicktrend":0,"ssl_error":0,"geo_lat":null,"geo_long":null,"geo_distance":null,"has_extended_info":false},{"changeuuid":"d3e08926-ad0c-4bc9-b6db-63b21d436caf","stationuuid":"22185840-f3ac-489b-bfe5-020171a4f970","serveruuid":"8cc11c42-ff0e-43c7-9d89-b8e32ecfc8ce","name":"Adamimogo FM","url":"http://stream.zeno.fm/sywy4vua6zhvv","url_resolved":"http://stream-155.zeno.fm/sywy4vua6zhvv?zt=eyJhbGciOiJIUzI1NiJ9.eyJzdHJlYW0iOiJzeXd5NHZ1YTZ6aHZ2IiwiaG9zdCI6InN0cmVhbS0xNTUuemVuby5mbSIsInRtIjpmYWxzZSwicnR0bCI6NSwianRpIjoiYl9kdlB3VkpTbFdMYVZBQWdVS3htUSIsImlhdCI6MTc2NDU3MzI2MCwiZXhwIjoxNzY0NTczMzIwfQ.wVAQuKlnXM8PTKv-up1auDFJsOuGxMItr958bBrSuQ0","homepage":"https://adamimogofm.com/","favicon":"https://i0.wp.com/adamimogofm.com/wp-content/uploads/2022/12/logo-removebg-preview-2.png?w=494&ssl=1","tags":"","country":"Nigeria","countrycode":"NG","iso_3166_2":"","state":"","language":"","languagecodes":"","votes":458,"lastchangetime":"2025-08-08 16:03:19","lastchangetime_iso8601":"2025-08-08T16:03:19Z","codec":"MP3","bitrate":0,"hls":0,"lastcheckok":1,"lastchecktime":"2025-12-01 07:14:38","lastchecktime_iso8601":"2025-12-01T07:14:38Z","lastcheckoktime":"2025-12-01 07:14:38","lastcheckoktime_iso8601":"2025-12-01T07:14:38Z","lastlocalchecktime":"2025-12-01 07:14:38","lastlocalchecktime_iso8601":"2025-12-01T07:14:38Z","clicktimestamp":"2025-12-01 08:43:11","clicktimestamp_iso8601":"2025-12-01T08:43:11Z","clickcount":32,"clicktrend":4,"ssl_error":0,"geo_lat":null,"geo_long":null,"geo_distance":null,"has_extended_info":false},{"changeuuid":"303c75d1-9ddd-4b77-a484-f51083fe973e","stationuuid":"536669d5-9b8e-4d4d-b462-caf9fdb9ab2a","serveruuid":"5f8ab514-5090-46dc-a52f-5886d74b0ab8","name":"Afrobeats Gospel Radio","url":"https://stream.zeno.fm/zyd9stmdlnlvv","url_resolved":"https://stream-164.zeno.fm/zyd9stmdlnlvv?zt=eyJhbGciOiJIUzI1NiJ9.eyJzdHJlYW0iOiJ6eWQ5c3RtZGxubHZ2IiwiaG9zdCI6InN0cmVhbS0xNjQuemVuby5mbSIsInRtIjpmYWxzZSwicnR0bCI6NSwianRpIjoicFRJUlBJTGlTMHlwQ3lXSzNCS2E3ZyIsImlhdCI6MTc2NDU1MTA3OCwiZXhwIjoxNzY0NTUxMTM4fQ.vduA8oOl5o-9p1cvMGxCaMfYWTQL4FhwT9vPWCWTlW8","homepage":"https://www.afrobeatsgospel.com/","favicon":"https://zeno.fm/_next/image/?url=https%3A%2F%2Fimages.zeno.fm%2FQQP3mGmsJ7eRVncsKMUkgNRs9dp4BsOgbjYSpFqWLZs%2Frs%3Afit%3A320%3A320%2Fg%3Ace%3A0%3A0%2FaHR0cHM6Ly96ZW5vaW1hZ2VzLnMzLnVzLXdlc3QtMDAxLmJhY2tibGF6ZWIyLmNvbS9kYmJlZWM3Yy1hZjBmLTQwYzMtOWUxYS1hMTMxYTM3ZmU2ZjEvY2FyZHMvZjAzZjc4NzgtNjk4MS00OTMyLWJiYzktZjU4NmI3MTRiNmIwP3U9NTc1OTE3OA.webp&w=1080&q=75","tags":"african,afrobeats,christian,gospel,inspirational","country":"Nigeria","countrycode":"NG","iso_3166_2":"","state":"Akwa Ibom State","language":"","languagecodes":"","votes":460,"lastchangetime":"2025-08-08 16:03:22","lastchangetime_iso8601":"2025-08-08T16:03:22Z","codec":"MP3","bitrate":0,"hls":0,"lastcheckok":1,"lastchecktime":"2025-12-01 01:04:49","lastchecktime_iso8601":"2025-12-01T01:04:49Z","lastcheckoktime":"2025-12-01 01:04:49","lastcheckoktime_iso8601":"2025-12-01T01:04:49Z","lastlocalchecktime":"2025-12-01 01:04:49","lastlocalchecktime_iso8601":"2025-12-01T01:04:49Z","clicktimestamp":"2025-12-01 09:06:10","clicktimestamp_iso8601":"2025-12-01T09:06:10Z","clickcount":56,"clicktrend":7,"ssl_error":0,"geo_lat":5.0275515138905185,"geo_long":7.927322387695313,"geo_distance":null,"has_extended_info":false},{"changeuuid":"30eb7926-73c0-4f9c-8536-30df897d2d56","stationuuid":"40507470-ace1-4637-8548-8173d9aaa3df","serveruuid":"3dbb0d9b-a0b7-4812-bd90-a653d160d670","name":"Air Gospel","url":"https://stream.zeno.fm/qkgrhugy908uv","url_resolved":"https://stream-179.zeno.fm/qkgrhugy908uv?zt=eyJhbGciOiJIUzI1NiJ9.eyJzdHJlYW0iOiJxa2dyaHVneTkwOHV2IiwiaG9zdCI6InN0cmVhbS0xNzkuemVuby5mbSIsInRtIjpmYWxzZSwicnR0bCI6NSwianRpIjoiN25BMXJHcURUZ202YnNtWTZKTTlmUSIsImlhdCI6MTc2NDU2Nzg4NywiZXhwIjoxNzY0NTY3OTQ3fQ.vMpCq0LEdJlPQTHbK_R39I3NZRaps1eSpotF-D6rE5Q","homepage":"https://airtv.world/","favicon":"https://drive.google.com/drive/u/0/my-drive","tags":"","country":"Nigeria","countrycode":"NG","iso_3166_2":"","state":"Lagos","language":"","languagecodes":"","votes":94,"lastchangetime":"2025-08-08 16:03:40","lastchangetime_iso8601":"2025-08-08T16:03:40Z","codec":"MP3","bitrate":0,"hls":0,"lastcheckok":1,"lastchecktime":"2025-12-01 05:51:53","lastchecktime_iso8601":"2025-12-01T05:51:53Z","lastcheckoktime":"2025-12-01 05:51:53","lastcheckoktime_iso8601":"2025-12-01T05:51:53Z","lastlocalchecktime":"2025-12-01 05:30:10","lastlocalchecktime_iso8601":"2025-12-01T05:30:10Z","clicktimestamp":"2025-12-01 07:44:21","clicktimestamp_iso8601":"2025-12-01T07:44:21Z","clickcount":15,"clicktrend":4,"ssl_error":0,"geo_lat":null,"geo_long":null,"geo_distance":null,"has_extended_info":false},{"changeuuid":"4d69df72-8916-4a72-9a6f-5dd98b38c473","stationuuid":"f4599800-804a-430d-b47a-534c54b79008","serveruuid":"3dbb0d9b-a0b7-4812-bd90-a653d160d670","name":"Air Radio","url":"https://stream.zeno.fm/xu7hp12tzv8uv","url_resolved":"https://stream-179.zeno.fm/xu7hp12tzv8uv?zt=eyJhbGciOiJIUzI1NiJ9.eyJzdHJlYW0iOiJ4dTdocDEydHp2OHV2IiwiaG9zdCI6InN0cmVhbS0xNzkuemVuby5mbSIsInRtIjpmYWxzZSwicnR0bCI6NSwianRpIjoiSlU1VGg2SHVTb1doRlZpellHY0tTQSIsImlhdCI6MTc2NDU0NjMwOCwiZXhwIjoxNzY0NTQ2MzY4fQ.CwFds9oT_nWGaqay88UaIjj3SSnluDRnU3xtcp8u-xM","homepage":"https://airtv.world/","favicon":"https://drive.google.com/drive/u/0/my-drive","tags":"","country":"Nigeria","countrycode":"NG","iso_3166_2":"","state":"Lagos","language":"","languagecodes":"","votes":67,"lastchangetime":"2025-08-08 16:03:40","lastchangetime_iso8601":"2025-08-08T16:03:40Z","codec":"MP3","bitrate":0,"hls":0,"lastcheckok":1,"lastchecktime":"2025-11-30 23:51:11","lastchecktime_iso8601":"2025-11-30T23:51:11Z","lastcheckoktime":"2025-11-30 23:51:11","lastcheckoktime_iso8601":"2025-11-30T23:51:11Z","lastlocalchecktime":"2025-11-30 13:11:05","lastlocalchecktime_iso8601":"2025-11-30T13:11:05Z","clicktimestamp":"2025-12-01 08:50:34","clicktimestamp_iso8601":"2025-12-01T08:50:34Z","clickcount":7,"clicktrend":2,"ssl_error":0,"geo_lat":null,"geo_long":null,"geo_distance":null,"has_extended_info":false},{"changeuuid":"5403738a-6055-4671-860d-b77f3dffe3fa","stationuuid":"811ce404-fde6-450c-ae31-21a762671f1c","serveruuid":"c58005cf-dba9-49e3-aa74-79442cdbe5ab","name":"Awoko Radio","url":"http://node-05.zeno.fm/tqq99en94v8uv","url_resolved":"http://stream-176.zeno.fm/tqq99en94v8uv?zt=eyJhbGciOiJIUzI1NiJ9.eyJzdHJlYW0iOiJ0cXE5OWVuOTR2OHV2IiwiaG9zdCI6InN0cmVhbS0xNzYuemVuby5mbSIsInRtIjpmYWxzZSwicnR0bCI6NSwianRpIjoiNjBHQXE0MFhTRldidXhWY1ljVG9hQSIsImlhdCI6MTc2NDUzOTc5NiwiZXhwIjoxNzY0NTM5ODU2fQ.kNBkuAnKJ-ry5XKmuN0IY6-k-fTxcM2WgDmHoT0QlcA","homepage":"https://liveonlineradio.net/awoko-radio","favicon":"https://cdn.onlineradiobox.com/img/l/6/90406.v10.png","tags":"african pop","country":"Nigeria","countrycode":"NG","iso_3166_2":"","state":"","language":"english","languagecodes":"en","votes":553,"lastchangetime":"2025-08-08 17:28:19","lastchangetime_iso8601":"2025-08-08T17:28:19Z","codec":"MP3","bitrate":0,"hls":0,"lastcheckok":1,"lastchecktime":"2025-11-30 21:56:49","lastchecktime_iso8601":"2025-11-30T21:56:49Z","lastcheckoktime":"2025-11-30 21:56:49","lastcheckoktime_iso8601":"2025-11-30T21:56:49Z","lastlocalchecktime":"2025-11-30 21:56:49","lastlocalchecktime_iso8601":"2025-11-30T21:56:49Z","clicktimestamp":"2025-12-01 05:18:31","clicktimestamp_iso8601":"2025-12-01T05:18:31Z","clickcount":18,"clicktrend":-1,"ssl_error":0,"geo_lat":null,"geo_long":null,"geo_distance":null,"has_extended_info":false},{"changeuuid":"78cf9d7e-f58c-4bdd-9587-767036bafd06","stationuuid":"d05e3e8b-241c-4672-be1a-90571135730d","serveruuid":"0dcca4d3-29b7-46c8-b471-4171032ac11c","name":"Blast 98.3 FM","url":"https://stream.zeno.fm/94a8u4h2uhhvv","url_resolved":"https://stream-151.zeno.fm/94a8u4h2uhhvv?zt=eyJhbGciOiJIUzI1NiJ9.eyJzdHJlYW0iOiI5NGE4dTRoMnVoaHZ2IiwiaG9zdCI6InN0cmVhbS0xNTEuemVuby5mbSIsInRtIjpmYWxzZSwicnR0bCI6NSwianRpIjoiX190enRlX0dTUjZYWjhYa0dEV0ROZyIsImlhdCI6MTc2NDU2OTQzOCwiZXhwIjoxNzY0NTY5NDk4fQ.d8IJRJS6N4zgayLZcUwJ3VhHjx0cSOBaJdJeQwLdlhE","homepage":"https://blasturban983fm.com/","favicon":"https://blasturban983fm.com/wp-content/uploads/2022/06/BlastFMSocial-removebg-preview.png","tags":"","country":"Nigeria","countrycode":"NG","iso_3166_2":"","state":"","language":"","languagecodes":"","votes":80,"lastchangetime":"2025-08-08 16:03:22","lastchangetime_iso8601":"2025-08-08T16:03:22Z","codec":"MP3","bitrate":0,"hls":0,"lastcheckok":1,"lastchecktime":"2025-12-01 06:18:47","lastchecktime_iso8601":"2025-12-01T06:18:47Z","lastcheckoktime":"2025-12-01 06:18:47","lastcheckoktime_iso8601":"2025-12-01T06:18:47Z","lastlocalchecktime":"2025-11-30 13:01:56","lastlocalchecktime_iso8601":"2025-11-30T13:01:56Z","clicktimestamp":"2025-12-01 08:51:00","clicktimestamp_iso8601":"2025-12-01T08:51:00Z","clickcount":21,"clicktrend":1,"ssl_error":0,"geo_lat":null,"geo_long":null,"geo_distance":null,"has_extended_info":false},{"changeuuid":"e73fabe1-8869-4777-985f-1ec236de3ce2","stationuuid":"fdfd32c3-7612-4d83-acf1-5f7f0bc887db","serveruuid":"63008a08-03dd-40b6-a592-454f7541a35c","name":"Bond 92.9 FM","url":"https://go.webgateready.com/bondfm","url_resolved":"https://go.webgateready.com/bondfm","homepage":"https://radionigerialagos.gov.ng/","favicon":"https://cdn-radiotime-logos.tunein.com/s297865q.png","tags":"","country":"Nigeria","countrycode":"NG","iso_3166_2":"","state":"Lagos","language":"","languagecodes":"","votes":622,"lastchangetime":"2025-08-08 16:03:20","lastchangetime_iso8601":"2025-08-08T16:03:20Z","codec":"MP3","bitrate":64,"hls":0,"lastcheckok":1,"lastchecktime":"2025-12-01 01:46:30","lastchecktime_iso8601":"2025-12-01T01:46:30Z","lastcheckoktime":"2025-12-01 01:46:30","lastcheckoktime_iso8601":"2025-12-01T01:46:30Z","lastlocalchecktime":"2025-11-30 10:55:23","lastlocalchecktime_iso8601":"2025-11-30T10:55:23Z","clicktimestamp":"2025-12-01 09:18:17","clicktimestamp_iso8601":"2025-12-01T09:18:17Z","clickcount":55,"clicktrend":5,"ssl_error":0,"geo_lat":null,"geo_long":null,"geo_distance":null,"has_extended_info":false},{"changeuuid":"ef83cfe5-4815-4e95-8836-017341d19548","stationuuid":"863f04a8-2a3b-4127-850a-d9c0056c2eab","serveruuid":"30b4a842-2a3b-4e65-929e-d7edfa71e15e","name":"BOSS 98.9 FM","url":"https://ec1.everestcast.host:4795/stream","url_resolved":"https://ec1.everestcast.host:4795/stream","homepage":"https://boss989fm.com/","favicon":"https://boss989fm.com/wp-content/uploads/2020/06/output-onlinepngtools1-1.png","tags":"","country":"Nigeria","countrycode":"NG","iso_3166_2":"","state":"","language":"","languagecodes":"","votes":186,"lastchangetime":"2025-08-08 16:03:19","lastchangetime_iso8601":"2025-08-08T16:03:19Z","codec":"MP3","bitrate":64,"hls":0,"lastcheckok":1,"lastchecktime":"2025-12-01 00:45:13","lastchecktime_iso8601":"2025-12-01T00:45:13Z","lastcheckoktime":"2025-12-01 00:45:13","lastcheckoktime_iso8601":"2025-12-01T00:45:13Z","lastlocalchecktime":"2025-12-01 00:45:13","lastlocalchecktime_iso8601":"2025-12-01T00:45:13Z","clicktimestamp":"2025-12-01 05:32:58","clicktimestamp_iso8601":"2025-12-01T05:32:58Z","clickcount":16,"clicktrend":1,"ssl_error":0,"geo_lat":null,"geo_long":null,"geo_distance":null,"has_extended_info":false},{"changeuuid":"3019e0dd-7e23-435a-82b9-23b28c536265","stationuuid":"a64b67e3-959a-421c-9bbc-35bef7fd8491","serveruuid":"abfdbef5-724c-43a7-9b63-30c0476005f6","name":"Domi Radio","url":"https://domimedia.org/stream","url_resolved":"https://domimedia.org/stream","homepage":"https://domimedia.org/#","favicon":"https://domimedia.org/images/icon.png","tags":"","country":"Nigeria","countrycode":"NG","iso_3166_2":"","state":"","language":"","languagecodes":"","votes":28,"lastchangetime":"2025-08-08 16:03:33","lastchangetime_iso8601":"2025-08-08T16:03:33Z","codec":"AAC+","bitrate":128,"hls":0,"lastcheckok":1,"lastchecktime":"2025-12-01 00:11:44","lastchecktime_iso8601":"2025-12-01T00:11:44Z","lastcheckoktime":"2025-12-01 00:11:44","lastcheckoktime_iso8601":"2025-12-01T00:11:44Z","lastlocalchecktime":"2025-11-30 20:13:55","lastlocalchecktime_iso8601":"2025-11-30T20:13:55Z","clicktimestamp":"2025-12-01 07:42:07","clicktimestamp_iso8601":"2025-12-01T07:42:07Z","clickcount":11,"clicktrend":1,"ssl_error":0,"geo_lat":null,"geo_long":null,"geo_distance":null,"has_extended_info":false},{"changeuuid":"bb73039b-9664-4208-b525-bf3530033bfc","stationuuid":"f75104b7-6c7a-4b52-87cf-1e999388371e","serveruuid":"af8ab69f-9d42-425c-8fd9-008747e41ed7","name":"Dream Center Internet Radio","url":"https://admin.dciradio.org/radio/8010/radio.mp3","url_resolved":"https://admin.dciradio.org/radio/8010/radio.mp3","homepage":"https://www.dciradio.org/","favicon":"https://www.dciradio.org/favicon.ico","tags":"","country":"Nigeria","countrycode":"NG","iso_3166_2":"","state":"","language":"","languagecodes":"","votes":111,"lastchangetime":"2025-08-08 16:03:20","lastchangetime_iso8601":"2025-08-08T16:03:20Z","codec":"MP3","bitrate":128,"hls":0,"lastcheckok":1,"lastchecktime":"2025-12-01 00:16:46","lastchecktime_iso8601":"2025-12-01T00:16:46Z","lastcheckoktime":"2025-12-01 00:16:46","lastcheckoktime_iso8601":"2025-12-01T00:16:46Z","lastlocalchecktime":"2025-11-30 14:05:28","lastlocalchecktime_iso8601":"2025-11-30T14:05:28Z","clicktimestamp":"2025-11-30 15:59:35","clicktimestamp_iso8601":"2025-11-30T15:59:35Z","clickcount":5,"clicktrend":1,"ssl_error":0,"geo_lat":null,"geo_long":null,"geo_distance":null,"has_extended_info":false},{"changeuuid":"29146241-d567-41c1-90ba-752ec0b97570","stationuuid":"565f011e-68d3-4221-8fb2-b73e9e0d555e","serveruuid":"86e58ee9-152a-4ee9-92bc-1b5a238564f2","name":"Enyimba FM","url":"https://ec1.everestcast.host:4625/stream","url_resolved":"https://ec1.everestcast.host:4625/stream","homepage":"https://enyinba.com/","favicon":"https://oyster-app-tzdpj.ondigitalocean.app/public/uploads/stations/enyimbalogo.png","tags":"","country":"Nigeria","countrycode":"NG","iso_3166_2":"","state":"","language":"","languagecodes":"","votes":243,"lastchangetime":"2025-08-08 16:03:19","lastchangetime_iso8601":"2025-08-08T16:03:19Z","codec":"MP3","bitrate":64,"hls":0,"lastcheckok":1,"lastchecktime":"2025-11-30 14:23:42","lastchecktime_iso8601":"2025-11-30T14:23:42Z","lastcheckoktime":"2025-11-30 14:23:42","lastcheckoktime_iso8601":"2025-11-30T14:23:42Z","lastlocalchecktime":"2025-11-30 12:31:20","lastlocalchecktime_iso8601":"2025-11-30T12:31:20Z","clicktimestamp":"2025-12-01 07:43:49","clicktimestamp_iso8601":"2025-12-01T07:43:49Z","clickcount":5,"clicktrend":1,"ssl_error":0,"geo_lat":null,"geo_long":null,"geo_distance":null,"has_extended_info":false},{"changeuuid":"547de876-9450-4ff4-af9a-b93fa21e5c46","stationuuid":"6a9bc3b3-dc02-4d48-8926-e6a2ff8af42c","serveruuid":"70fbfe95-2a32-4b1d-a10f-7d8adcbd02c4","name":"FAD FM","url":"https://radio.gotright.net/listen/fadfm/radio.mp3","url_resolved":"https://radio.gotright.net/listen/fadfm/radio.mp3","homepage":"https://fadfm.com/","favicon":"https://fadfm.com/wp-content/uploads/2023/02/fadfm_logo-removebg-preview.png","tags":"","country":"Nigeria","countrycode":"NG","iso_3166_2":"","state":"","language":"","languagecodes":"","votes":75,"lastchangetime":"2025-08-08 16:03:33","lastchangetime_iso8601":"2025-08-08T16:03:33Z","codec":"MP3","bitrate":128,"hls":0,"lastcheckok":1,"lastchecktime":"2025-12-01 04:40:47","lastchecktime_iso8601":"2025-12-01T04:40:47Z","lastcheckoktime":"2025-12-01 04:40:47","lastcheckoktime_iso8601":"2025-12-01T04:40:47Z","lastlocalchecktime":"2025-12-01 01:50:05","lastlocalchecktime_iso8601":"2025-12-01T01:50:05Z","clicktimestamp":"2025-11-29 15:13:46","clicktimestamp_iso8601":"2025-11-29T15:13:46Z","clickcount":2,"clicktrend":-1,"ssl_error":0,"geo_lat":null,"geo_long":null,"geo_distance":null,"has_extended_info":false},{"changeuuid":"cf59b1c4-81c7-4587-95bd-5b81d1caf768","stationuuid":"f4f247ba-7614-42a8-9763-c0a11012d344","serveruuid":"1ae36511-bec8-48f5-896a-7e1d7f3bc2e6","name":"Fahimta Radio","url":"https://cutt.ly/v49jJkV","url_resolved":"https://stream-176.zeno.fm/x6vurqw6508uv?zt=eyJhbGciOiJIUzI1NiJ9.eyJzdHJlYW0iOiJ4NnZ1cnF3NjUwOHV2IiwiaG9zdCI6InN0cmVhbS0xNzYuemVuby5mbSIsInRtIjpmYWxzZSwicnR0bCI6NSwianRpIjoiSDFBeWd4SG9TbnVPcUgtZFZ1dm1mUSIsImlhdCI6MTc2NDU3Mzc0OCwiZXhwIjoxNzY0NTczODA4fQ.PSywOhK0LL6qB4wI7tvUy1wLiSMaPVuMZzkMxdrgzSU","homepage":"https://abdultech.co/","favicon":"","tags":"bauchi,fahimta,naija,ng,nigeria,online radio","country":"Nigeria","countrycode":"NG","iso_3166_2":"","state":"","language":"english,hausa","languagecodes":"en,ha","votes":350,"lastchangetime":"2025-08-09 06:20:17","lastchangetime_iso8601":"2025-08-09T06:20:17Z","codec":"MP3","bitrate":0,"hls":0,"lastcheckok":1,"lastchecktime":"2025-12-01 07:22:45","lastchecktime_iso8601":"2025-12-01T07:22:45Z","lastcheckoktime":"2025-12-01 07:22:45","lastcheckoktime_iso8601":"2025-12-01T07:22:45Z","lastlocalchecktime":"2025-12-01 07:22:45","lastlocalchecktime_iso8601":"2025-12-01T07:22:45Z","clicktimestamp":"2025-12-01 05:25:14","clicktimestamp_iso8601":"2025-12-01T05:25:14Z","clickcount":9,"clicktrend":2,"ssl_error":0,"geo_lat":null,"geo_long":null,"geo_distance":null,"has_extended_info":false},{"changeuuid":"823ef85c-b280-41f8-b986-3c85aa5ea7f2","stationuuid":"15392242-57a0-4e31-9e2d-71859675caf8","serveruuid":"58a3e16f-7cb5-497e-8724-e4f73e1bc0ef","name":"GanGan Radio","url":"https://stream.zeno.fm/9reuhyz8up8uv","url_resolved":"https://stream-176.zeno.fm/9reuhyz8up8uv?zt=eyJhbGciOiJIUzI1NiJ9.eyJzdHJlYW0iOiI5cmV1aHl6OHVwOHV2IiwiaG9zdCI6InN0cmVhbS0xNzYuemVuby5mbSIsInRtIjpmYWxzZSwicnR0bCI6NSwianRpIjoiVzk5dzB1cjVTcDJaVUVoVWRXVzZ5dyIsImlhdCI6MTc2NDU2NDc2MCwiZXhwIjoxNzY0NTY0ODIwfQ.NAnsMJIXWAmDbolOgmnPkQpFOUU_p1zKM0xn7LwATAo","homepage":"https://liveonlineradio.net/gangan-radio","favicon":"https://cdn.onlineradiobox.com/img/l/5/100965.v3.png","tags":"african music,traditional","country":"Nigeria","countrycode":"NG","iso_3166_2":"","state":"","language":"africa,english","languagecodes":"en","votes":539,"lastchangetime":"2025-08-09 08:43:25","lastchangetime_iso8601":"2025-08-09T08:43:25Z","codec":"MP3","bitrate":0,"hls":0,"lastcheckok":1,"lastchecktime":"2025-12-01 04:58:26","lastchecktime_iso8601":"2025-12-01T04:58:26Z","lastcheckoktime":"2025-12-01 04:58:26","lastcheckoktime_iso8601":"2025-12-01T04:58:26Z","lastlocalchecktime":"2025-11-30 17:34:20","lastlocalchecktime_iso8601":"2025-11-30T17:34:20Z","clicktimestamp":"2025-12-01 05:20:08","clicktimestamp_iso8601":"2025-12-01T05:20:08Z","clickcount":12,"clicktrend":1,"ssl_error":0,"geo_lat":null,"geo_long":null,"geo_distance":null,"has_extended_info":false},{"changeuuid":"6f81a55f-21d6-4f7f-8bdb-8b407bbede5b","stationuuid":"4494646d-b2f4-4243-b4ff-8aa14f24b885","serveruuid":"e4e00f57-0ae4-4d6c-ae7c-ab98593391f4","name":"Godfrey Okoye University Radio 106.9fm","url":"https://us5new.listen2myradio.com:2199/stream.php?port=8178","url_resolved":"https://us5new.listen2myradio.com:2199/stream.php?port=8178","homepage":"https://1069gouniradio.com/","favicon":"","tags":"","country":"Nigeria","countrycode":"NG","iso_3166_2":"","state":"Enugu","language":"","languagecodes":"","votes":84,"lastchangetime":"2025-08-08 16:03:19","lastchangetime_iso8601":"2025-08-08T16:03:19Z","codec":"MP3","bitrate":0,"hls":0,"lastcheckok":1,"lastchecktime":"2025-12-01 06:18:47","lastchecktime_iso8601":"2025-12-01T06:18:47Z","lastcheckoktime":"2025-12-01 06:18:47","lastcheckoktime_iso8601":"2025-12-01T06:18:47Z","lastlocalchecktime":"2025-11-30 13:56:03","lastlocalchecktime_iso8601":"2025-11-30T13:56:03Z","clicktimestamp":"2025-11-28 14:01:54","clicktimestamp_iso8601":"2025-11-28T14:01:54Z","clickcount":1,"clicktrend":0,"ssl_error":0,"geo_lat":null,"geo_long":null,"geo_distance":null,"has_extended_info":false},{"changeuuid":"ef3a7e35-c723-44d9-8327-e56175e645e7","stationuuid":"aed5c72c-7f47-406e-9154-177c6968252a","serveruuid":"70fbfe95-2a32-4b1d-a10f-7d8adcbd02c4","name":"Gospotainment Radio","url":"https://radio.gotright.net/radio/8000/radio.mp3","url_resolved":"https://radio.gotright.net/radio/8000/radio.mp3","homepage":"https://gospotainment.com/","favicon":"","tags":"afrobeats,christian,christian contemporary,christian praise&worship,gospel,gospel music","country":"Nigeria","countrycode":"NG","iso_3166_2":"","state":"","language":"","languagecodes":"","votes":1054,"lastchangetime":"2025-08-08 16:03:21","lastchangetime_iso8601":"2025-08-08T16:03:21Z","codec":"MP3","bitrate":128,"hls":0,"lastcheckok":1,"lastchecktime":"2025-11-30 21:42:53","lastchecktime_iso8601":"2025-11-30T21:42:53Z","lastcheckoktime":"2025-11-30 21:42:53","lastcheckoktime_iso8601":"2025-11-30T21:42:53Z","lastlocalchecktime":"2025-11-30 10:44:34","lastlocalchecktime_iso8601":"2025-11-30T10:44:34Z","clicktimestamp":"2025-12-01 05:52:23","clicktimestamp_iso8601":"2025-12-01T05:52:23Z","clickcount":7,"clicktrend":2,"ssl_error":0,"geo_lat":null,"geo_long":null,"geo_distance":null,"has_extended_info":false},{"changeuuid":"42f4ca6d-5b54-4bce-ac5b-2b4aebcac204","stationuuid":"2c30d91f-29a2-4a24-99bb-e56fd02e84c5","serveruuid":"3ee35cb2-965c-46b4-ae9f-16939b47db87","name":"Green Radio Uganda","url":"https://servidor17-1.brlogic.com:7940/live?source=12124","url_resolved":"https://servidor17-1.brlogic.com:7940/live?source=12124","homepage":"https://greenradionigeria.com/","favicon":"https://greenradionigeria.com/wp-content/uploads/2022/04/greenlogo.png","tags":"","country":"Nigeria","countrycode":"NG","iso_3166_2":"","state":"","language":"","languagecodes":"","votes":138,"lastchangetime":"2025-08-08 16:03:19","lastchangetime_iso8601":"2025-08-08T16:03:19Z","codec":"MP3","bitrate":128,"hls":0,"lastcheckok":1,"lastchecktime":"2025-12-01 00:50:22","lastchecktime_iso8601":"2025-12-01T00:50:22Z","lastcheckoktime":"2025-12-01 00:50:22","lastcheckoktime_iso8601":"2025-12-01T00:50:22Z","lastlocalchecktime":"2025-11-30 20:06:13","lastlocalchecktime_iso8601":"2025-11-30T20:06:13Z","clicktimestamp":"2025-11-30 09:54:52","clicktimestamp_iso8601":"2025-11-30T09:54:52Z","clickcount":3,"clicktrend":1,"ssl_error":0,"geo_lat":null,"geo_long":null,"geo_distance":null,"has_extended_info":false},{"changeuuid":"9e251379-1f86-4266-ba12-475a1dab1c49","stationuuid":"619071c3-ee44-4d44-9f19-a7f7b400d78e","serveruuid":"68582f1a-f428-4181-bc75-c71c307c1d78","name":"HOD RADIO","url":"https://servidor21.brlogic.com:7766/live","url_resolved":"https://servidor21.brlogic.com:7766/live","homepage":"https://hodradio.webradiosite.com/","favicon":"https://www.facebook.com/hodradio","tags":"","country":"Nigeria","countrycode":"NG","iso_3166_2":"","state":"Edo State","language":"","languagecodes":"","votes":138,"lastchangetime":"2025-08-08 16:03:18","lastchangetime_iso8601":"2025-08-08T16:03:18Z","codec":"MP3","bitrate":96,"hls":0,"lastcheckok":1,"lastchecktime":"2025-12-01 09:09:34","lastchecktime_iso8601":"2025-12-01T09:09:34Z","lastcheckoktime":"2025-12-01 09:09:34","lastcheckoktime_iso8601":"2025-12-01T09:09:34Z","lastlocalchecktime":"2025-12-01 09:09:34","lastlocalchecktime_iso8601":"2025-12-01T09:09:34Z","clicktimestamp":"2025-12-01 05:39:03","clicktimestamp_iso8601":"2025-12-01T05:39:03Z","clickcount":2,"clicktrend":1,"ssl_error":0,"geo_lat":null,"geo_long":null,"geo_distance":null,"has_extended_info":false},{"changeuuid":"5349d48d-cd91-43cd-941e-cc511302e5ba","stationuuid":"0f09d0aa-7233-42f2-82cb-1af9697f0198","serveruuid":"68582f1a-f428-4181-bc75-c71c307c1d78","name":"HOD RADIO","url":"https://servidor21.brlogic.com:7766/live","url_resolved":"https://servidor21.brlogic.com:7766/live","homepage":"https://hodradio.webradiosite.com/","favicon":"","tags":"","country":"Nigeria","countrycode":"NG","iso_3166_2":"","state":"Edo state","language":"","languagecodes":"","votes":442,"lastchangetime":"2025-08-08 16:03:18","lastchangetime_iso8601":"2025-08-08T16:03:18Z","codec":"MP3","bitrate":96,"hls":0,"lastcheckok":1,"lastchecktime":"2025-12-01 05:57:15","lastchecktime_iso8601":"2025-12-01T05:57:15Z","lastcheckoktime":"2025-12-01 05:57:15","lastcheckoktime_iso8601":"2025-12-01T05:57:15Z","lastlocalchecktime":"2025-11-30 23:15:48","lastlocalchecktime_iso8601":"2025-11-30T23:15:48Z","clicktimestamp":"2025-11-29 22:14:33","clicktimestamp_iso8601":"2025-11-29T22:14:33Z","clickcount":1,"clicktrend":-1,"ssl_error":0,"geo_lat":null,"geo_long":null,"geo_distance":null,"has_extended_info":false},{"changeuuid":"d7bd3214-a88a-400a-aff9-be22cec698b1","stationuuid":"cdd20cd2-2871-4bd7-9e0f-cd0720064865","serveruuid":"3dbb0d9b-a0b7-4812-bd90-a653d160d670","name":"Inform Me Radio","url":"http://stream.zeno.fm/ta1fke6sz1zuv","url_resolved":"https://stream-176.zeno.fm/ta1fke6sz1zuv?zt=eyJhbGciOiJIUzI1NiJ9.eyJzdHJlYW0iOiJ0YTFma2U2c3oxenV2IiwiaG9zdCI6InN0cmVhbS0xNzYuemVuby5mbSIsInRtIjpmYWxzZSwicnR0bCI6NSwianRpIjoieEZSYndSbHJURDJTd2trcnBTNUZEUSIsImlhdCI6MTc2NDU3ODI1NywiZXhwIjoxNzY0NTc4MzE3fQ.PY_DxycKSlB3TWJq0olGEDsCBvr6Y5FH704avL4MP4s","homepage":"https://www.informmeradio.com/","favicon":"","tags":"business programs,family,farming,news,relationship,talk","country":"Nigeria","countrycode":"NG","iso_3166_2":"","state":"Edo","language":"english","languagecodes":"en","votes":1360,"lastchangetime":"2025-08-08 22:58:00","lastchangetime_iso8601":"2025-08-08T22:58:00Z","codec":"MP3","bitrate":0,"hls":0,"lastcheckok":1,"lastchecktime":"2025-12-01 08:42:15","lastchecktime_iso8601":"2025-12-01T08:42:15Z","lastcheckoktime":"2025-12-01 08:42:15","lastcheckoktime_iso8601":"2025-12-01T08:42:15Z","lastlocalchecktime":"2025-12-01 05:40:51","lastlocalchecktime_iso8601":"2025-12-01T05:40:51Z","clicktimestamp":"2025-12-01 09:01:55","clicktimestamp_iso8601":"2025-12-01T09:01:55Z","clickcount":11,"clicktrend":3,"ssl_error":0,"geo_lat":null,"geo_long":null,"geo_distance":null,"has_extended_info":false},{"changeuuid":"f666459f-a484-451d-ad94-ecdfc606cfef","stationuuid":"136df879-9acd-4281-9723-36c73ccbe738","serveruuid":"70fbfe95-2a32-4b1d-a10f-7d8adcbd02c4","name":"KCity Radio","url":"https://radio.gotright.net/radio/8010/radio.mp3","url_resolved":"https://radio.gotright.net/radio/8010/radio.mp3","homepage":"https://kcityradio.com/","favicon":"","tags":"misc","country":"Nigeria","countrycode":"NG","iso_3166_2":"","state":"Abuja","language":"english","languagecodes":"en","votes":87,"lastchangetime":"2025-08-09 08:40:34","lastchangetime_iso8601":"2025-08-09T08:40:34Z","codec":"MP3","bitrate":128,"hls":0,"lastcheckok":1,"lastchecktime":"2025-12-01 05:57:15","lastchecktime_iso8601":"2025-12-01T05:57:15Z","lastcheckoktime":"2025-12-01 05:57:15","lastcheckoktime_iso8601":"2025-12-01T05:57:15Z","lastlocalchecktime":"2025-11-30 17:05:12","lastlocalchecktime_iso8601":"2025-11-30T17:05:12Z","clicktimestamp":"2025-11-30 21:29:41","clicktimestamp_iso8601":"2025-11-30T21:29:41Z","clickcount":4,"clicktrend":3,"ssl_error":0,"geo_lat":null,"geo_long":null,"geo_distance":null,"has_extended_info":false},{"changeuuid":"e73a63eb-0c64-4f5f-8a65-380781b02e49","stationuuid":"72514d03-46b6-44bb-9fa7-fda2c3b83180","serveruuid":"48dd579c-17f6-4c99-a9f9-d347287b4380","name":"Konga103.7FM","url":"https://lunar.citrus3.com:8124/stream","url_resolved":"https://lunar.citrus3.com:8124/stream","homepage":"https://kongafm.com/","favicon":"https://kongafm.com/logo.svg","tags":"","country":"Nigeria","countrycode":"NG","iso_3166_2":"","state":"Lagos","language":"english","languagecodes":"en","votes":28,"lastchangetime":"2025-08-09 01:08:01","lastchangetime_iso8601":"2025-08-09T01:08:01Z","codec":"MP3","bitrate":96,"hls":0,"lastcheckok":1,"lastchecktime":"2025-12-01 07:32:44","lastchecktime_iso8601":"2025-12-01T07:32:44Z","lastcheckoktime":"2025-12-01 07:32:44","lastcheckoktime_iso8601":"2025-12-01T07:32:44Z","lastlocalchecktime":"2025-12-01 06:31:57","lastlocalchecktime_iso8601":"2025-12-01T06:31:57Z","clicktimestamp":"2025-12-01 05:35:00","clicktimestamp_iso8601":"2025-12-01T05:35:00Z","clickcount":6,"clicktrend":1,"ssl_error":0,"geo_lat":null,"geo_long":null,"geo_distance":null,"has_extended_info":false},{"changeuuid":"e577ce75-6f4c-4390-bbdb-e988d4589ea8","stationuuid":"f835db87-94b4-4256-a893-b8194316df3f","serveruuid":"48dd579c-17f6-4c99-a9f9-d347287b4380","name":"Konga103.7FM","url":"https://lunar.citrus3.com:8124/stream","url_resolved":"https://lunar.citrus3.com:8124/stream","homepage":"https://kongafm.com/","favicon":"https://kongafm.com/logo.svg","tags":"business,commerce,hits,inspiration,music","country":"Nigeria","countrycode":"NG","iso_3166_2":"","state":"Lagos","language":"english","languagecodes":"en","votes":44,"lastchangetime":"2025-08-09 09:05:31","lastchangetime_iso8601":"2025-08-09T09:05:31Z","codec":"MP3","bitrate":96,"hls":0,"lastcheckok":1,"lastchecktime":"2025-11-30 16:08:39","lastchecktime_iso8601":"2025-11-30T16:08:39Z","lastcheckoktime":"2025-11-30 16:08:39","lastcheckoktime_iso8601":"2025-11-30T16:08:39Z","lastlocalchecktime":"2025-11-30 16:08:39","lastlocalchecktime_iso8601":"2025-11-30T16:08:39Z","clicktimestamp":"2025-12-01 08:51:21","clicktimestamp_iso8601":"2025-12-01T08:51:21Z","clickcount":7,"clicktrend":3,"ssl_error":0,"geo_lat":6.5515029758095675,"geo_long":3.3779928088188176,"geo_distance":null,"has_extended_info":false},{"changeuuid":"f15a85ca-1d9d-4d4f-ba77-98b5750c838a","stationuuid":"3c8dd994-143a-444d-95da-1a8ba41fce16","serveruuid":"1bdd504f-70b1-49e3-aaa0-abfcea2595e4","name":"LagosJump Radio","url":"https://radio.lagosjumpradio.com/listen/lagosjump_radio/radio.mp3","url_resolved":"https://radio.lagosjumpradio.com/listen/lagosjump_radio/radio.mp3","homepage":"https://www.lagosjumpradio.com/","favicon":"","tags":"afrobeats","country":"Nigeria","countrycode":"NG","iso_3166_2":"","state":"Abuja","language":"english","languagecodes":"en","votes":314,"lastchangetime":"2025-08-09 00:01:32","lastchangetime_iso8601":"2025-08-09T00:01:32Z","codec":"MP3","bitrate":192,"hls":0,"lastcheckok":1,"lastchecktime":"2025-12-01 06:29:03","lastchecktime_iso8601":"2025-12-01T06:29:03Z","lastcheckoktime":"2025-12-01 06:29:03","lastcheckoktime_iso8601":"2025-12-01T06:29:03Z","lastlocalchecktime":"2025-12-01 06:29:03","lastlocalchecktime_iso8601":"2025-12-01T06:29:03Z","clicktimestamp":"2025-12-01 05:19:10","clicktimestamp_iso8601":"2025-12-01T05:19:10Z","clickcount":16,"clicktrend":2,"ssl_error":0,"geo_lat":null,"geo_long":null,"geo_distance":null,"has_extended_info":false},{"changeuuid":"4276b45f-bae4-439e-923d-a0113b04a466","stationuuid":"a56d44d8-1d60-4acf-a80f-5be05636d420","serveruuid":"d50d0995-cf3d-4cd0-855b-07b4be03f7d4","name":"Legend FM","url":"https://ec1.everestcast.host:4815/stream","url_resolved":"https://ec1.everestcast.host:4815/stream","homepage":"https://legend.enyinba.com/","favicon":"https://oyster-app-tzdpj.ondigitalocean.app/public/uploads/stations/logole.png","tags":"","country":"Nigeria","countrycode":"NG","iso_3166_2":"","state":"","language":"","languagecodes":"","votes":133,"lastchangetime":"2025-08-08 16:03:19","lastchangetime_iso8601":"2025-08-08T16:03:19Z","codec":"MP3","bitrate":64,"hls":0,"lastcheckok":1,"lastchecktime":"2025-12-01 06:53:52","lastchecktime_iso8601":"2025-12-01T06:53:52Z","lastcheckoktime":"2025-12-01 06:53:52","lastcheckoktime_iso8601":"2025-12-01T06:53:52Z","lastlocalchecktime":"2025-11-30 21:16:17","lastlocalchecktime_iso8601":"2025-11-30T21:16:17Z","clicktimestamp":"2025-12-01 05:25:52","clicktimestamp_iso8601":"2025-12-01T05:25:52Z","clickcount":9,"clicktrend":-3,"ssl_error":0,"geo_lat":null,"geo_long":null,"geo_distance":null,"has_extended_info":false},{"changeuuid":"6a68207b-47b9-43d6-a080-d2877193904f","stationuuid":"1da93dc5-365a-49b9-8fa8-67a8ce5668f8","serveruuid":"1d921a2b-b34c-4c4c-aebb-d44237e8c510","name":"MajorFM","url":"http://stream.zeno.fm/pkza99xshkhvv","url_resolved":"http://stream-178.zeno.fm/pkza99xshkhvv?zt=eyJhbGciOiJIUzI1NiJ9.eyJzdHJlYW0iOiJwa3phOTl4c2hraHZ2IiwiaG9zdCI6InN0cmVhbS0xNzguemVuby5mbSIsInRtIjpmYWxzZSwicnR0bCI6NSwianRpIjoiMjl6bnU2WXRUZGVRNktGUkdFQjhEUSIsImlhdCI6MTc2NDU2Nzk4MSwiZXhwIjoxNzY0NTY4MDQxfQ.YvvcDYfI8BcndwsO9Q7NJyVTVhN2WgceGQks4ZL961M","homepage":"https://zeno.fm/radio/major-fm/","favicon":"https://zeno.fm/favicon.ico","tags":"80s,dj mixes,electro,hiphop,jazz,lounge,mix,r&b,smooth jazz","country":"Nigeria","countrycode":"NG","iso_3166_2":"","state":"Lagos","language":"africa,english,ghana,usa","languagecodes":"en","votes":1608,"lastchangetime":"2025-08-09 06:46:08","lastchangetime_iso8601":"2025-08-09T06:46:08Z","codec":"MP3","bitrate":0,"hls":0,"lastcheckok":1,"lastchecktime":"2025-12-01 05:51:53","lastchecktime_iso8601":"2025-12-01T05:51:53Z","lastcheckoktime":"2025-12-01 05:51:53","lastcheckoktime_iso8601":"2025-12-01T05:51:53Z","lastlocalchecktime":"2025-12-01 01:17:54","lastlocalchecktime_iso8601":"2025-12-01T01:17:54Z","clicktimestamp":"2025-12-01 08:24:13","clicktimestamp_iso8601":"2025-12-01T08:24:13Z","clickcount":15,"clicktrend":0,"ssl_error":0,"geo_lat":6.500050180123714,"geo_long":3.3769393269335706,"geo_distance":null,"has_extended_info":false},{"changeuuid":"eac9dcb4-e268-42f5-af92-c73581752b30","stationuuid":"0b533a72-250a-4bc9-b692-25b6fdc1acd7","serveruuid":"3dbb0d9b-a0b7-4812-bd90-a653d160d670","name":"Map Radio ","url":"https://stream.zeno.fm/dgepldrdjv9vv","url_resolved":"https://stream-176.zeno.fm/dgepldrdjv9vv?zt=eyJhbGciOiJIUzI1NiJ9.eyJzdHJlYW0iOiJkZ2VwbGRyZGp2OXZ2IiwiaG9zdCI6InN0cmVhbS0xNzYuemVuby5mbSIsInRtIjpmYWxzZSwicnR0bCI6NSwianRpIjoiRURTNEVmMFFTei1mZ0VBUVRKY0lJZyIsImlhdCI6MTc2NDU3NDEwMSwiZXhwIjoxNzY0NTc0MTYxfQ.MSA0p4TpZg9euzvBxZBf0sjBhGzeyC17RTTP0jWV3bY","homepage":"https://stream.zeno.fm/dgepldrdjv9vv","favicon":"https://stream.zeno.fm/dgepldrdjv9vv","tags":"livestream,news,talk","country":"Nigeria","countrycode":"NG","iso_3166_2":"","state":"Niger Minna ","language":"arabic,english,hausa","languagecodes":"ar,en,ha","votes":29,"lastchangetime":"2025-08-09 01:08:39","lastchangetime_iso8601":"2025-08-09T01:08:39Z","codec":"MP3","bitrate":0,"hls":0,"lastcheckok":1,"lastchecktime":"2025-12-01 07:28:35","lastchecktime_iso8601":"2025-12-01T07:28:35Z","lastcheckoktime":"2025-12-01 07:28:35","lastcheckoktime_iso8601":"2025-12-01T07:28:35Z","lastlocalchecktime":"2025-12-01 07:28:35","lastlocalchecktime_iso8601":"2025-12-01T07:28:35Z","clicktimestamp":"2025-12-01 05:25:44","clicktimestamp_iso8601":"2025-12-01T05:25:44Z","clickcount":6,"clicktrend":1,"ssl_error":0,"geo_lat":null,"geo_long":null,"geo_distance":null,"has_extended_info":false},{"changeuuid":"8b77e862-b075-4c94-8485-e8eedf4e0dbc","stationuuid":"050bccf6-2ca8-41f9-ad89-66d035c8b779","serveruuid":"63008a08-03dd-40b6-a592-454f7541a35c","name":"Metro 97.7 FM","url":"https://go.webgateready.com/metrofm","url_resolved":"https://go.webgateready.com/metrofm","homepage":"https://radionigerialagos.gov.ng/metrofm","favicon":"https://radionigerialagos.gov.ng/metrofm/wp-content/uploads/2019/02/met.png","tags":"","country":"Nigeria","countrycode":"NG","iso_3166_2":"","state":"Lagos","language":"","languagecodes":"","votes":170,"lastchangetime":"2025-08-08 16:03:22","lastchangetime_iso8601":"2025-08-08T16:03:22Z","codec":"MP3","bitrate":64,"hls":0,"lastcheckok":1,"lastchecktime":"2025-12-01 07:38:34","lastchecktime_iso8601":"2025-12-01T07:38:34Z","lastcheckoktime":"2025-12-01 07:38:34","lastcheckoktime_iso8601":"2025-12-01T07:38:34Z","lastlocalchecktime":"2025-12-01 04:15:46","lastlocalchecktime_iso8601":"2025-12-01T04:15:46Z","clicktimestamp":"2025-12-01 05:48:50","clicktimestamp_iso8601":"2025-12-01T05:48:50Z","clickcount":17,"clicktrend":2,"ssl_error":0,"geo_lat":null,"geo_long":null,"geo_distance":null,"has_extended_info":false},{"changeuuid":"816f9d69-0f0b-467c-aa31-869bd9abbf44","stationuuid":"dc3c6b97-8f2d-42ba-94b3-effc96dcb49f","serveruuid":"63008a08-03dd-40b6-a592-454f7541a35c","name":"METRO FM LAGOS","url":"https://go.webgateready.com/metrofm/radio.mp3","url_resolved":"https://go.webgateready.com/metrofm/radio.mp3","homepage":"https://go.webgateready.com/metrofm/radio.mp3","favicon":"","tags":"","country":"Nigeria","countrycode":"NG","iso_3166_2":"","state":"","language":"english","languagecodes":"en","votes":1741,"lastchangetime":"2025-08-09 03:07:41","lastchangetime_iso8601":"2025-08-09T03:07:41Z","codec":"MP3","bitrate":64,"hls":0,"lastcheckok":1,"lastchecktime":"2025-12-01 08:54:29","lastchecktime_iso8601":"2025-12-01T08:54:29Z","lastcheckoktime":"2025-12-01 08:54:29","lastcheckoktime_iso8601":"2025-12-01T08:54:29Z","lastlocalchecktime":"2025-12-01 08:54:29","lastlocalchecktime_iso8601":"2025-12-01T08:54:29Z","clicktimestamp":"2025-12-01 08:43:02","clicktimestamp_iso8601":"2025-12-01T08:43:02Z","clickcount":32,"clicktrend":1,"ssl_error":0,"geo_lat":null,"geo_long":null,"geo_distance":null,"has_extended_info":false},{"changeuuid":"0cfe5dd4-c4b5-4671-bf2c-c51095239581","stationuuid":"ce2dc22e-3dc0-450a-805c-63f43bd9dd54","serveruuid":"1d921a2b-b34c-4c4c-aebb-d44237e8c510","name":"Nagari Radio","url":"http://stream.zeno.fm/287z97ksdg8uv","url_resolved":"http://stream-178.zeno.fm/287z97ksdg8uv?zt=eyJhbGciOiJIUzI1NiJ9.eyJzdHJlYW0iOiIyODd6OTdrc2RnOHV2IiwiaG9zdCI6InN0cmVhbS0xNzguemVuby5mbSIsInRtIjpmYWxzZSwicnR0bCI6NSwianRpIjoibm01S0lieDdSNldqMTZobnM5dzBOdyIsImlhdCI6MTc2NDU3MzUwNiwiZXhwIjoxNzY0NTczNTY2fQ.e4agI2hL8AnrQrRP8RrBnptRw8_VcSJPF8JwQbBt6gM","homepage":"http://stream.zeno.fm/287z97ksdg8uv","favicon":"","tags":"http://stream.zeno.fm/287z97ksdg8uv","country":"Nigeria","countrycode":"NG","iso_3166_2":"","state":"","language":"hausa l","languagecodes":"","votes":970,"lastchangetime":"2025-08-08 16:03:18","lastchangetime_iso8601":"2025-08-08T16:03:18Z","codec":"MP3","bitrate":0,"hls":0,"lastcheckok":1,"lastchecktime":"2025-12-01 07:22:22","lastchecktime_iso8601":"2025-12-01T07:22:22Z","lastcheckoktime":"2025-12-01 07:22:22","lastcheckoktime_iso8601":"2025-12-01T07:22:22Z","lastlocalchecktime":"2025-11-30 17:14:25","lastlocalchecktime_iso8601":"2025-11-30T17:14:25Z","clicktimestamp":"2025-12-01 05:24:40","clicktimestamp_iso8601":"2025-12-01T05:24:40Z","clickcount":10,"clicktrend":1,"ssl_error":0,"geo_lat":null,"geo_long":null,"geo_distance":null,"has_extended_info":false},{"changeuuid":"b7fee11c-076a-4d58-95ad-fa450722b696","stationuuid":"9aa3d762-d7f7-4d5c-a471-8f75616c6c3a","serveruuid":"1d921a2b-b34c-4c4c-aebb-d44237e8c510","name":"Nagari Radio","url":"http://stream.zeno.fm/287z97ksdg8uv","url_resolved":"http://stream-178.zeno.fm/287z97ksdg8uv?zt=eyJhbGciOiJIUzI1NiJ9.eyJzdHJlYW0iOiIyODd6OTdrc2RnOHV2IiwiaG9zdCI6InN0cmVhbS0xNzguemVuby5mbSIsInRtIjpmYWxzZSwicnR0bCI6NSwianRpIjoiZGFUamMweGZTTHlkVXBIaGhBZ20zQSIsImlhdCI6MTc2NDU1MDc5MywiZXhwIjoxNzY0NTUwODUzfQ.9b9uWGzyNtp0SJI78fTi-HrOAmDOsnHhlIu3kTO7yhU","homepage":"http://stream.zeno.fm/287z97ksdg8uv","favicon":"","tags":"entertainment","country":"Nigeria","countrycode":"NG","iso_3166_2":"","state":"","language":"hausa","languagecodes":"ha","votes":513,"lastchangetime":"2025-08-09 08:51:51","lastchangetime_iso8601":"2025-08-09T08:51:51Z","codec":"MP3","bitrate":0,"hls":0,"lastcheckok":1,"lastchecktime":"2025-12-01 01:14:08","lastchecktime_iso8601":"2025-12-01T01:14:08Z","lastcheckoktime":"2025-12-01 01:14:08","lastcheckoktime_iso8601":"2025-12-01T01:14:08Z","lastlocalchecktime":"2025-11-30 20:17:38","lastlocalchecktime_iso8601":"2025-11-30T20:17:38Z","clicktimestamp":"2025-11-30 17:09:06","clicktimestamp_iso8601":"2025-11-30T17:09:06Z","clickcount":6,"clicktrend":1,"ssl_error":0,"geo_lat":null,"geo_long":null,"geo_distance":null,"has_extended_info":false},{"changeuuid":"0383dfad-e337-406e-a4c9-fbebab5ee734","stationuuid":"3a27d119-dcea-4034-bf69-afbf47750ed7","serveruuid":"1d921a2b-b34c-4c4c-aebb-d44237e8c510","name":"Nagari Radio","url":"http://stream.zeno.fm/287z97ksdg8uv","url_resolved":"http://stream-178.zeno.fm/287z97ksdg8uv?zt=eyJhbGciOiJIUzI1NiJ9.eyJzdHJlYW0iOiIyODd6OTdrc2RnOHV2IiwiaG9zdCI6InN0cmVhbS0xNzguemVuby5mbSIsInRtIjpmYWxzZSwicnR0bCI6NSwianRpIjoiM1VidVktT25RX1N0UWVrU2NmdGhPQSIsImlhdCI6MTc2NDU1MjQ5NywiZXhwIjoxNzY0NTUyNTU3fQ.slBmUIMHP1Tzdl6m8qTuhEF863cfcNaY3AaaD-oke0I","homepage":"http://stream.zeno.fm/287z97ksdg8uv","favicon":"","tags":"http://stream.zeno.fm/287z97ksdg8uv","country":"Nigeria","countrycode":"NG","iso_3166_2":"","state":"","language":"hausa","languagecodes":"ha","votes":429,"lastchangetime":"2025-08-08 20:58:09","lastchangetime_iso8601":"2025-08-08T20:58:09Z","codec":"MP3","bitrate":0,"hls":0,"lastcheckok":1,"lastchecktime":"2025-12-01 01:28:48","lastchecktime_iso8601":"2025-12-01T01:28:48Z","lastcheckoktime":"2025-12-01 01:28:48","lastcheckoktime_iso8601":"2025-12-01T01:28:48Z","lastlocalchecktime":"2025-12-01 01:28:48","lastlocalchecktime_iso8601":"2025-12-01T01:28:48Z","clicktimestamp":"2025-12-01 05:24:26","clicktimestamp_iso8601":"2025-12-01T05:24:26Z","clickcount":11,"clicktrend":1,"ssl_error":0,"geo_lat":null,"geo_long":null,"geo_distance":null,"has_extended_info":false},{"changeuuid":"e69109d6-a8cf-468f-a44d-dd55747f50d8","stationuuid":"559e101a-34cd-4175-9bff-f60970497586","serveruuid":"3dbb0d9b-a0b7-4812-bd90-a653d160d670","name":"NCBN Abuja","url":"https://stream.zeno.fm/1zur4ycs6x8uv","url_resolved":"https://stream-179.zeno.fm/1zur4ycs6x8uv?zt=eyJhbGciOiJIUzI1NiJ9.eyJzdHJlYW0iOiIxenVyNHljczZ4OHV2IiwiaG9zdCI6InN0cmVhbS0xNzkuemVuby5mbSIsInRtIjpmYWxzZSwicnR0bCI6NSwianRpIjoicDZRaXpQZGdTZXVJQjgzQy1laDhjQSIsImlhdCI6MTc2NDU2ODY2MSwiZXhwIjoxNzY0NTY4NzIxfQ.vSWh-eVCbkfQyv-l8ECE9SIaC_5wyGgndLmVk_tM1ww","homepage":"https://news.ncbn.ng/","favicon":"https://news.ncbn.ng/favicon.ico","tags":"","country":"Nigeria","countrycode":"NG","iso_3166_2":"","state":"","language":"","languagecodes":"","votes":243,"lastchangetime":"2025-08-08 16:03:33","lastchangetime_iso8601":"2025-08-08T16:03:33Z","codec":"MP3","bitrate":0,"hls":0,"lastcheckok":1,"lastchecktime":"2025-12-01 05:57:54","lastchecktime_iso8601":"2025-12-01T05:57:54Z","lastcheckoktime":"2025-12-01 05:57:54","lastcheckoktime_iso8601":"2025-12-01T05:57:54Z","lastlocalchecktime":"2025-12-01 05:57:54","lastlocalchecktime_iso8601":"2025-12-01T05:57:54Z","clicktimestamp":"2025-12-01 05:25:01","clicktimestamp_iso8601":"2025-12-01T05:25:01Z","clickcount":8,"clicktrend":-2,"ssl_error":0,"geo_lat":null,"geo_long":null,"geo_distance":null,"has_extended_info":false},{"changeuuid":"d3bfb32e-f9b4-443a-a5f2-f1967e175d54","stationuuid":"f8d499d5-e223-4a0c-b712-2fb374628e35","serveruuid":"fcdf7089-c1b1-412b-9c53-a7bab9a61eff","name":"Nigerian Gospel Music Radio (MP3)","url":"http://stream.zeno.fm/3fmqr74a7f8uv","url_resolved":"http://stream-160.zeno.fm/3fmqr74a7f8uv?zt=eyJhbGciOiJIUzI1NiJ9.eyJzdHJlYW0iOiIzZm1xcjc0YTdmOHV2IiwiaG9zdCI6InN0cmVhbS0xNjAuemVuby5mbSIsInRtIjpmYWxzZSwicnR0bCI6NSwianRpIjoiNG1pTWRLVHVRRmlZelpEZExLc0J6ZyIsImlhdCI6MTc2NDU2ODA2NCwiZXhwIjoxNzY0NTY4MTI0fQ.kWbVsleZy3X-wK_ZRkVPc1yxPOBmru4Aa5etsNoQaY0","homepage":"https://nigeriangospelmusic.com.ng/","favicon":"https://nigeriangospelmusic.com.ng/wp-content/uploads/2022/09/NGM-icon.png","tags":"christian,gospel,gospel music,religious","country":"Nigeria","countrycode":"NG","iso_3166_2":"","state":"Lagos","language":"english","languagecodes":"en","votes":1936,"lastchangetime":"2025-08-09 07:37:33","lastchangetime_iso8601":"2025-08-09T07:37:33Z","codec":"MP3","bitrate":0,"hls":0,"lastcheckok":1,"lastchecktime":"2025-12-01 05:48:34","lastchecktime_iso8601":"2025-12-01T05:48:34Z","lastcheckoktime":"2025-12-01 05:48:34","lastcheckoktime_iso8601":"2025-12-01T05:48:34Z","lastlocalchecktime":"2025-12-01 05:48:34","lastlocalchecktime_iso8601":"2025-12-01T05:48:34Z","clicktimestamp":"2025-12-01 08:35:53","clicktimestamp_iso8601":"2025-12-01T08:35:53Z","clickcount":80,"clicktrend":4,"ssl_error":0,"geo_lat":null,"geo_long":null,"geo_distance":null,"has_extended_info":false},{"changeuuid":"1b28f422-6852-446e-acd7-e7b8e5979fee","stationuuid":"db8d4942-2b8d-4385-9c38-f1021af6dc48","serveruuid":"7f4bd515-48e1-437f-b102-b2d801550a7d","name":"Obong Radio","url":"https://stream.zeno.fm/vlssnjcwkisvv","url_resolved":"https://stream-177.zeno.fm/vlssnjcwkisvv?zt=eyJhbGciOiJIUzI1NiJ9.eyJzdHJlYW0iOiJ2bHNzbmpjd2tpc3Z2IiwiaG9zdCI6InN0cmVhbS0xNzcuemVuby5mbSIsInRtIjpmYWxzZSwicnR0bCI6NSwianRpIjoiWkZydFQ0UnNRWkt3ZWJQcjJjV2h1USIsImlhdCI6MTc2NDU0MTMxMSwiZXhwIjoxNzY0NTQxMzcxfQ.Hy0sJSTB2NAH9UmkCMuV-wr_hzeTqLkCQ8vs48dvP2o","homepage":"https://zeno.fm/radio/obong-radio-service-of-dept-of-mass-communications-obong-university/","favicon":"https://zeno.fm/_next/image/?url=https%3A%2F%2Fimages.zeno.fm%2FrXvdNZYGr5eXW_nXeLY9WO6zZrbPbYucuxqvwbzluBg%2Frs%3Afit%3A240%3A240%2Fg%3Ace%3A0%3A0%2FaHR0cHM6Ly9zdHJlYW0tdG9vbHMuemVub21lZGlhLmNvbS9jb250ZW50L3N0YXRpb25zL2FneHpmbnBsYm04dGMzUmhkSE55TWdzU0NrRjFkR2hEYkdsbGJuUVlnSUR3eDRXdC13a01DeElPVTNSaGRHbHZibEJ5YjJacGJHVVlnSUR3LTRESWx3a01vZ0VFZW1WdWJ3L2ltYWdlLz91cGRhdGVkPTE2OTg3MTIwMDkwMDA.webp&w=1920&q=100","tags":"afrobeats,amapiano,college,educational,instrumental,jazz,university","country":"Nigeria","countrycode":"NG","iso_3166_2":"","state":"Akwa Ibom State","language":"annang,efik,engllish,ibibio","languagecodes":"","votes":190,"lastchangetime":"2025-08-08 16:03:22","lastchangetime_iso8601":"2025-08-08T16:03:22Z","codec":"MP3","bitrate":0,"hls":0,"lastcheckok":1,"lastchecktime":"2025-11-30 22:25:46","lastchecktime_iso8601":"2025-11-30T22:25:46Z","lastcheckoktime":"2025-11-30 22:25:46","lastcheckoktime_iso8601":"2025-11-30T22:25:46Z","lastlocalchecktime":"2025-11-30 12:19:51","lastlocalchecktime_iso8601":"2025-11-30T12:19:51Z","clicktimestamp":"2025-12-01 05:40:14","clicktimestamp_iso8601":"2025-12-01T05:40:14Z","clickcount":19,"clicktrend":-2,"ssl_error":0,"geo_lat":4.949986603651791,"geo_long":7.5671124458313,"geo_distance":null,"has_extended_info":false},{"changeuuid":"dd3b1b41-8e94-49f9-91b3-1a7c41c7548e","stationuuid":"d22eaa1d-4f56-457c-b060-7857b63fc2b9","serveruuid":"9519692a-3c87-40fe-93bd-3d6a6b3fbf40","name":"Praiseworld Radio","url":"https://streaming.radio.co/s7dc18f0ad/listen","url_resolved":"https://streaming.radio.co/s7dc18f0ad/listen","homepage":"https://www.praiseworldradio.com/","favicon":"https://www.praiseworldradio.com/wp-content/uploads/2020/05/praiseworldlogo-1.png","tags":"","country":"Nigeria","countrycode":"NG","iso_3166_2":"","state":"","language":"","languagecodes":"","votes":306,"lastchangetime":"2025-08-08 16:03:19","lastchangetime_iso8601":"2025-08-08T16:03:19Z","codec":"AAC","bitrate":192,"hls":0,"lastcheckok":1,"lastchecktime":"2025-12-01 02:06:45","lastchecktime_iso8601":"2025-12-01T02:06:45Z","lastcheckoktime":"2025-12-01 02:06:45","lastcheckoktime_iso8601":"2025-12-01T02:06:45Z","lastlocalchecktime":"2025-11-30 17:54:24","lastlocalchecktime_iso8601":"2025-11-30T17:54:24Z","clicktimestamp":"2025-12-01 05:52:41","clicktimestamp_iso8601":"2025-12-01T05:52:41Z","clickcount":12,"clicktrend":2,"ssl_error":0,"geo_lat":null,"geo_long":null,"geo_distance":null,"has_extended_info":false},{"changeuuid":"24c6c957-5535-4134-916c-d7c600f9d5eb","stationuuid":"7e6e7bb9-6f55-4c79-83fa-ff25aa72e117","serveruuid":"c58005cf-dba9-49e3-aa74-79442cdbe5ab","name":"Radio East","url":"http://stream.zeno.fm/7f4w4us5wp8uv","url_resolved":"http://stream-179.zeno.fm/7f4w4us5wp8uv?zt=eyJhbGciOiJIUzI1NiJ9.eyJzdHJlYW0iOiI3ZjR3NHVzNXdwOHV2IiwiaG9zdCI6InN0cmVhbS0xNzkuemVuby5mbSIsInRtIjpmYWxzZSwicnR0bCI6NSwianRpIjoidHNxS0ZPVlhUMjZmeEo2cHJvRG9pQSIsImlhdCI6MTc2NDU1MjE4OSwiZXhwIjoxNzY0NTUyMjQ5fQ.5votpcQZhQSb_XSdYSM_Vly-asE3hZsM_OE5VDpswqM","homepage":"https://www.radioeast.com.ng/","favicon":"","tags":"music,talk","country":"Nigeria","countrycode":"NG","iso_3166_2":"","state":"Imo","language":"english","languagecodes":"en","votes":1881,"lastchangetime":"2025-08-09 06:51:31","lastchangetime_iso8601":"2025-08-09T06:51:31Z","codec":"MP3","bitrate":0,"hls":0,"lastcheckok":1,"lastchecktime":"2025-12-01 01:24:03","lastchecktime_iso8601":"2025-12-01T01:24:03Z","lastcheckoktime":"2025-12-01 01:24:03","lastcheckoktime_iso8601":"2025-12-01T01:24:03Z","lastlocalchecktime":"2025-12-01 01:24:03","lastlocalchecktime_iso8601":"2025-12-01T01:24:03Z","clicktimestamp":"2025-12-01 08:07:41","clicktimestamp_iso8601":"2025-12-01T08:07:41Z","clickcount":12,"clicktrend":1,"ssl_error":0,"geo_lat":null,"geo_long":null,"geo_distance":null,"has_extended_info":false},{"changeuuid":"6582ac7c-b24c-4877-acfc-400537e3129d","stationuuid":"5f9a9575-2117-4217-9ef4-6ce28d03e4e3","serveruuid":"1ae36511-bec8-48f5-896a-7e1d7f3bc2e6","name":"RadioTiwa","url":"https://stream.zeno.fm/tvqvamkwe5zuv","url_resolved":"https://stream-175.zeno.fm/tvqvamkwe5zuv?zt=eyJhbGciOiJIUzI1NiJ9.eyJzdHJlYW0iOiJ0dnF2YW1rd2U1enV2IiwiaG9zdCI6InN0cmVhbS0xNzUuemVuby5mbSIsInRtIjpmYWxzZSwicnR0bCI6NSwianRpIjoicmZrWVRINXRTZGkzOGVJdlF3MUp0QSIsImlhdCI6MTc2NDU3OTExNiwiZXhwIjoxNzY0NTc5MTc2fQ.cy85JBgaThFEF0HcW4xJQK2eXB_XC58toUzi_IpaLJ8","homepage":"http://www.radiotiwa.com.ng/","favicon":"","tags":"talk & speech","country":"Nigeria","countrycode":"NG","iso_3166_2":"","state":"","language":"","languagecodes":"","votes":701,"lastchangetime":"2025-08-08 16:03:20","lastchangetime_iso8601":"2025-08-08T16:03:20Z","codec":"MP3","bitrate":0,"hls":0,"lastcheckok":1,"lastchecktime":"2025-12-01 09:01:10","lastchecktime_iso8601":"2025-12-01T09:01:10Z","lastcheckoktime":"2025-12-01 09:01:10","lastcheckoktime_iso8601":"2025-12-01T09:01:10Z","lastlocalchecktime":"2025-11-30 15:43:50","lastlocalchecktime_iso8601":"2025-11-30T15:43:50Z","clicktimestamp":"2025-12-01 08:44:01","clicktimestamp_iso8601":"2025-12-01T08:44:01Z","clickcount":24,"clicktrend":0,"ssl_error":0,"geo_lat":null,"geo_long":null,"geo_distance":null,"has_extended_info":false},{"changeuuid":"1af0f999-7efc-48a1-b5a9-c77c46c5b1de","stationuuid":"bd84e569-e827-4ddf-91af-d2c9378614fa","serveruuid":"1ae36511-bec8-48f5-896a-7e1d7f3bc2e6","name":"RadioTiwa","url":"https://stream.zeno.fm/tvqvamkwe5zuv.m3u","url_resolved":"https://stream-175.zeno.fm/tvqvamkwe5zuv?zt=eyJhbGciOiJIUzI1NiJ9.eyJzdHJlYW0iOiJ0dnF2YW1rd2U1enV2IiwiaG9zdCI6InN0cmVhbS0xNzUuemVuby5mbSIsInRtIjpmYWxzZSwicnR0bCI6NSwianRpIjoiLU5wckYxMjBUYXFadjZ6VG1ldlJHdyIsImlhdCI6MTc2NDU3MjUwNywiZXhwIjoxNzY0NTcyNTY3fQ.uBNnlWmflKF-hWMJYHhCBkQrD-uewp5m4N9t7M3zbJk","homepage":"http://www.instagram.com/","favicon":"","tags":"talk & speech","country":"Nigeria","countrycode":"NG","iso_3166_2":"","state":"","language":"","languagecodes":"","votes":437,"lastchangetime":"2025-08-08 16:03:22","lastchangetime_iso8601":"2025-08-08T16:03:22Z","codec":"MP3","bitrate":0,"hls":0,"lastcheckok":1,"lastchecktime":"2025-12-01 07:04:27","lastchecktime_iso8601":"2025-12-01T07:04:27Z","lastcheckoktime":"2025-12-01 07:04:27","lastcheckoktime_iso8601":"2025-12-01T07:04:27Z","lastlocalchecktime":"2025-11-30 13:43:40","lastlocalchecktime_iso8601":"2025-11-30T13:43:40Z","clicktimestamp":"2025-12-01 05:23:49","clicktimestamp_iso8601":"2025-12-01T05:23:49Z","clickcount":13,"clicktrend":-2,"ssl_error":0,"geo_lat":null,"geo_long":null,"geo_distance":null,"has_extended_info":false},{"changeuuid":"8c009b3b-526e-4436-b325-9ab3023bdec5","stationuuid":"0bbe1392-8d92-447a-8381-7615cc33369b","serveruuid":"ffab2e1a-10ca-4751-aed8-d702327e1ae0","name":"RCCG Central Parish Radio","url":"https://s2.radio.co/s82911d13a/low","url_resolved":"https://s2.radio.co/s82911d13a/low","homepage":"https://www.centralparishradio.org/#","favicon":"https://centralparishradio.org/wp-content/uploads/2019/11/church.jpg","tags":"","country":"Nigeria","countrycode":"NG","iso_3166_2":"","state":"","language":"","languagecodes":"","votes":145,"lastchangetime":"2025-08-08 16:09:01","lastchangetime_iso8601":"2025-08-08T16:09:01Z","codec":"AAC","bitrate":32,"hls":0,"lastcheckok":1,"lastchecktime":"2025-12-01 00:50:22","lastchecktime_iso8601":"2025-12-01T00:50:22Z","lastcheckoktime":"2025-12-01 00:50:22","lastcheckoktime_iso8601":"2025-12-01T00:50:22Z","lastlocalchecktime":"2025-11-30 14:16:24","lastlocalchecktime_iso8601":"2025-11-30T14:16:24Z","clicktimestamp":"2025-11-30 22:15:57","clicktimestamp_iso8601":"2025-11-30T22:15:57Z","clickcount":4,"clicktrend":2,"ssl_error":0,"geo_lat":null,"geo_long":null,"geo_distance":null,"has_extended_info":false},{"changeuuid":"c1de8dee-1cc2-456b-90c1-6186ad0bec5f","stationuuid":"85550c05-c693-11e8-a498-52543be04c81","serveruuid":"0a587304-e0d6-42fa-9f6c-f14170a22db8","name":"RFI Haoussa","url":"http://live02.rfi.fr/rfihaoussa-96k.mp3","url_resolved":"http://rfihaoussa96k.ice.infomaniak.ch/rfihaoussa-96k.mp3","homepage":"http://www.rfi.fr/","favicon":"","tags":"","country":"Nigeria","countrycode":"NG","iso_3166_2":"","state":"","language":"","languagecodes":"","votes":4381,"lastchangetime":"2025-08-08 16:03:20","lastchangetime_iso8601":"2025-08-08T16:03:20Z","codec":"MP3","bitrate":96,"hls":0,"lastcheckok":1,"lastchecktime":"2025-12-01 09:01:18","lastchecktime_iso8601":"2025-12-01T09:01:18Z","lastcheckoktime":"2025-12-01 09:01:18","lastcheckoktime_iso8601":"2025-12-01T09:01:18Z","lastlocalchecktime":"2025-12-01 00:45:13","lastlocalchecktime_iso8601":"2025-12-01T00:45:13Z","clicktimestamp":"2025-12-01 08:49:44","clicktimestamp_iso8601":"2025-12-01T08:49:44Z","clickcount":26,"clicktrend":4,"ssl_error":0,"geo_lat":null,"geo_long":null,"geo_distance":null,"has_extended_info":false},{"changeuuid":"bb5daefd-3c24-4148-b1db-454d911d83dd","stationuuid":"b212d36a-5b07-46fe-8da2-171d9833c6a4","serveruuid":"7bd856c5-309f-46c1-8455-09a528088a83","name":"Rose FM","url":"http://ec1.everestcast.host:4730/stream","url_resolved":"http://ec1.everestcast.host:4730/stream","homepage":"https://www.radio-nigeria.com/rose-fm","favicon":"https://static.mytuner.mobi/media/tvos_radios/K8vTSYfcw4.png","tags":"","country":"Nigeria","countrycode":"NG","iso_3166_2":"","state":"","language":"","languagecodes":"","votes":139,"lastchangetime":"2025-08-08 16:03:33","lastchangetime_iso8601":"2025-08-08T16:03:33Z","codec":"MP3","bitrate":64,"hls":0,"lastcheckok":1,"lastchecktime":"2025-12-01 05:41:10","lastchecktime_iso8601":"2025-12-01T05:41:10Z","lastcheckoktime":"2025-12-01 05:41:10","lastcheckoktime_iso8601":"2025-12-01T05:41:10Z","lastlocalchecktime":"2025-11-30 23:40:52","lastlocalchecktime_iso8601":"2025-11-30T23:40:52Z","clicktimestamp":"2025-12-01 08:50:43","clicktimestamp_iso8601":"2025-12-01T08:50:43Z","clickcount":7,"clicktrend":0,"ssl_error":0,"geo_lat":null,"geo_long":null,"geo_distance":null,"has_extended_info":false},{"changeuuid":"de978ba6-65b0-4bd3-acf3-f7b873319245","stationuuid":"6b7cacb7-68d2-4983-948f-f706d2445451","serveruuid":"739325ca-58c4-4004-8b6e-d3580f53fbea","name":"Salinga Radio","url":"https://stream.zeno.fm/zdorrycexhxuv","url_resolved":"https://stream-157.zeno.fm/zdorrycexhxuv?zt=eyJhbGciOiJIUzI1NiJ9.eyJzdHJlYW0iOiJ6ZG9ycnljZXhoeHV2IiwiaG9zdCI6InN0cmVhbS0xNTcuemVuby5mbSIsInRtIjpmYWxzZSwicnR0bCI6NSwianRpIjoiemx4eldCdFpSSzJfNnp6T1B0NGRCUSIsImlhdCI6MTc2NDUwOTAxNSwiZXhwIjoxNzY0NTA5MDc1fQ.1OIj3DwLRj3p1uuG4W4A6DRLqDB1eqMnCHfxsfPMqgw","homepage":"https://stream.zeno.fm/zdorrycexhxuv","favicon":"https://stream.zeno.fm/zdorrycexhxuv","tags":"livestream,news","country":"Nigeria","countrycode":"NG","iso_3166_2":"","state":"Kaduna","language":"","languagecodes":"","votes":26,"lastchangetime":"2025-08-09 01:25:20","lastchangetime_iso8601":"2025-08-09T01:25:20Z","codec":"MP3","bitrate":0,"hls":0,"lastcheckok":1,"lastchecktime":"2025-11-30 13:30:27","lastchecktime_iso8601":"2025-11-30T13:30:27Z","lastcheckoktime":"2025-11-30 13:30:27","lastcheckoktime_iso8601":"2025-11-30T13:30:27Z","lastlocalchecktime":"2025-11-30 12:59:08","lastlocalchecktime_iso8601":"2025-11-30T12:59:08Z","clicktimestamp":"2025-12-01 06:37:50","clicktimestamp_iso8601":"2025-12-01T06:37:50Z","clickcount":4,"clicktrend":1,"ssl_error":0,"geo_lat":null,"geo_long":null,"geo_distance":null,"has_extended_info":false},{"changeuuid":"4add5f25-5119-46de-8dcf-c14f583d19ed","stationuuid":"f69afbf3-fc53-44d1-b0ec-69911f350705","serveruuid":"323cc672-d9e8-4fc5-a3d3-3f439f0b21b0","name":"Splash FM 105.5","url":"https://edge.mixlr.com/channel/cfeki","url_resolved":"https://edge.mixlr.com/channel/cfeki","homepage":"https://splashfm1055.com/","favicon":"https://splashfm1055.com/img/logo.png","tags":"","country":"Nigeria","countrycode":"NG","iso_3166_2":"","state":"Ibadan","language":"","languagecodes":"","votes":1354,"lastchangetime":"2025-08-08 16:03:33","lastchangetime_iso8601":"2025-08-08T16:03:33Z","codec":"MP3","bitrate":0,"hls":0,"lastcheckok":1,"lastchecktime":"2025-12-01 03:30:25","lastchecktime_iso8601":"2025-12-01T03:30:25Z","lastcheckoktime":"2025-12-01 03:30:25","lastcheckoktime_iso8601":"2025-12-01T03:30:25Z","lastlocalchecktime":"2025-11-30 21:52:27","lastlocalchecktime_iso8601":"2025-11-30T21:52:27Z","clicktimestamp":"2025-12-01 09:14:19","clicktimestamp_iso8601":"2025-12-01T09:14:19Z","clickcount":64,"clicktrend":12,"ssl_error":0,"geo_lat":null,"geo_long":null,"geo_distance":null,"has_extended_info":false},{"changeuuid":"c3b88ea3-46b3-4932-b8c6-55a84fac44b8","stationuuid":"92041a7e-33de-453a-9a52-e5c88a2d7cd5","serveruuid":"739325ca-58c4-4004-8b6e-d3580f53fbea","name":"Splash FM Abeokuta","url":"https://stream.zeno.fm/m9x6zr5trp8uv","url_resolved":"https://stream-157.zeno.fm/m9x6zr5trp8uv?zt=eyJhbGciOiJIUzI1NiJ9.eyJzdHJlYW0iOiJtOXg2enI1dHJwOHV2IiwiaG9zdCI6InN0cmVhbS0xNTcuemVuby5mbSIsInRtIjpmYWxzZSwicnR0bCI6NSwianRpIjoiWGZEcGVqQlpRY2FiTmdBQVVHT0F0USIsImlhdCI6MTc2NDUxNzYzNywiZXhwIjoxNzY0NTE3Njk3fQ.v7mWYt72JibkuSr2Rk9Q4ihxaD7kgeLOVeKl78822yc","homepage":"https://www.splashfm1067.com/","favicon":"https://splashfm1055.com/img/logo.png","tags":"","country":"Nigeria","countrycode":"NG","iso_3166_2":"","state":"","language":"","languagecodes":"","votes":338,"lastchangetime":"2025-08-08 16:03:22","lastchangetime_iso8601":"2025-08-08T16:03:22Z","codec":"MP3","bitrate":0,"hls":0,"lastcheckok":0,"lastchecktime":"2025-12-01 00:31:49","lastchecktime_iso8601":"2025-12-01T00:31:49Z","lastcheckoktime":"2025-11-30 15:47:31","lastcheckoktime_iso8601":"2025-11-30T15:47:31Z","lastlocalchecktime":"2025-11-30 15:47:31","lastlocalchecktime_iso8601":"2025-11-30T15:47:31Z","clicktimestamp":"2025-12-01 08:51:18","clicktimestamp_iso8601":"2025-12-01T08:51:18Z","clickcount":19,"clicktrend":4,"ssl_error":0,"geo_lat":null,"geo_long":null,"geo_distance":null,"has_extended_info":false},{"changeuuid":"752181e1-6d40-4a97-beb9-66445a66a2d1","stationuuid":"ade28777-a20a-4e72-b049-0e02799391ad","serveruuid":"3dbb0d9b-a0b7-4812-bd90-a653d160d670","name":"Sunshine FM 104.5 MHz Potiskum","url":"https://stream.zeno.fm/cu2e39ra0chvv","url_resolved":"https://stream-179.zeno.fm/cu2e39ra0chvv?zt=eyJhbGciOiJIUzI1NiJ9.eyJzdHJlYW0iOiJjdTJlMzlyYTBjaHZ2IiwiaG9zdCI6InN0cmVhbS0xNzkuemVuby5mbSIsInRtIjpmYWxzZSwicnR0bCI6NSwianRpIjoiS2dJOTBYNkRUY3VSV2ljLTZHTExDQSIsImlhdCI6MTc2NDU3NDk5NSwiZXhwIjoxNzY0NTc1MDU1fQ.UjIBDFx78nTEUdIjklQg9bHg6mXxkEBWCFgflTIy0vs","homepage":"https://sunshinefmng.com/","favicon":"https://img.sedoparking.com/templates/logos/sedo_logo.png","tags":"","country":"Nigeria","countrycode":"NG","iso_3166_2":"","state":"","language":"","languagecodes":"","votes":380,"lastchangetime":"2025-08-08 16:03:20","lastchangetime_iso8601":"2025-08-08T16:03:20Z","codec":"MP3","bitrate":0,"hls":0,"lastcheckok":1,"lastchecktime":"2025-12-01 07:49:40","lastchecktime_iso8601":"2025-12-01T07:49:40Z","lastcheckoktime":"2025-12-01 07:49:40","lastcheckoktime_iso8601":"2025-12-01T07:49:40Z","lastlocalchecktime":"2025-12-01 01:44:41","lastlocalchecktime_iso8601":"2025-12-01T01:44:41Z","clicktimestamp":"2025-12-01 07:42:51","clicktimestamp_iso8601":"2025-12-01T07:42:51Z","clickcount":11,"clicktrend":8,"ssl_error":0,"geo_lat":null,"geo_long":null,"geo_distance":null,"has_extended_info":false},{"changeuuid":"82887603-1c5a-4314-833f-b7488d983e46","stationuuid":"cf884bee-1b34-419a-a0a2-408eed204b19","serveruuid":"d036cd30-21f6-4087-a5bf-bfb79cfbe996","name":"The Today Africa Radio ","url":"http://stream.zeno.fm/e66eb3qmg48uv","url_resolved":"http://stream-176.zeno.fm/e66eb3qmg48uv?zt=eyJhbGciOiJIUzI1NiJ9.eyJzdHJlYW0iOiJlNjZlYjNxbWc0OHV2IiwiaG9zdCI6InN0cmVhbS0xNzYuemVuby5mbSIsInRtIjpmYWxzZSwicnR0bCI6NSwianRpIjoiQ1loM3NxdlNSVGlqSHZkRE1acVB1QSIsImlhdCI6MTc2NDUxMTM5NSwiZXhwIjoxNzY0NTExNDU1fQ.vOY6Li5e4zYoQjhDgtBL8e-eVFA7B7qH_JgnsRFRLSg","homepage":"http://radio.thetodayafrica.com/","favicon":"","tags":"rock","country":"Nigeria","countrycode":"NG","iso_3166_2":"","state":"Lagos","language":"","languagecodes":"","votes":875,"lastchangetime":"2025-08-08 16:03:18","lastchangetime_iso8601":"2025-08-08T16:03:18Z","codec":"MP3","bitrate":0,"hls":0,"lastcheckok":1,"lastchecktime":"2025-11-30 14:08:05","lastchecktime_iso8601":"2025-11-30T14:08:05Z","lastcheckoktime":"2025-11-30 14:08:05","lastcheckoktime_iso8601":"2025-11-30T14:08:05Z","lastlocalchecktime":"2025-11-30 14:04:48","lastlocalchecktime_iso8601":"2025-11-30T14:04:48Z","clicktimestamp":"2025-12-01 07:12:29","clicktimestamp_iso8601":"2025-12-01T07:12:29Z","clickcount":9,"clicktrend":4,"ssl_error":0,"geo_lat":8.233227395569616,"geo_long":8.16127270460129,"geo_distance":null,"has_extended_info":false},{"changeuuid":"554beb21-1b70-43fe-aa15-821b3257cad9","stationuuid":"6f8b706b-866c-4d14-ac07-b752d2e38b2d","serveruuid":"7f4bd515-48e1-437f-b102-b2d801550a7d","name":"Trove Radio Station","url":"https://stream.zeno.fm/c4ghegiwnkcvv","url_resolved":"https://stream-177.zeno.fm/c4ghegiwnkcvv?zt=eyJhbGciOiJIUzI1NiJ9.eyJzdHJlYW0iOiJjNGdoZWdpd25rY3Z2IiwiaG9zdCI6InN0cmVhbS0xNzcuemVuby5mbSIsInRtIjpmYWxzZSwicnR0bCI6NSwianRpIjoiY284UUl5UDhSaEdEcG9ULWZNNUo4ZyIsImlhdCI6MTc2NDUwOTgxMywiZXhwIjoxNzY0NTA5ODczfQ.eh5zzHpI0O1U30SBQi0RzGzMbc6Ta7upGaBc7e--H0w","homepage":"https://march3rdmedia.com.ng/","favicon":"https://od.lk/s/NjJfNTI0Mjg3NDVf/TroveRadioGif2.gif","tags":"gospel,hip-pop,jazz","country":"Nigeria","countrycode":"NG","iso_3166_2":"","state":"Osun","language":"english,yoruba","languagecodes":"en,yo","votes":41,"lastchangetime":"2025-08-09 06:03:57","lastchangetime_iso8601":"2025-08-09T06:03:57Z","codec":"MP3","bitrate":0,"hls":0,"lastcheckok":1,"lastchecktime":"2025-11-30 13:37:11","lastchecktime_iso8601":"2025-11-30T13:37:11Z","lastcheckoktime":"2025-11-30 13:37:11","lastcheckoktime_iso8601":"2025-11-30T13:37:11Z","lastlocalchecktime":"2025-11-30 13:37:11","lastlocalchecktime_iso8601":"2025-11-30T13:37:11Z","clicktimestamp":"2025-12-01 06:07:34","clicktimestamp_iso8601":"2025-12-01T06:07:34Z","clickcount":6,"clicktrend":2,"ssl_error":0,"geo_lat":null,"geo_long":null,"geo_distance":null,"has_extended_info":false},{"changeuuid":"f6043a66-a307-4ee9-8001-ae5e56257329","stationuuid":"0c72b256-d28a-4933-ab35-0257cff2d403","serveruuid":"323cc672-d9e8-4fc5-a3d3-3f439f0b21b0","name":"URBAN RADIO ENUGU","url":"https://edge.mixlr.com/channel/cfldr","url_resolved":"https://edge.mixlr.com/channel/cfldr","homepage":"https://www.urbanradio945.com/","favicon":"","tags":"","country":"Nigeria","countrycode":"NG","iso_3166_2":"","state":"Enugu","language":"","languagecodes":"","votes":1128,"lastchangetime":"2025-08-08 16:03:22","lastchangetime_iso8601":"2025-08-08T16:03:22Z","codec":"MP3","bitrate":0,"hls":0,"lastcheckok":1,"lastchecktime":"2025-12-01 06:18:19","lastchecktime_iso8601":"2025-12-01T06:18:19Z","lastcheckoktime":"2025-12-01 06:18:19","lastcheckoktime_iso8601":"2025-12-01T06:18:19Z","lastlocalchecktime":"2025-12-01 00:41:19","lastlocalchecktime_iso8601":"2025-12-01T00:41:19Z","clicktimestamp":"2025-12-01 05:33:39","clicktimestamp_iso8601":"2025-12-01T05:33:39Z","clickcount":12,"clicktrend":1,"ssl_error":0,"geo_lat":null,"geo_long":null,"geo_distance":null,"has_extended_info":false},{"changeuuid":"b4a797e7-b383-44e8-b799-882cec6d39e8","stationuuid":"5ed4335b-542b-4ec3-a026-37ba522a392b","serveruuid":"63ec22f7-2ce0-4ebe-87f6-ff76555004b1","name":"Usaku FM 90.5","url":"https://eu8.fastcast4u.com/proxy/usakufm?mp=/1","url_resolved":"https://eu8.fastcast4u.com/proxy/usakufm?mp=/1","homepage":"https://usakufm.com/","favicon":"","tags":"fm yola,radio yola,usaku,usaku fm,usaku radio","country":"Nigeria","countrycode":"NG","iso_3166_2":"","state":"","language":"english,hausa","languagecodes":"en,ha","votes":115,"lastchangetime":"2025-08-09 05:54:58","lastchangetime_iso8601":"2025-08-09T05:54:58Z","codec":"MP3","bitrate":96,"hls":0,"lastcheckok":1,"lastchecktime":"2025-12-01 06:36:58","lastchecktime_iso8601":"2025-12-01T06:36:58Z","lastcheckoktime":"2025-12-01 06:36:58","lastcheckoktime_iso8601":"2025-12-01T06:36:58Z","lastlocalchecktime":"2025-11-30 14:26:26","lastlocalchecktime_iso8601":"2025-11-30T14:26:26Z","clicktimestamp":"2025-12-01 05:24:15","clicktimestamp_iso8601":"2025-12-01T05:24:15Z","clickcount":11,"clicktrend":-1,"ssl_error":0,"geo_lat":null,"geo_long":null,"geo_distance":null,"has_extended_info":false},{"changeuuid":"3158c27e-361b-454f-a39b-623fb2d50816","stationuuid":"f92bd51f-578b-4ed8-8bd7-fbd1891959e4","serveruuid":"9872b9be-8eef-4bb6-9aa9-23cbf232db75","name":"WiGRadio","url":"http://stream-152.zeno.fm/k4w8hv26nzzuv?zs=9e7U8mPaSMyi2Nnt_ivOqA","url_resolved":"https://stream-167.zeno.fm/k4w8hv26nzzuv?zt=eyJhbGciOiJIUzI1NiJ9.eyJzdHJlYW0iOiJrNHc4aHYyNm56enV2IiwiaG9zdCI6InN0cmVhbS0xNjcuemVuby5mbSIsInRtIjpmYWxzZSwicnR0bCI6NSwianRpIjoicmJyOW1UNzdTRXExUDlMeVZveG55QSIsImlhdCI6MTc2NDU2OTUzOSwiZXhwIjoxNzY0NTY5NTk5fQ.UplNXO-nTSFK4bkS63F5Gc36MkjHa2C6yv5_U-olnx4","homepage":"https://wigradio.com/","favicon":"https://wigradio.com/wp-content/uploads/2021/10/WiGRadio-logo-90-e1634133264755.png","tags":"christian,sermons,talk","country":"Nigeria","countrycode":"NG","iso_3166_2":"","state":"Lagos","language":"english","languagecodes":"en","votes":78,"lastchangetime":"2025-10-29 04:09:37","lastchangetime_iso8601":"2025-10-29T04:09:37Z","codec":"MP3","bitrate":0,"hls":0,"lastcheckok":1,"lastchecktime":"2025-12-01 06:16:28","lastchecktime_iso8601":"2025-12-01T06:16:28Z","lastcheckoktime":"2025-12-01 06:16:28","lastcheckoktime_iso8601":"2025-12-01T06:16:28Z","lastlocalchecktime":"2025-12-01 06:16:28","lastlocalchecktime_iso8601":"2025-12-01T06:16:28Z","clicktimestamp":"2025-12-01 08:50:54","clicktimestamp_iso8601":"2025-12-01T08:50:54Z","clickcount":6,"clicktrend":-2,"ssl_error":0,"geo_lat":null,"geo_long":null,"geo_distance":null,"has_extended_info":false},{"changeuuid":"1c59f6c4-2f37-462a-9e1c-b46c6a1d7af2","stationuuid":"0edc2f14-2586-49b4-b083-6dff1433c1a8","serveruuid":"6211129b-0ffe-4c9a-a57d-a7167016e858","name":"YDI Radio","url":"https://s9.voscast.com:9079/stream","url_resolved":"https://s9.voscast.com:9079/stream","homepage":"https://ydiradio.com/","favicon":"https://ydiradio.com/wp-content/uploads/2021/01/ydiradiologo-trans.png","tags":"","country":"Nigeria","countrycode":"NG","iso_3166_2":"","state":"Lagos","language":"","languagecodes":"","votes":77,"lastchangetime":"2025-08-08 16:03:18","lastchangetime_iso8601":"2025-08-08T16:03:18Z","codec":"MP3","bitrate":64,"hls":0,"lastcheckok":1,"lastchecktime":"2025-12-01 06:47:01","lastchecktime_iso8601":"2025-12-01T06:47:01Z","lastcheckoktime":"2025-12-01 06:47:01","lastcheckoktime_iso8601":"2025-12-01T06:47:01Z","lastlocalchecktime":"2025-12-01 05:37:31","lastlocalchecktime_iso8601":"2025-12-01T05:37:31Z","clicktimestamp":"2025-11-30 04:51:39","clicktimestamp_iso8601":"2025-11-30T04:51:39Z","clickcount":2,"clicktrend":-1,"ssl_error":0,"geo_lat":-56.835234755303446,"geo_long":-51.328126610082954,"geo_distance":null,"has_extended_info":false},{"changeuuid":"75d17bec-26f5-4a51-b553-71cb52aa72d6","stationuuid":"dc771977-291d-4fe4-928d-43d19b0739bc","serveruuid":"6211129b-0ffe-4c9a-a57d-a7167016e858","name":"YDI Radio","url":"https://s9.voscast.com:9079/stream","url_resolved":"https://s9.voscast.com:9079/stream","homepage":"https://ydiradio.com/","favicon":"","tags":"","country":"Nigeria","countrycode":"NG","iso_3166_2":"","state":"Lagos","language":"","languagecodes":"","votes":76,"lastchangetime":"2025-08-08 16:03:21","lastchangetime_iso8601":"2025-08-08T16:03:21Z","codec":"MP3","bitrate":64,"hls":0,"lastcheckok":1,"lastchecktime":"2025-12-01 01:37:22","lastchecktime_iso8601":"2025-12-01T01:37:22Z","lastcheckoktime":"2025-12-01 01:37:22","lastcheckoktime_iso8601":"2025-12-01T01:37:22Z","lastlocalchecktime":"2025-12-01 01:37:22","lastlocalchecktime_iso8601":"2025-12-01T01:37:22Z","clicktimestamp":"2025-11-29 15:12:21","clicktimestamp_iso8601":"2025-11-29T15:12:21Z","clickcount":3,"clicktrend":-1,"ssl_error":0,"geo_lat":null,"geo_long":null,"geo_distance":null,"has_extended_info":false},{"changeuuid":"e602b750-59ee-469a-91aa-017726cb401d","stationuuid":"65e1fb3e-efa9-4698-9ebc-972f03776eba","serveruuid":"739325ca-58c4-4004-8b6e-d3580f53fbea","name":"YES 101.7 FM","url":"https://stream.zenolive.com/kqgbf9g3mfhvv","url_resolved":"https://stream-156.zeno.fm/kqgbf9g3mfhvv?zt=eyJhbGciOiJIUzI1NiJ9.eyJzdHJlYW0iOiJrcWdiZjlnM21maHZ2IiwiaG9zdCI6InN0cmVhbS0xNTYuemVuby5mbSIsInRtIjpmYWxzZSwicnR0bCI6NSwianRpIjoiYTc3TDloSlpRV0dBb0pTdTlhRTVxUSIsImlhdCI6MTc2NDU2MDU3MSwiZXhwIjoxNzY0NTYwNjMxfQ.mchm3S5kWqFVMfs0A3ByMbcmSJAWshgBu-niagecCBQ","homepage":"https://yesfmibadan.com/","favicon":"","tags":"","country":"Nigeria","countrycode":"NG","iso_3166_2":"","state":"Ibadan","language":"","languagecodes":"","votes":280,"lastchangetime":"2025-08-08 16:03:20","lastchangetime_iso8601":"2025-08-08T16:03:20Z","codec":"MP3","bitrate":0,"hls":0,"lastcheckok":1,"lastchecktime":"2025-12-01 03:42:59","lastchecktime_iso8601":"2025-12-01T03:42:59Z","lastcheckoktime":"2025-12-01 03:42:59","lastcheckoktime_iso8601":"2025-12-01T03:42:59Z","lastlocalchecktime":"2025-12-01 03:42:59","lastlocalchecktime_iso8601":"2025-12-01T03:42:59Z","clicktimestamp":"2025-12-01 05:33:54","clicktimestamp_iso8601":"2025-12-01T05:33:54Z","clickcount":11,"clicktrend":6,"ssl_error":0,"geo_lat":null,"geo_long":null,"geo_distance":null,"has_extended_info":false},{"changeuuid":"fd9ef17a-bbb2-4136-a7b7-4c6c3d9114a5","stationuuid":"7e66acae-0f86-4d20-ba2a-b79909df9c47","serveruuid":"739325ca-58c4-4004-8b6e-d3580f53fbea","name":"Yes FM 101.7","url":"https://stream.zeno.fm/kqgbf9g3mfhvv","url_resolved":"https://stream-157.zeno.fm/kqgbf9g3mfhvv?zt=eyJhbGciOiJIUzI1NiJ9.eyJzdHJlYW0iOiJrcWdiZjlnM21maHZ2IiwiaG9zdCI6InN0cmVhbS0xNTcuemVuby5mbSIsInRtIjpmYWxzZSwicnR0bCI6NSwianRpIjoiSnJnd09mZXdUWDJ2TXg1QjA5NXdXQSIsImlhdCI6MTc2NDUyMjA4MywiZXhwIjoxNzY0NTIyMTQzfQ.W3o1DGm0TMiPTApZvJJbEZlRxS8rn362Z3h83liRItM","homepage":"https://yesfmibadan.com/","favicon":"","tags":"","country":"Nigeria","countrycode":"NG","iso_3166_2":"","state":"Ibadan","language":"","languagecodes":"","votes":700,"lastchangetime":"2025-08-08 16:03:19","lastchangetime_iso8601":"2025-08-08T16:03:19Z","codec":"MP3","bitrate":0,"hls":0,"lastcheckok":1,"lastchecktime":"2025-11-30 17:01:32","lastchecktime_iso8601":"2025-11-30T17:01:32Z","lastcheckoktime":"2025-11-30 17:01:32","lastcheckoktime_iso8601":"2025-11-30T17:01:32Z","lastlocalchecktime":"2025-11-30 17:01:32","lastlocalchecktime_iso8601":"2025-11-30T17:01:32Z","clicktimestamp":"2025-12-01 08:49:53","clicktimestamp_iso8601":"2025-12-01T08:49:53Z","clickcount":29,"clicktrend":2,"ssl_error":0,"geo_lat":null,"geo_long":null,"geo_distance":null,"has_extended_info":false}]