[{"changeuuid":"09e0347b-eb04-4c13-82cc-ef0f06779c3a","stationuuid":"4240ed04-41af-4a4c-bca4-419976cb0a67","serveruuid":"e56ba850-411b-4fa6-ab44-cc81c191d098","name":"103 The Beat","url":"https://stream.radiojar.com/01d8c449cyduv","url_resolved":"http://n08.radiojar.com/01d8c449cyduv?rj-ttl=5&rj-tok=AAABmthjLZcAXjhdl46oOpiAoA","homepage":"https://103beat.com/","favicon":"https://103beat.com/wp-content/uploads/2019/05/103thebeat-700x700.jpeg","tags":"pop","country":"The Bahamas","countrycode":"BS","iso_3166_2":"","state":"New Providence, Nassau","language":"english","languagecodes":"en","votes":21,"lastchangetime":"2025-08-09 04:41:12","lastchangetime_iso8601":"2025-08-09T04:41:12Z","codec":"MP3","bitrate":0,"hls":0,"lastcheckok":1,"lastchecktime":"2025-12-01 05:20:03","lastchecktime_iso8601":"2025-12-01T05:20:03Z","lastcheckoktime":"2025-12-01 05:20:03","lastcheckoktime_iso8601":"2025-12-01T05:20:03Z","lastlocalchecktime":"2025-12-01 05:20:03","lastlocalchecktime_iso8601":"2025-12-01T05:20:03Z","clicktimestamp":"2025-11-30 14:29:50","clicktimestamp_iso8601":"2025-11-30T14:29:50Z","clickcount":8,"clicktrend":-4,"ssl_error":0,"geo_lat":25.078447091841248,"geo_long":-77.34134674072266,"geo_distance":null,"has_extended_info":false},{"changeuuid":"7e79d7e1-fef3-4a3a-b085-264ee94b1e5b","stationuuid":"3e7a0936-43cb-4c5e-9220-948b98d11ccd","serveruuid":"db07295f-1e9c-451e-a42f-7d6d0fbaefc2","name":"96.9 FM GuardianRadio","url":"https://radiostreams.streamcomedia.com:8000/969guardianradio","url_resolved":"https://radiostreams.streamcomedia.com:8000/969guardianradio","homepage":"https://guardiantalkradio.com/","favicon":"https://guardiantalkradio.com/wp-content/themes/guardianradio/images/logo_site1.png","tags":"","country":"The Bahamas","countrycode":"BS","iso_3166_2":"","state":"Nassau","language":"","languagecodes":"","votes":84,"lastchangetime":"2025-08-08 16:03:18","lastchangetime_iso8601":"2025-08-08T16:03:18Z","codec":"MP3","bitrate":82,"hls":0,"lastcheckok":1,"lastchecktime":"2025-12-01 09:12:14","lastchecktime_iso8601":"2025-12-01T09:12:14Z","lastcheckoktime":"2025-12-01 09:12:14","lastcheckoktime_iso8601":"2025-12-01T09:12:14Z","lastlocalchecktime":"2025-12-01 00:37:11","lastlocalchecktime_iso8601":"2025-12-01T00:37:11Z","clicktimestamp":"2025-12-01 07:30:14","clicktimestamp_iso8601":"2025-12-01T07:30:14Z","clickcount":5,"clicktrend":2,"ssl_error":0,"geo_lat":null,"geo_long":null,"geo_distance":null,"has_extended_info":false},{"changeuuid":"29085f21-b93f-428e-97db-c15ef6346c9d","stationuuid":"f7dfc0b9-ffd6-4da6-903c-7284a0fd5486","serveruuid":"db07295f-1e9c-451e-a42f-7d6d0fbaefc2","name":"96.9FM GuardianRadio","url":"https://radiostreams.streamcomedia.com:8000/969guardianradio","url_resolved":"https://radiostreams.streamcomedia.com:8000/969guardianradio","homepage":"https://guardiantalkradio.com/","favicon":"https://guardiantalkradio.com/wp-content/themes/guardianradio/images/logo_site1.png","tags":"","country":"The Bahamas","countrycode":"BS","iso_3166_2":"","state":"","language":"","languagecodes":"","votes":26,"lastchangetime":"2025-08-08 16:03:19","lastchangetime_iso8601":"2025-08-08T16:03:19Z","codec":"MP3","bitrate":82,"hls":0,"lastcheckok":1,"lastchecktime":"2025-12-01 07:54:51","lastchecktime_iso8601":"2025-12-01T07:54:51Z","lastcheckoktime":"2025-12-01 07:54:51","lastcheckoktime_iso8601":"2025-12-01T07:54:51Z","lastlocalchecktime":"2025-12-01 05:45:18","lastlocalchecktime_iso8601":"2025-12-01T05:45:18Z","clicktimestamp":"2025-11-30 22:15:16","clicktimestamp_iso8601":"2025-11-30T22:15:16Z","clickcount":1,"clicktrend":1,"ssl_error":0,"geo_lat":null,"geo_long":null,"geo_distance":null,"has_extended_info":false},{"changeuuid":"c690f49d-57dd-4989-8218-9bda9d8bff5b","stationuuid":"5abe461a-3854-44b4-9067-8b116c9d80b7","serveruuid":"cb8f6669-15d6-4eb3-97d9-6deb484075a5","name":"Abdulbasit Abdulsamad","url":"https://radio.mp3islam.com/listen/abdulbasit/radio.mp3","url_resolved":"https://radio.mp3islam.com/listen/abdulbasit/radio.mp3","homepage":"https://mp3islam.com/","favicon":"null","tags":"","country":"The Bahamas","countrycode":"BS","iso_3166_2":"","state":"","language":"arabic","languagecodes":"ar","votes":16,"lastchangetime":"2025-08-08 23:31:54","lastchangetime_iso8601":"2025-08-08T23:31:54Z","codec":"MP3","bitrate":192,"hls":0,"lastcheckok":1,"lastchecktime":"2025-12-01 05:45:18","lastchecktime_iso8601":"2025-12-01T05:45:18Z","lastcheckoktime":"2025-12-01 05:45:18","lastcheckoktime_iso8601":"2025-12-01T05:45:18Z","lastlocalchecktime":"2025-12-01 05:45:18","lastlocalchecktime_iso8601":"2025-12-01T05:45:18Z","clicktimestamp":"2025-12-01 04:27:42","clicktimestamp_iso8601":"2025-12-01T04:27:42Z","clickcount":2,"clicktrend":2,"ssl_error":0,"geo_lat":null,"geo_long":null,"geo_distance":null,"has_extended_info":false},{"changeuuid":"484d8c29-9451-4013-a8c8-be1d835fa392","stationuuid":"65d7732e-7d7f-4617-beb6-a22f67d5d102","serveruuid":"655b5a4c-4bf3-4a91-a28c-266acc2d4411","name":"Bahamian or Nuttin","url":"https://s2.reliastream.com/proxy/rumcayme?mp=/stream","url_resolved":"https://s2.reliastream.com/proxy/rumcayme?mp=/stream","homepage":"https://www.bahamianornuttin.com/","favicon":"https://img1.wsimg.com/isteam/ip/3828e59f-f1ce-4e2a-8946-b8dbdfaadc31/favicon/78d0b8fe-c6cf-4ef3-a4dc-f5284754eed2.png/:/rs=w:64,h:64,m","tags":"caribbean,junkanoo","country":"The Bahamas","countrycode":"BS","iso_3166_2":"","state":"","language":"english","languagecodes":"en","votes":272,"lastchangetime":"2025-08-09 03:13:05","lastchangetime_iso8601":"2025-08-09T03:13:05Z","codec":"MP3","bitrate":128,"hls":0,"lastcheckok":1,"lastchecktime":"2025-11-30 23:20:18","lastchecktime_iso8601":"2025-11-30T23:20:18Z","lastcheckoktime":"2025-11-30 23:20:18","lastcheckoktime_iso8601":"2025-11-30T23:20:18Z","lastlocalchecktime":"2025-11-30 23:20:18","lastlocalchecktime_iso8601":"2025-11-30T23:20:18Z","clicktimestamp":"2025-12-01 07:29:52","clicktimestamp_iso8601":"2025-12-01T07:29:52Z","clickcount":6,"clicktrend":2,"ssl_error":0,"geo_lat":25.070766205882947,"geo_long":-77.35061645507814,"geo_distance":null,"has_extended_info":false},{"changeuuid":"48aa50fd-6eda-40fd-b457-2523f451d977","stationuuid":"50d40505-0930-4068-b96a-4cf5cf0444bc","serveruuid":"655b5a4c-4bf3-4a91-a28c-266acc2d4411","name":"Bahamianor Nuttin 92.5 FM","url":"https://s2.reliastream.com/proxy/rumcayme?mp=/stream","url_resolved":"https://s2.reliastream.com/proxy/rumcayme?mp=/stream","homepage":"https://www.bahamianornuttin.com/","favicon":"https://img1.wsimg.com/isteam/ip/3828e59f-f1ce-4e2a-8946-b8dbdfaadc31/favicon/78d0b8fe-c6cf-4ef3-a4dc-f5284754eed2.png/:/rs=w:64,h:64,m","tags":"caribbean,junkanoo","country":"The Bahamas","countrycode":"BS","iso_3166_2":"","state":"","language":"english","languagecodes":"en","votes":142,"lastchangetime":"2025-08-09 02:53:10","lastchangetime_iso8601":"2025-08-09T02:53:10Z","codec":"MP3","bitrate":128,"hls":0,"lastcheckok":1,"lastchecktime":"2025-12-01 09:07:13","lastchecktime_iso8601":"2025-12-01T09:07:13Z","lastcheckoktime":"2025-12-01 09:07:13","lastcheckoktime_iso8601":"2025-12-01T09:07:13Z","lastlocalchecktime":"2025-12-01 09:07:13","lastlocalchecktime_iso8601":"2025-12-01T09:07:13Z","clicktimestamp":"2025-11-30 14:04:47","clicktimestamp_iso8601":"2025-11-30T14:04:47Z","clickcount":1,"clicktrend":1,"ssl_error":0,"geo_lat":25.07138815758652,"geo_long":-77.35336303710939,"geo_distance":null,"has_extended_info":false},{"changeuuid":"abdedc71-6437-40eb-b185-13d5654e45f6","stationuuid":"a90e52ff-840e-11e8-aa66-52543be04c81","serveruuid":"2eb1582a-440e-4d2f-a5ba-1566469f8525","name":"Global 99.5 FM","url":"http://ice64.securenetsystems.net/GLOBALBS","url_resolved":"http://ice64.securenetsystems.net/GLOBALBS","homepage":"http://globalradio995fm.com/","favicon":"https://cdn-radiotime-logos.tunein.com/s206590q.png","tags":"","country":"The Bahamas","countrycode":"BS","iso_3166_2":"","state":"","language":"english","languagecodes":"en","votes":763,"lastchangetime":"2025-08-09 06:05:01","lastchangetime_iso8601":"2025-08-09T06:05:01Z","codec":"AAC+","bitrate":32,"hls":0,"lastcheckok":1,"lastchecktime":"2025-12-01 04:17:43","lastchecktime_iso8601":"2025-12-01T04:17:43Z","lastcheckoktime":"2025-12-01 04:17:43","lastcheckoktime_iso8601":"2025-12-01T04:17:43Z","lastlocalchecktime":"2025-11-30 15:03:07","lastlocalchecktime_iso8601":"2025-11-30T15:03:07Z","clicktimestamp":"2025-11-29 15:36:43","clicktimestamp_iso8601":"2025-11-29T15:36:43Z","clickcount":2,"clicktrend":-1,"ssl_error":0,"geo_lat":null,"geo_long":null,"geo_distance":null,"has_extended_info":false},{"changeuuid":"1fb011ac-0c4d-4d32-aec9-6b9847dec45a","stationuuid":"963fbb20-0601-11e8-ae97-52543be04c81","serveruuid":"ce6ff7ef-749e-4037-978c-ecc365ce1dd8","name":"LCLHST R1","url":"http://s1.radio.lclhst.net:1437/r1","url_resolved":"http://s1.radio.lclhst.net:1437/r1","homepage":"http://radio.lclhst.net/","favicon":"","tags":"electro sets,electronic,minimal,techno","country":"The Bahamas","countrycode":"BS","iso_3166_2":"","state":"","language":"english","languagecodes":"en","votes":374,"lastchangetime":"2025-08-09 02:13:05","lastchangetime_iso8601":"2025-08-09T02:13:05Z","codec":"MP3","bitrate":192,"hls":0,"lastcheckok":1,"lastchecktime":"2025-12-01 06:06:45","lastchecktime_iso8601":"2025-12-01T06:06:45Z","lastcheckoktime":"2025-12-01 06:06:45","lastcheckoktime_iso8601":"2025-12-01T06:06:45Z","lastlocalchecktime":"2025-12-01 06:06:45","lastlocalchecktime_iso8601":"2025-12-01T06:06:45Z","clicktimestamp":"2025-11-30 14:30:19","clicktimestamp_iso8601":"2025-11-30T14:30:19Z","clickcount":5,"clicktrend":0,"ssl_error":0,"geo_lat":null,"geo_long":null,"geo_distance":null,"has_extended_info":false},{"changeuuid":"5cae07b4-e959-41db-ba8f-4bc3f919b1e2","stationuuid":"963f2357-0601-11e8-ae97-52543be04c81","serveruuid":"ce6ff7ef-749e-4037-978c-ecc365ce1dd8","name":"LCLHST R2","url":"http://s1.radio.lclhst.net:1437/r2","url_resolved":"http://s1.radio.lclhst.net:1437/r2","homepage":"http://radio.lclhst.net/","favicon":"","tags":"electro sets,electronic,minimal,techno","country":"The Bahamas","countrycode":"BS","iso_3166_2":"","state":"","language":"english","languagecodes":"en","votes":350,"lastchangetime":"2025-08-08 23:55:01","lastchangetime_iso8601":"2025-08-08T23:55:01Z","codec":"MP3","bitrate":128,"hls":0,"lastcheckok":1,"lastchecktime":"2025-12-01 08:34:49","lastchecktime_iso8601":"2025-12-01T08:34:49Z","lastcheckoktime":"2025-12-01 08:34:49","lastcheckoktime_iso8601":"2025-12-01T08:34:49Z","lastlocalchecktime":"2025-12-01 08:34:49","lastlocalchecktime_iso8601":"2025-12-01T08:34:49Z","clicktimestamp":"2025-11-29 19:53:57","clicktimestamp_iso8601":"2025-11-29T19:53:57Z","clickcount":3,"clicktrend":-1,"ssl_error":0,"geo_lat":null,"geo_long":null,"geo_distance":null,"has_extended_info":false}]