[{"id":"115386","changeuuid":"e9180172-d1cf-11e8-a54a-52543be04c81","stationuuid":"e9180163-d1cf-11e8-a54a-52543be04c81","name":"Pal Doğa","url":"http://shoutcast.radyogrup.com:1040/;stream.mp3","homepage":"","favicon":"https://www.canliradyodinle.fm/wp-content/uploads/pal-doga-radyo.jpg","tags":"","country":"Tu","state":"","language":"Tur","votes":"10","negativevotes":"0","lastchangetime":"2018-10-17 07:45:53","ip":"88.253.175.172","codec":"","bitrate":"0","hls":"0","lastcheckok":"0","lastchecktime":"2019-07-01 14:29:05","lastcheckoktime":"2019-06-30 14:23:46","clicktimestamp":"2019-06-29 23:19:25","clickcount":"0","clicktrend":"0"}]