[{"id":"124824","changeuuid":"e9766116-91fa-11e9-a6c6-52543be04c81","stationuuid":"e9766102-91fa-11e9-a6c6-52543be04c81","name":"Antioch OTR","url":"http://radio.macinmind.com/listen.m3u","homepage":"https://radio.macinmind.com/","favicon":"https://radio.macinmind.com//mstile-144x144.png?v=5AAbPoMjGY","tags":"","country":"US","state":"Illinois","language":"english","votes":"5","negativevotes":"0","lastchangetime":"2019-06-18 20:57:25","ip":"98.6.40.26","codec":"MP3","bitrate":"32","hls":"0","lastcheckok":"1","lastchecktime":"2019-07-01 12:53:19","lastcheckoktime":"2019-07-01 12:53:19","clicktimestamp":"2019-07-13 02:52:39","clickcount":"0","clicktrend":"0"},{"id":"124048","changeuuid":"db95f665-805d-11e9-aa30-52543be04c81","stationuuid":"db95f657-805d-11e9-aa30-52543be04c81","name":"KOWA 106.5 FM Community Radio","url":"http://kowa.out.airtime.pro:8000/kowa_b","homepage":"http://kowalp.org/","favicon":"http://kowalp.org/favicon.ico","tags":"Low-power,non-profit,Pacific Network,Olympia, WA","country":"US","state":"Washington","language":"English","votes":"0","negativevotes":"0","lastchangetime":"2019-05-27 11:00:21","ip":"75.172.104.30","codec":"MP3","bitrate":"64","hls":"0","lastcheckok":"1","lastchecktime":"2019-07-02 09:53:41","lastcheckoktime":"2019-07-02 09:53:41","clicktimestamp":"2019-07-10 03:47:32","clickcount":"0","clicktrend":"0"},{"id":"124182","changeuuid":"8acd1f4c-8443-11e9-aa30-52543be04c81","stationuuid":"8acd1f39-8443-11e9-aa30-52543be04c81","name":"Rapid Fire Radio","url":"http://shaincast.caster.fm:40816/listen.mp3","homepage":"http://rapidfire.Caster.fm/","favicon":"http://www.caster.fm/images/user_logo/user_logo_id_339693.jpg","tags":"","country":"US","state":"SD","language":"english","votes":"1","negativevotes":"0","lastchangetime":"2019-06-01 10:02:04","ip":"64.179.187.86","codec":"","bitrate":"0","hls":"0","lastcheckok":"0","lastchecktime":"2019-07-01 11:28:00","lastcheckoktime":"2019-06-30 11:15:16","clicktimestamp":"2019-06-30 14:26:22","clickcount":"0","clicktrend":"0"}]